Workbook
Name HandleListWithPiston: '[1]#REF'!$F$11:$G$26
Name HandleListWithPiston2: '[1]#REF'!$F$11:$F$26

Sheet SELL 
A1: Sell List
A3: TEL: FAX: E:
A4: Name: | F4: Date: | K4: Phone:
A5: Fax: | F5: Address: | K5: Product Code
A6: Product | B6: Qty | C6: Price | D6: TOTAL | F6: Product | G6: Qty | H6: Price | I6: TOTAL
A7: F9-W3036 | B7: 1 | C7: =IFERROR(VLOOKUP(A7,PRICE!$A$1:$B$2601,2,FALSE),"0") -> 851 | D7: =C7*B7 -> 851 | F7: F9-DB30 | G7: 1 | H7: =IFERROR(VLOOKUP(F7,PRICE!$A$1:$B$2601,2,FALSE),"0") -> 1490 | I7: =H7*G7 -> 1490
A8: F9-W4236 | B8: 1 | C8: =IFERROR(VLOOKUP(A8,PRICE!$A$1:$B$2601,2,FALSE),"0") -> 1200 | D8: =C8*B8 -> 1200 | F8: F9-DB24 | G8: 1 | H8: =IFERROR(VLOOKUP(F8,PRICE!$A$1:$B$2601,2,FALSE),"0") -> 1346 | I8: =H8*G8 -> 1346
A9: F9-WEP1336 | B9: 4 | C9: =IFERROR(VLOOKUP(A9,PRICE!$A$1:$B$2601,2,FALSE),"0") -> 51 | D9: =C9*B9 -> 204 | F9: F9-FB36 | G9: 1 | H9: =IFERROR(VLOOKUP(F9,PRICE!$A$1:$B$2601,2,FALSE),"0") -> 1046 | I9: =H9*G9 -> 1046
A10: F9-WF396 | B10: 3 | C10: =IFERROR(VLOOKUP(A10,PRICE!$A$1:$B$2601,2,FALSE),"0") -> 133 | D10: =C10*B10 -> 399 | G10: 1 | H10: =IFERROR(VLOOKUP(F10,PRICE!$A$1:$B$2601,2,FALSE),"0") -> 0 | I10: =H10*G10 -> 0 | K10: Instructions
A11: F9-WF1.596 | B11: 2 | C11: =IFERROR(VLOOKUP(A11,PRICE!$A$1:$B$2601,2,FALSE),"0") -> 83 | D11: =C11*B11 -> 166 | F11: F9-B18-PO | G11: 1 | H11: =IFERROR(VLOOKUP(F11,PRICE!$A$1:$B$2601,2,FALSE),"0") -> 1060 | I11: =H11*G11 -> 1060 | K11: 1. Select product from drop-down menu of column 1 and 2
B12: 1 | C12: =IFERROR(VLOOKUP(A12,PRICE!$A$1:$B$2601,2,FALSE),"0") -> 0 | D12: =C12*B12 -> 0 | F12: F9-Garbage Bin | G12: 2 | H12: =IFERROR(VLOOKUP(F12,PRICE!$A$1:$B$2601,2,FALSE),"0") -> 37 | I12: =H12*G12 -> 74
B13: 1 | C13: =IFERROR(VLOOKUP(A13,PRICE!$A$1:$B$2601,2,FALSE),"0") -> 0 | D13: =C13*B13 -> 0 | F13: F9-DB36 | G13: 1 | H13: =IFERROR(VLOOKUP(F13,PRICE!$A$1:$B$2601,2,FALSE),"0") -> 1620 | I13: =H13*G13 -> 1620 | K13: 2. Enter quantity
B14: 1 | C14: =IFERROR(VLOOKUP(A14,PRICE!$A$1:$B$2601,2,FALSE),"0") -> 0 | D14: =C14*B14 -> 0 | F14: F9-FB42 | G14: 1 | H14: =IFERROR(VLOOKUP(F14,PRICE!$A$1:$B$2601,2,FALSE),"0") -> 1140 | I14: =H14*G14 -> 1140 | K14: 3. Enter discount rate at the bottom
B15: 1 | C15: =IFERROR(VLOOKUP(A15,PRICE!$A$1:$B$2601,2,FALSE),"0") -> 0 | D15: =C15*B15 -> 0 | F15: F9-W3330 | G15: 2 | H15: =IFERROR(VLOOKUP(F15,PRICE!$A$1:$B$2601,2,FALSE),"0") -> 794 | I15: =H15*G15 -> 1588 | K15: 4. Enter tax rate at the bottom
B16: 5 | C16: =IFERROR(VLOOKUP(A16,PRICE!$A$1:$B$2601,2,FALSE),"0") -> 0 | D16: =C16*B16 -> 0 | F16: F9-W3030 | G16: 1 | H16: =IFERROR(VLOOKUP(F16,PRICE!$A$1:$B$2601,2,FALSE),"0") -> 727 | I16: =H16*G16 -> 727 | K16: *Please refer to "Price List & Description" tab at bottom for details
B17: 2 | C17: =IFERROR(VLOOKUP(A17,PRICE!$A$1:$B$2601,2,FALSE),"0") -> 0 | D17: =C17*B17 -> 0 | F17: F9-ISP37.75X36 | G17: 2 | H17: =IFERROR(VLOOKUP(F17,PRICE!$A$1:$B$2601,2,FALSE),"0") -> 175 | I17: =H17*G17 -> 350
B18: 2 | C18: =IFERROR(VLOOKUP(A18,PRICE!$A$1:$B$2601,2,FALSE),"0") -> 0 | D18: =C18*B18 -> 0 | F18: F9-TK8 | G18: 4 | H18: =IFERROR(VLOOKUP(F18,PRICE!$A$1:$B$2601,2,FALSE),"0") -> 47 | I18: =H18*G18 -> 188
B19: 3 | C19: =IFERROR(VLOOKUP(A19,PRICE!$A$1:$B$2601,2,FALSE),"0") -> 0 | D19: =C19*B19 -> 0 | F19: F9-WF330 | G19: 3 | H19: =IFERROR(VLOOKUP(F19,PRICE!$A$1:$B$2601,2,FALSE),"0") -> 47 | I19: =H19*G19 -> 141
B20: 1 | C20: =IFERROR(VLOOKUP(A20,PRICE!$A$1:$B$2601,2,FALSE),"0") -> 0 | D20: =C20*B20 -> 0 | G20: 4 | H20: =IFERROR(VLOOKUP(F20,PRICE!$A$1:$B$2601,2,FALSE),"0") -> 0 | I20: =H20*G20 -> 0
B21: 3 | C21: =IFERROR(VLOOKUP(A21,PRICE!$A$1:$B$2601,2,FALSE),"0") -> 0 | D21: =C21*B21 -> 0 | H21: =IFERROR(VLOOKUP(F21,PRICE!$A$1:$B$2601,2,FALSE),"0") -> 0 | I21: =H21*G21 -> 0 | K21: Assembly Cost
C22: =IFERROR(VLOOKUP(A22,PRICE!$A$1:$B$2601,2,FALSE),"0") -> 0 | D22: =C22*B22 -> 0 | H22: =IFERROR(VLOOKUP(F22,PRICE!$A$1:$B$2601,2,FALSE),"0") -> 0 | I22: =H22*G22 -> 0
C23: =IFERROR(VLOOKUP(A23,PRICE!$A$1:$B$2601,2,FALSE),"0") -> 0 | D23: =C23*B23 -> 0 | H23: =IFERROR(VLOOKUP(F23,PRICE!$A$1:$B$2601,2,FALSE),"0") -> 0 | I23: =H23*G23 -> 0 | K23: Assembly Type | L23: Quantity | M23: per unit
C24: =IFERROR(VLOOKUP(A24,PRICE!$A$1:$B$2601,2,FALSE),"0") -> 0 | D24: =C24*B24 -> 0 | H24: =IFERROR(VLOOKUP(F24,PRICE!$A$1:$B$2601,2,FALSE),"0") -> 0 | I24: =H24*G24 -> 0 | K24: Base Units | L24: 6 | M24: 50
C25: =IFERROR(VLOOKUP(A25,PRICE!$A$1:$B$2601,2,FALSE),"0") -> 0 | D25: =C25*B25 -> 0 | H25: =IFERROR(VLOOKUP(F25,PRICE!$A$1:$B$2601,2,FALSE),"0") -> 0 | I25: =H25*G25 -> 0 | K25: Wall Units | L25: 5 | M25: 25
C26: =IFERROR(VLOOKUP(A26,PRICE!$A$1:$B$2601,2,FALSE),"0") -> 0 | D26: =C26*B26 -> 0 | H26: =IFERROR(VLOOKUP(F26,PRICE!$A$1:$B$2601,2,FALSE),"0") -> 0 | I26: =H26*G26 -> 0 | K26: Tall Panty, Lazy Susan, Mantle and 48"-60" Vanity units | M26: 100
C27: =IFERROR(VLOOKUP(A27,PRICE!$A$1:$B$2601,2,FALSE),"0") -> 0 | D27: =C27*B27 -> 0 | H27: =IFERROR(VLOOKUP(F27,PRICE!$A$1:$B$2601,2,FALSE),"0") -> 0 | I27: =H27*G27 -> 0
C28: =IFERROR(VLOOKUP(A28,PRICE!$A$1:$B$2601,2,FALSE),"0") -> 0 | D28: =C28*B28 -> 0 | H28: =IFERROR(VLOOKUP(F28,PRICE!$A$1:$B$2601,2,FALSE),"0") -> 0 | I28: =H28*G28 -> 0 | K28: Custom Assembly Costs:
C29: =IFERROR(VLOOKUP(A29,PRICE!$A$1:$B$2601,2,FALSE),"0") -> 0 | D29: =C29*B29 -> 0 | H29: =IFERROR(VLOOKUP(F29,PRICE!$A$1:$B$2601,2,FALSE),"0") -> 0 | I29: =H29*G29 -> 0 | K29: Delivery Costs:
A30: handles | B30: Qty | C30: Price | D30: TOTAL | F30: Custom items | G30: Qty | H30: Price | I30: TOTAL | K30: Total Cost: | L30: =(L24*M24)+(L25*M25)+(L26*M26)+L28+L29 -> 425
D31: =C31*B31 -> 0
D32: =C32*B32 -> 0
D33: =C33*B33 -> 0
D34: =C34*B34 -> 0
D35: =C35*B35 -> 0 | I35: =H35*G35 -> 0
A36: List Total: | C36: =SUM(D7:D29)+SUM(I7:I29) -> 13590 | F36: Discount Rate: | H36: 0.76 | K36: After Disc: | M36: =(C36+M30)*(1-H36) -> 3261.6
A37: Assembly Cost: | C37: =L30 -> 425 | F37: Subtotal: | H37: =M36+C37+SUM(D31:D35)+SUM(I31:I35) -> 3686.6 | K37: QST+GST (%): | L37: 0.09975 | M37: 0.05
A38: GST: | B38: =H37*M37 -> 184.33 | C38: QST: | D38: =H37*L37 -> 367.73835 | F38: TOTAL GST+QST | H38: =D38+B38 -> 552.06835 | K38: Total: | M38: =H37+H38 -> 4238.6683

Sheet PRICE
A1: 型号 | B1: 零售价
A2: MUF9-B12 | B2: 810 | C2: F9-B12 | D2: 742 | E2: =B2-D2 -> 68 | F2: =E2/B2 -> 0.083950617
A3: MUF9-B15 | B3: 900 | C3: F9-B15 | D3: 822 | E3: =B3-D3 -> 78 | F3: =E3/B3 -> 0.086666667 | I3: muf9
A4: MUF9-B18 | B4: 970 | C4: F9-B18 | D4: 883 | E4: =B4-D4 -> 87 | F4: =E4/B4 -> 0.089690722 | I4: 1pouce shaker
A5: MUF9-B18-PO | B5: 1171 | C5: F9-B18-PO | D5: 1060 | E5: =B5-D5 -> 111 | F5: =E5/B5 -> 0.094790777
A6: MUF9-B21 | B6: 1017 | C6: F9-B21 | D6: 925 | E6: =B6-D6 -> 92 | F6: =E6/B6 -> 0.090462144
A7: MUF9-BBC42 | B7: 1336 | C7: F9-BBC42 | D7: 1203 | E7: =B7-D7 -> 133 | F7: =E7/B7 -> 0.099550898 | I7: f8
A8: MUF9-BBC45 | B8: 1457 | C8: F9-BBC45 | D8: 1303 | E8: =B8-D8 -> 154 | F8: =E8/B8 -> 0.10569664
A9: MUF9-BBC48 | B9: 1569 | C9: F9-BBC48 | D9: 1404 | E9: =B9-D9 -> 165 | F9: =E9/B9 -> 0.10516252
A10: MUF9-BMC27 | B10: 1393 | C10: F9-BMC27 | D10: 1241 | E10: =B10-D10 -> 152 | F10: =E10/B10 -> 0.10911701
A11: MUF9-DB12 | B11: 1153 | C11: F9-DB12 | D11: 1059 | E11: =B11-D11 -> 94 | F11: =E11/B11 -> 0.081526453
A12: MUF9-DB15 | B12: 1273 | C12: F9-DB15 | D12: 1157 | E12: =B12-D12 -> 116 | F12: =E12/B12 -> 0.091123331
A13: MUF9-DB18 | B13: 1364 | C13: F9-DB18 | D13: 1202 | E13: =B13-D13 -> 162 | F13: =E13/B13 -> 0.11876833
A14: MUF9-DB21 | B14: 1467 | C14: F9-DB21 | D14: 1306 | E14: =B14-D14 -> 161 | F14: =E14/B14 -> 0.10974778
A15: MUF9-DB24 | B15: 1509 | C15: F9-DB24 | D15: 1346 | E15: =B15-D15 -> 163 | F15: =E15/B15 -> 0.10801856
A16: MUF9-DB27 | B16: 1597 | C16: F9-DB27 | D16: 1419 | E16: =B16-D16 -> 178 | F16: =E16/B16 -> 0.11145899
A17: MUF9-DB30 | B17: 1669 | C17: F9-DB30 | D17: 1490 | E17: =B17-D17 -> 179 | F17: =E17/B17 -> 0.10724985
A18: MUF9-DB33 | B18: 1754 | C18: F9-DB33 | D18: 1552 | E18: =B18-D18 -> 202 | F18: =E18/B18 -> 0.11516534
A19: MUF9-DB36 | B19: 1854 | C19: F9-DB36 | D19: 1620 | E19: =B19-D19 -> 234 | F19: =E19/B19 -> 0.12621359
A20: MUF9-DB12-2 | B20: 865
A21: MUF9-DB15-2 | B21: 944
A22: MUF9-DB18-2 | B22: 1030
A23: MUF9-DB21-2 | B23: 1139
A24: MUF9-DB24-2 | B24: 1239
A25: MUF9-DB27-2 | B25: 1328 | C25: F9-DB27-2 | D25: 1122 | E25: =B25-D25 -> 206 | F25: =E25/B25 -> 0.15512048
A26: MUF9-DB30-2 | B26: 1419 | C26: F9-DB30-2 | D26: 1211 | E26: =B26-D26 -> 208 | F26: =E26/B26 -> 0.1465821
A27: MUF9-DB33-2 | B27: 1519
A28: MUF9-DB36-2 | B28: 1621
A29: MUF9-FB09 | B29: 535 | C29: F9-FB09 | D29: 492 | E29: =B29-D29 -> 43 | F29: =E29/B29 -> 0.080373832
A30: MUF9-FB12 | B30: 598 | C30: F9-FB12 | D30: 545 | E30: =B30-D30 -> 53 | F30: =E30/B30 -> 0.088628763
A31: MUF9-FB15 | B31: 676 | C31: F9-FB15 | D31: 616 | E31: =B31-D31 -> 60 | F31: =E31/B31 -> 0.088757396
A32: MUF9-FB18 | B32: 740 | C32: F9-FB18 | D32: 670 | E32: =B32-D32 -> 70 | F32: =E32/B32 -> 0.094594595
A33: MUF9-FB21 | B33: 818 | C33: F9-FB21 | D33: 732 | E33: =B33-D33 -> 86 | F33: =E33/B33 -> 0.10513447
A34: MUF9-FB24 | B34: 911 | C34: F9-FB24 | D34: 817 | E34: =B34-D34 -> 94 | F34: =E34/B34 -> 0.10318332
A35: MUF9-FB27 | B35: 982 | C35: F9-FB27 | D35: 875 | E35: =B35-D35 -> 107 | F35: =E35/B35 -> 0.1089613
A36: MUF9-FB30 | B36: 1051 | C36: F9-FB30 | D36: 937 | E36: =B36-D36 -> 114 | F36: =E36/B36 -> 0.10846813
A37: MUF9-FB33 | B37: 1110 | C37: F9-FB33 | D37: 991 | E37: =B37-D37 -> 119 | F37: =E37/B37 -> 0.10720721
A38: MUF9-FB36 | B38: 1187 | C38: F9-FB36 | D38: 1046 | E38: =B38-D38 -> 141 | F38: =E38/B38 -> 0.11878686
A39: MUF9-FB39 | B39: 1266 | C39: F9-FB39 | D39: 1109 | E39: =B39-D39 -> 157 | F39: =E39/B39 -> 0.12401264
A40: MUF9-FB42 | B40: 1301 | C40: F9-FB42 | D40: 1140 | E40: =B40-D40 -> 161 | F40: =E40/B40 -> 0.12375096
A41: MUF9-FSB33*19.75(10-1/8) | B41: 992 | C41: F9-LS3309 | D41: 1383
A42: MUF9-FSB36*19.75(10-1/8) | B42: 1070 | C42: F9-LS3612 | D42: 1478
A43: MUF9-IBP9636 | B43: 521 | C43: F9-OC-DB30 DRAWER | D43: 447
A44: MUF9-LS3309 | B44: 1459 | C44: F9-OCM8 | D44: 54
A45: MUF9-LS3612 | B45: 1577 | C45: F9-DWR | D45: 168
A46: MUF9-OCM8 | B46: 76 | C46: F9-RRP103.527 3/4 | D46: 482
A47: MUF9-DWR | B47: 250 | C47: F9-SM1.5 | D47: 51
A48: MUF9-SP09 | B48: 652 | C48: F9-SM1.5X120 | D48: 79
A49: MUF9-SP12 | B49: 706 | C49: F9-BM96 | D49: 276
A50: MUF9-TK8 | B50: 74 | C50: F9-TK8 | D50: 47 | E50: =B50-D50 -> 27 | F50: =E50/B50 -> 0.36486486
A51: MUF9-VS2421 | B51: 881 | C51: F9-SP06 | D51: 554
A52: MUF9-VS3021 | B52: 1014 | C52: F9-SP09 | D52: 611
A53: MUF9-VDB1221 | B53: 1098 | C53: F9-SP12 | D53: 660
A54: MUF9-VDB1521 | B54: 1202 | C54: F9-TK8 | D54: 47
A55: MUF9-VDB1821 | B55: 1253 | C55: F9-VS2421 | D55: 798
A56: MUF9-W0930 | B56: 388 | C56: F9-VS3021 | D56: 910
A57: MUF9-W1230 | B57: 440 | C57: F9-VDB1221 | D57: 1013
A58: MUF9-W1530 | B58: 503 | C58: F9-VDB1521 | D58: 1098
A59: MUF9-W1830 | B59: 564 | C59: F9-VDB1821 | D59: 1141
A60: MUF9-W2130 | B60: 628 | C60: F9-W0930 | D60: 347 | E60: =B56-D60 -> 41 | F60: =E60/B60 -> 0.065286624
A61: MUF9-W2430 | B61: 720 | C61: F9-W0936 | D61: 397
A62: MUF9-W2730 | B62: 797 | C62: F9-W1230 | D62: 394 | E62: =B57-D62 -> 46 | F62: =E62/B62 -> 0.057716437
A63: MUF9-W3018 | B63: 526 | C63: F9-W1236 | D63: 450
A64: MUF9-W3030 | B64: 854 | C64: F9-W1248 | D64: 749
A65: MUF9-W30X19.5 | B65: 575 | C65: F9-W1530 | D65: 450
A66: MUF9-W33X19.5 | B66: 622 | C66: F9-W1536 | D66: 519
A67: MUF9-W36X19.5 | B67: 707 | C67: F9-W1548 | D67: 900
A68: MUF9-W3020 | B68: 349 | C68: F9-W1830 | D68: 499
A69: MUF9-W3320 | B69: 379 | C69: F9-W1836 | D69: 567
A70: MUF9-W3620 | B70: 414 | C70: F9-W1848 | D70: 996
A71: MUF9-W3318 | B71: 592 | C71: F9-W2130 | D71: 562
A72: MUF9-W3330 | B72: 907 | C72: F9-W2136 | D72: 628
A73: MUF9-W3618 | B73: 634 | C73: F9-W2148 | D73: 1092
A74: MUF9-W3630 | B74: 954 | C74: F9-W2430 | D74: 634
... A77: MUF9-WDC2430 | B77: 942 | C77: F9-W2730 | D77: 687
A78: MUF9-WF330 | B78: 69 | C78: F9-WF330 | D78: 47 | E78: =B78-D78 -> 22 | F78: =E78/B78 -> 0.31884058
A79: MUF9-WF336 | B79: 75 | C79: F9-WF336 | D79: 51 | E79: =B79-D79 -> 24 | F79: =E79/B79 -> 0.32
A80: MUF9-WF342 | B80: 140 | C80: F9-WF342 | D80: 96 | E80: =B80-D80 -> 44 | F80: =E80/B80 -> 0.31428571
A81: MUF9-WF348 | B81: 170 | C81: F9-WF348 | D81: 115 | E81: =B81-D81 -> 55 | F81: =E81/B81 -> 0.32352941
A82: MUF9-WF396 | B82: 197 | C82: F9-WF396 | D82: 133 | E82: =B82-D82 -> 64 | F82: =E82/B82 -> 0.3248731
A83: MUF9-WF3X120 | B83: 270 | C83: F9-WF3X120 | D83: 182 | E83: =B83-D83 -> 88 | F83: =E83/B83 -> 0.32592593
A84: MUF9-WF636 | B84: 145 | C84: F9-WF636 | D84: 98 | E84: =B84-D84 -> 47 | F84: =E84/B84 -> 0.32413793
A85: MUF9-WF696 | B85: 413 | C85: F9-WF696 | D85: 278 | E85: =B85-D85 -> 135 | F85: =E85/B85 -> 0.32687651
A86: MUF9-WF6X120 | B86: 496 | C86: F9-WF6X120 | D86: 339 | E86: =B86-D86 -> 157 | F86: =E86/B86 -> 0.31653226
A87: MUF9-WF6*126 | B87: 515 | C87: F9-WF6*126 | D87: 357 | E87: =B87-D87 -> 158 | F87: =E87/B87 -> 0.30679612
A88: MUF9-WF1.596 | B88: 122 | C88: F9-WF1.596 | D88: 83 | E88: =B88-D88 -> 39 | F88: =E88/B88 -> 0.31967213
A89: MUF9-WF1.5120 | B89: 167 | C89: F9-WF1.5120 | D89: 114 | E89: =B89-D89 -> 53 | F89: =E89/B89 -> 0.31736527
A90: MUF9-BDD12.75*36 | B90: 193 | C90: F9-BDD12.75*36 | D90: 150 | E90: =B90-D90 -> 43 | F90: =E90/B90 -> 0.22279793
A91: MUF9-BDD21.75*36 | B91: 307 | C91: F9-BDD21.75*36 | D91: 238
A92: MUF9-BDD24.75*36 | B92: 335 | C92: F9-BDD24.75*36 | D92: 250
A93: MUF9-BDD25.75*36 | B93: 340 | C93: F9-BDD25.75*36 | D93: 256
A94: MUF9-BDD37.5x36 | B94: 506 | C94: F9-BDD37.5x36 | D94: 365
A95: MUF9-BDD49.75*36 | B95: 716 | C95: F9-BDD49.75*36 | D95: 535
A96: MUF9-BDD2430 | B96: 254 | C96: F9-BDD2430 | D96: 192
A97: MUF9-BDD2730 | B97: 288 | C97: F9-BDD2730 | D97: 223
A98: MUF9-BDD3030 | B98: 335 | C98: F9-BDD3030 | D98: 257
A99: MUF9-BDD3330 | B99: 386 | C99: F9-BDD3330 | D99: 290
A100: MUF9-ROD15 | B100: 101 | C100: F9-W3318 | D100: 521
A101: MUF9-ROD18 | B101: 115 | C101: F9-W3330 | D101: 794
A102: MUF9-ROD21 | B102: 130 | C102: F9-W3336 | D102: 914
...

Sheet price bc
A1: Product Code Yihai | B1: Price Yihai | C1: Price Dilamco - Standard | D1: Price Dilamco - Chene Blanc | E1: Product | F1: Product Type | G1: Product Sub-type | H1: Part Type | I1: Certain? Catégorie | J1: Certain Item | K1: Width | L1: Height | M1: Depth | N1: Door | O1: Drawer
A2: F9-Garbage Bin | B2: 37 | C2: =B2*0.3 -> 11.1 | E2: =_xlfn.TEXTAFTER(A2,"-") -> Garbage Bin | F2: {=_xlfn.LET( _xlpm.p,E2, _xlpm.code,IFERROR( IF(AND(LEFT(_xlpm.p,2)="DB",ISNUMBER(SEARCH("-2",_xlpm.p))),"DB-2", IF(LEFT(_xlpm.p,3)="OC-","OC", LEFT(_xlpm.p,_xlfn.XMATCH(TRUE,ISNUMBER(--MID(_xlpm.p,_xlfn.SEQUENCE(LEN(_xlpm.p)),1)))-1) ) ), _xlpm.p ), _xlfn.XLOOKUP(_xlpm.code,'Product Code'!A:A,'Product Code'!B:B,"") )} -> Accessories | G2: {=_xlfn.LET( _xlpm.p,E2, _xlpm.code,IFERROR( IF(AND(LEFT(_xlpm.p,2)="DB",ISNUMBER(SEARCH("-2",_xlpm.p))),"DB-2", IF(LEFT(_xlpm.p,3)="OC-","OC", LEFT(_xlpm.p,_xlfn.XMATCH(TRUE,ISNUMBER(--MID(_xlpm.p,_xlfn.SEQUENCE(LEN(_xlpm.p)),1)))-1) ) ), _xlpm.p ), _xlpm.base,_xlfn.XLOOKUP(_xlpm.code,'Product Code'!A:A,'Product Code'!C:C,""), IF(RIGHT(_xlpm.p,3)="-PO",_xlpm.base&" - Pull-Out",_xlpm.base) )} -> Plastic Garbage Bin | H2: N/A | I2: {=_xlfn.LET( _xlpm.p,E2, _xlpm.code,IFERROR( IF(AND(LEFT(_xlpm.p,2)="DB",ISNUMBER(SEARCH("-2",_xlpm.p))),"DB-2", IF(LEFT(_xlpm.p,3)="OC-","OC", LEFT(_xlpm.p,_xlfn.XMATCH(TRUE,ISNUMBER(--MID(_xlpm.p,_xlfn.SEQUENCE(LEN(_xlpm.p)),1)))-1) ) ), _xlpm.p ), _xlpm.productType,_xlfn.XLOOKUP(_xlpm.code,'Product Code'!A:A,'Product Code'!D:D,""), IF(OR(RIGHT(_xlpm.p,5)="-Door",RIGHT(_xlpm.p,6)="-DOORS"),_xlpm.productType&" - Door",_xlpm.productType) )} -> 0 | K2: N/A | L2: N/A | M2: N/A | N2: 1 | O2: 1
A3: F9-美式铰链 | B3: 10 | C3: =B3*0.3 -> 3 | E3: =_xlfn.TEXTAFTER(A3,"-") -> 美式铰链 | F3: {=_xlfn.LET( _xlpm.p,E3, _xlpm.code,IFERROR( IF(AND(LEFT(_xlpm.p,2)="DB",ISNUMBER(SEARCH("-2",_xlpm.p))),"DB-2", IF(LEFT(_xlpm.p,3)="OC-","OC", LEFT(_xlpm.p,_xlfn.XMATCH(TRUE,ISNUMBER(--MID(_xlpm.p,_xlfn.SEQUENCE(LEN(_xlpm.p)),1)))-1) ) ), _xlpm.p ), _xlfn.XLOOKUP(_xlpm.code,'Product Code'!A:A,'Product Code'!B:B,"") )} -> American Style Hinge | G3: {=_xlfn.LET( _xlpm.p,E3, _xlpm.code,IFERROR( IF(AND(LEFT(_xlpm.p,2)="DB",ISNUMBER(SEARCH("-2",_xlpm.p))),"DB-2", IF(LEFT(_xlpm.p,3)="OC-","OC", LEFT(_xlpm.p,_xlfn.XMATCH(TRUE,ISNUMBER(--MID(_xlpm.p,_xlfn.SEQUENCE(LEN(_xlpm.p)),1)))-1) ) ), _xlpm.p ), _xlpm.base,_xlfn.XLOOKUP(_xlpm.code,'Product Code'!A:A,'Product Code'!C:C,""), IF(RIGHT(_xlpm.p,3)="-PO",_xlpm.base&" - Pull-Out",_xlpm.base) )} -> 0 | I3: {=_xlfn.LET( _xlpm.p,E3, _xlpm.code,IFERROR( IF(AND(LEFT(_xlpm.p,2)="DB",ISNUMBER(SEARCH("-2",_xlpm.p))),"DB-2", IF(LEFT(_xlpm.p,3)="OC-","OC", LEFT(_xlpm.p,_xlfn.XMATCH(TRUE,ISNUMBER(--MID(_xlpm.p,_xlfn.SEQUENCE(LEN(_xlpm.p)),1)))-1) ) ), _xlpm.p ), _xlpm.productType,_xlfn.XLOOKUP(_xlpm.code,'Product Code'!A:A,'Product Code'!D:D,""), IF(OR(RIGHT(_xlpm.p,5)="-Door",RIGHT(_xlpm.p,6)="-DOORS"),_xlpm.productType&" - Door",_xlpm.productType) )} -> - | N3: 1 | O3: 1
A4: F9-B12 | B4: 742 | C4: =B4*0.3 -> 222.6 | D4: =C4*1.13 -> 251.538 | E4: =_xlfn.TEXTAFTER(A4,"-") -> B12 | F4: {=_xlfn.LET( _xlpm.p,E4, _xlpm.code,IFERROR( IF(AND(LEFT(_xlpm.p,2)="DB",ISNUMBER(SEARCH("-2",_xlpm.p))),"DB-2", IF(LEFT(_xlpm.p,3)="OC-","OC", LEFT(_xlpm.p,_xlfn.XMATCH(TRUE,ISNUMBER(--MID(_xlpm.p,_xlfn.SEQUENCE(LEN(_xlpm.p)),1)))-1) ) ), _xlpm.p ), _xlpm.productType,_xlfn.XLOOKUP(_xlpm.code,'Product Code'!A:A,'Product Code'!B:B,""), IF(OR(RIGHT(_xlpm.p,5)="-Door",RIGHT(_xlpm.p,6)="-DOORS"),_xlpm.productType&" - Door",_xlpm.productType) )} -> Base Cabinet | G4: {=_xlfn.LET( _xlpm.p,E4, _xlpm.code,IFERROR( IF(AND(LEFT(_xlpm.p,2)="DB",ISNUMBER(SEARCH("-2",_xlpm.p))),"DB-2", IF(LEFT(_xlpm.p,3)="OC-","OC", LEFT(_xlpm.p,_xlfn.XMATCH(TRUE,ISNUMBER(--MID(_xlpm.p,_xlfn.SEQUENCE(LEN(_xlpm.p)),1)))-1) ) ), _xlpm.p ), _xlpm.base,_xlfn.XLOOKUP(_xlpm.code,'Product Code'!A:A,'Product Code'!C:C,""), IF(RIGHT(_xlpm.p,3)="-PO",_xlpm.base&" - Pull-Out",_xlpm.base) )} -> Standard | H4: Complete Cabinet | I4: {=_xlfn.LET( _xlpm.p,E4, _xlpm.code,IFERROR( IF(AND(LEFT(_xlpm.p,2)="DB",ISNUMBER(SEARCH("-2",_xlpm.p))),"DB-2", IF(LEFT(_xlpm.p,3)="OC-","OC", LEFT(_xlpm.p,_xlfn.XMATCH(TRUE,ISNUMBER(--MID(_xlpm.p,_xlfn.SEQUENCE(LEN(_xlpm.p)),1)))-1) ) ), _xlpm.p ), _xlpm.productType,_xlfn.XLOOKUP(_xlpm.code,'Product Code'!A:A,'Product Code'!D:D,""), IF(OR(RIGHT(_xlpm.p,5)="-Door",RIGHT(_xlpm.p,6)="-DOORS"),_xlpm.productType&" - Door",_xlpm.productType) )} -> x | J4: x | K4: 12 | L4: 34.5 | M4: 24 | N4: 1 | O4: 1
A5: F9-B15 | B5: 822 | C5: =B5*0.3 -> 246.6 | D5: =C5*1.13 -> 278.658 | E5: =_xlfn.TEXTAFTER(A5,"-") -> B15 | F5: {=_xlfn.LET( _xlpm.p,E5, _xlpm.code,IFERROR( IF(AND(LEFT(_xlpm.p,2)="DB",ISNUMBER(SEARCH("-2",_xlpm.p))),"DB-2", IF(LEFT(_xlpm.p,3)="OC-","OC", LEFT(_xlpm.p,_xlfn.XMATCH(TRUE,ISNUMBER(--MID(_xlpm.p,_xlfn.SEQUENCE(LEN(_xlpm.p)),1)))-1) ) ), _xlpm.p ), _xlpm.productType,_xlfn.XLOOKUP(_xlpm.code,'Product Code'!A:A,'Product Code'!B:B,""), IF(OR(RIGHT(_xlpm.p,5)="-Door",RIGHT(_xlpm.p,6)="-DOORS"),_xlpm.productType&" - Door",_xlpm.productType) )} -> Base Cabinet | G5: {=_xlfn.LET( _xlpm.p,E5, _xlpm.code,IFERROR( IF(AND(LEFT(_xlpm.p,2)="DB",ISNUMBER(SEARCH("-2",_xlpm.p))),"DB-2", IF(LEFT(_xlpm.p,3)="OC-","OC", LEFT(_xlpm.p,_xlfn.XMATCH(TRUE,ISNUMBER(--MID(_xlpm.p,_xlfn.SEQUENCE(LEN(_xlpm.p)),1)))-1) ) ), _xlpm.p ), _xlpm.base,_xlfn.XLOOKUP(_xlpm.code,'Product Code'!A:A,'Product Code'!C:C,""), IF(RIGHT(_xlpm.p,3)="-PO",_xlpm.base&" - Pull-Out",_xlpm.base) )} -> Standard | H5: Complete Cabinet | I5: {=_xlfn.LET( _xlpm.p,E5, _xlpm.code,IFERROR( IF(AND(LEFT(_xlpm.p,2)="DB",ISNUMBER(SEARCH("-2",_xlpm.p))),"DB-2", IF(LEFT(_xlpm.p,3)="OC-","OC", LEFT(_xlpm.p,_xlfn.XMATCH(TRUE,ISNUMBER(--MID(_xlpm.p,_xlfn.SEQUENCE(LEN(_xlpm.p)),1)))-1) ) ), _xlpm.p ), _xlpm.productType,_xlfn.XLOOKUP(_xlpm.code,'Product Code'!A:A,'Product Code'!D:D,""), IF(OR(RIGHT(_xlpm.p,5)="-Door",RIGHT(_xlpm.p,6)="-DOORS"),_xlpm.productType&" - Door",_xlpm.productType) )} -> x | J5: x | K5: 15 | L5: 34.5 | M5: 24 | N5: 0 | O5: 1
A6: F9-B18 | B6: 883 | C6: =B6*0.3 -> 264.9 | D6: =C6*1.13 -> 299.337 | E6: =_xlfn.TEXTAFTER(A6,"-") -> B18 | F6: {=_xlfn.LET( _xlpm.p,E6, _xlpm.code,IFERROR( IF(AND(LEFT(_xlpm.p,2)="DB",ISNUMBER(SEARCH("-2",_xlpm.p))),"DB-2", IF(LEFT(_xlpm.p,3)="OC-","OC", LEFT(_xlpm.p,_xlfn.XMATCH(TRUE,ISNUMBER(--MID(_xlpm.p,_xlfn.SEQUENCE(LEN(_xlpm.p)),1)))-1) ) ), _xlpm.p ), _xlpm.productType,_xlfn.XLOOKUP(_xlpm.code,'Product Code'!A:A,'Product Code'!B:B,""), IF(OR(RIGHT(_xlpm.p,5)="-Door",RIGHT(_xlpm.p,6)="-DOORS"),_xlpm.productType&" - Door",_xlpm.productType) )} -> Base Cabinet | G6: {=_xlfn.LET( _xlpm.p,E6, _xlpm.code,IFERROR( IF(AND(LEFT(_xlpm.p,2)="DB",ISNUMBER(SEARCH("-2",_xlpm.p))),"DB-2", IF(LEFT(_xlpm.p,3)="OC-","OC", LEFT(_xlpm.p,_xlfn.XMATCH(TRUE,ISNUMBER(--MID(_xlpm.p,_xlfn.SEQUENCE(LEN(_xlpm.p)),1)))-1) ) ), _xlpm.p ), _xlpm.base,_xlfn.XLOOKUP(_xlpm.code,'Product Code'!A:A,'Product Code'!C:C,""), IF(RIGHT(_xlpm.p,3)="-PO",_xlpm.base&" - Pull-Out",_xlpm.base) )} -> Standard | H6: Complete Cabinet | I6: {=_xlfn.LET( _xlpm.p,E6, _xlpm.code,IFERROR( IF(AND(LEFT(_xlpm.p,2)="DB",ISNUMBER(SEARCH("-2",_xlpm.p))),"DB-2", IF(LEFT(_xlpm.p,3)="OC-","OC", LEFT(_xlpm.p,_xlfn.XMATCH(TRUE,ISNUMBER(--MID(_xlpm.p,_xlfn.SEQUENCE(LEN(_xlpm.p)),1)))-1) ) ), _xlpm.p ), _xlpm.productType,_xlfn.XLOOKUP(_xlpm.code,'Product Code'!A:A,'Product Code'!D:D,""), IF(OR(RIGHT(_xlpm.p,5)="-Door",RIGHT(_xlpm.p,6)="-DOORS"),_xlpm.productType&" - Door",_xlpm.productType) )} -> x | J6: x | K6: 18 | L6: 34.5 | M6: 24 | N6: 1 | O6: 1
A7: F9-B18-PO | B7: 1060 | C7: =B7*0.3 -> 318 | D7: =C7*1.13 -> 359.34 | E7: =_xlfn.TEXTAFTER(A7,"-") -> B18-PO | F7: {=_xlfn.LET( _xlpm.p,E7, _xlpm.code,IFERROR( IF(AND(LEFT(_xlpm.p,2)="DB",ISNUMBER(SEARCH("-2",_xlpm.p))),"DB-2", IF(LEFT(_xlpm.p,3)="OC-","OC", LEFT(_xlpm.p,_xlfn.XMATCH(TRUE,ISNUMBER(--MID(_xlpm.p,_xlfn.SEQUENCE(LEN(_xlpm.p)),1)))-1) ) ), _xlpm.p ), _xlpm.productType,_xlfn.XLOOKUP(_xlpm.code,'Product Code'!A:A,'Product Code'!B:B,""), IF(OR(RIGHT(_xlpm.p,5)="-Door",RIGHT(_xlpm.p,6)="-DOORS"),_xlpm.productType&" - Door",_xlpm.productType) )} -> Base Cabinet | G7: {=_xlfn.LET( _xlpm.p,E7, _xlpm.code,IFERROR( IF(AND(LEFT(_xlpm.p,2)="DB",ISNUMBER(SEARCH("-2",_xlpm.p))),"DB-2", IF(LEFT(_xlpm.p,3)="OC-","OC", LEFT(_xlpm.p,_xlfn.XMATCH(TRUE,ISNUMBER(--MID(_xlpm.p,_xlfn.SEQUENCE(LEN(_xlpm.p)),1)))-1) ) ), _xlpm.p ), _xlpm.base,_xlfn.XLOOKUP(_xlpm.code,'Product Code'!A:A,'Product Code'!C:C,""), IF(RIGHT(_xlpm.p,3)="-PO",_xlpm.base&" - Pull-Out",_xlpm.base) )} -> Standard - Pull-Out | H7: Complete Cabinet, for garbage bin | I7: {=_xlfn.LET( _xlpm.p,E7, _xlpm.code,IFERROR( IF(AND(LEFT(_xlpm.p,2)="DB",ISNUMBER(SEARCH("-2",_xlpm.p))),"DB-2", IF(LEFT(_xlpm.p,3)="OC-","OC", LEFT(_xlpm.p,_xlfn.XMATCH(TRUE,ISNUMBER(--MID(_xlpm.p,_xlfn.SEQUENCE(LEN(_xlpm.p)),1)))-1) ) ), _xlpm.p ), _xlpm.productType,_xlfn.XLOOKUP(_xlpm.code,'Product Code'!A:A,'Product Code'!D:D,""), IF(OR(RIGHT(_xlpm.p,5)="-Door",RIGHT(_xlpm.p,6)="-DOORS"),_xlpm.productType&" - Door",_xlpm.productType) )} -> x | J7: x | K7: 18 | L7: 34.5 | M7: 24 | N7: 1 | O7: 1
A8: F9-B21 | B8: 925 | C8: =B8*0.3 -> 277.5 | D8: =C8*1.13 -> 313.575 | E8: =_xlfn.TEXTAFTER(A8,"-") -> B21 | F8: {=_xlfn.LET( _xlpm.p,E8, _xlpm.code,IFERROR( IF(AND(LEFT(_xlpm.p,2)="DB",ISNUMBER(SEARCH("-2",_xlpm.p))),"DB-2", IF(LEFT(_xlpm.p,3)="OC-","OC", LEFT(_xlpm.p,_xlfn.XMATCH(TRUE,ISNUMBER(--MID(_xlpm.p,_xlfn.SEQUENCE(LEN(_xlpm.p)),1)))-1) ) ), _xlpm.p ), _xlpm.productType,_xlfn.XLOOKUP(_xlpm.code,'Product Code'!A:A,'Product Code'!B:B,""), IF(OR(RIGHT(_xlpm.p,5)="-Door",RIGHT(_xlpm.p,6)="-DOORS"),_xlpm.productType&" - Door",_xlpm.productType) )} -> Base Cabinet | G8: {=_xlfn.LET( _xlpm.p,E8, _xlpm.code,IFERROR( IF(AND(LEFT(_xlpm.p,2)="DB",ISNUMBER(SEARCH("-2",_xlpm.p))),"DB-2", IF(LEFT(_xlpm.p,3)="OC-","OC", LEFT(_xlpm.p,_xlfn.XMATCH(TRUE,ISNUMBER(--MID(_xlpm.p,_xlfn.SEQUENCE(LEN(_xlpm.p)),1)))-1) ) ), _xlpm.p ), _xlpm.base,_xlfn.XLOOKUP(_xlpm.code,'Product Code'!A:A,'Product Code'!C:C,""), IF(RIGHT(_xlpm.p,3)="-PO",_xlpm.base&" - Pull-Out",_xlpm.base) )} -> Standard | H8: Complete Cabinet | I8: {=_xlfn.LET( _xlpm.p,E8, _xlpm.code,IFERROR( IF(AND(LEFT(_xlpm.p,2)="DB",ISNUMBER(SEARCH("-2",_xlpm.p))),"DB-2", IF(LEFT(_xlpm.p,3)="OC-","OC", LEFT(_xlpm.p,_xlfn.XMATCH(TRUE,ISNUMBER(--MID(_xlpm.p,_xlfn.SEQUENCE(LEN(_xlpm.p)),1)))-1) ) ), _xlpm.p ), _xlpm.productType,_xlfn.XLOOKUP(_xlpm.code,'Product Code'!A:A,'Product Code'!D:D,""), IF(OR(RIGHT(_xlpm.p,5)="-Door",RIGHT(_xlpm.p,6)="-DOORS"),_xlpm.productType&" - Door",_xlpm.productType) )} -> x | J8: x | K8: 21 | L8: 34.5 | M8: 24 | N8: 1 | O8: 1
A9: F9-BBC42 | B9: 1203 | C9: =B9*0.3 -> 360.9 | D9: =C9*1.13 -> 407.817 | E9: =_xlfn.TEXTAFTER(A9,"-") -> BBC42 | F9: {=_xlfn.LET( _xlpm.p,E9, _xlpm.code,IFERROR( IF(AND(LEFT(_xlpm.p,2)="DB",ISNUMBER(SEARCH("-2",_xlpm.p))),"DB-2", IF(LEFT(_xlpm.p,3)="OC-","OC", LEFT(_xlpm.p,_xlfn.XMATCH(TRUE,ISNUMBER(--MID(_xlpm.p,_xlfn.SEQUENCE(LEN(_xlpm.p)),1)))-1) ) ), _xlpm.p ), _xlpm.productType,_xlfn.XLOOKUP(_xlpm.code,'Product Code'!A:A,'Product Code'!B:B,""), IF(OR(RIGHT(_xlpm.p,5)="-Door",RIGHT(_xlpm.p,6)="-DOORS"),_xlpm.productType&" - Door",_xlpm.productType) )} -> Base Cabinet | G9: {=_xlfn.LET( _xlpm.p,E9, _xlpm.code,IFERROR( IF(AND(LEFT(_xlpm.p,2)="DB",ISNUMBER(SEARCH("-2",_xlpm.p))),"DB-2", IF(LEFT(_xlpm.p,3)="OC-","OC", LEFT(_xlpm.p,_xlfn.XMATCH(TRUE,ISNUMBER(--MID(_xlpm.p,_xlfn.SEQUENCE(LEN(_xlpm.p)),1)))-1) ) ), _xlpm.p ), _xlpm.base,_xlfn.XLOOKUP(_xlpm.code,'Product Code'!A:A,'Product Code'!C:C,""), IF(RIGHT(_xlpm.p,3)="-PO",_xlpm.base&" - Pull-Out",_xlpm.base) )} -> Blind Corner | H9: Complete Cabinet | I9: {=_xlfn.LET( _xlpm.p,E9, _xlpm.code,IFERROR( IF(AND(LEFT(_xlpm.p,2)="DB",ISNUMBER(SEARCH("-2",_xlpm.p))),"DB-2", IF(LEFT(_xlpm.p,3)="OC-","OC", LEFT(_xlpm.p,_xlfn.XMATCH(TRUE,ISNUMBER(--MID(_xlpm.p,_xlfn.SEQUENCE(LEN(_xlpm.p)),1)))-1) ) ), _xlpm.p ), _xlpm.productType,_xlfn.XLOOKUP(_xlpm.code,'Product Code'!A:A,'Product Code'!D:D,""), IF(OR(RIGHT(_xlpm.p,5)="-Door",RIGHT(_xlpm.p,6)="-DOORS"),_xlpm.productType&" - Door",_xlpm.productType) )} -> x | J9: x | K9: 42 | L9: 34.5 | M9: 24 | N9: 1 | O9: 1
A10: F9-BBC45 | B10: 1303 | C10: =B10*0.3 -> 390.9 | D10: =C10*1.13 -> 441.717 | E10: =_xlfn.TEXTAFTER(A10,"-") -> BBC45 | F10: {=_xlfn.LET( _xlpm.p,E10, _xlpm.code,IFERROR( IF(AND(LEFT(_xlpm.p,2)="DB",ISNUMBER(SEARCH("-2",_xlpm.p))),"DB-2", IF(LEFT(_xlpm.p,3)="OC-","OC", LEFT(_xlpm.p,_xlfn.XMATCH(TRUE,ISNUMBER(--MID(_xlpm.p,_xlfn.SEQUENCE(LEN(_xlpm.p)),1)))-1) ) ), _xlpm.p ), _xlpm.productType,_xlfn.XLOOKUP(_xlpm.code,'Product Code'!A:A,'Product Code'!B:B,""), IF(OR(RIGHT(_xlpm.p,5)="-Door",RIGHT(_xlpm.p,6)="-DOORS"),_xlpm.productType&" - Door",_xlpm.productType) )} -> Base Cabinet | G10: {=_xlfn.LET( _xlpm.p,E10, _xlpm.code,IFERROR( IF(AND(LEFT(_xlpm.p,2)="DB",ISNUMBER(SEARCH("-2",_xlpm.p))),"DB-2", IF(LEFT(_xlpm.p,3)="OC-","OC", LEFT(_xlpm.p,_xlfn.XMATCH(TRUE,ISNUMBER(--MID(_xlpm.p,_xlfn.SEQUENCE(LEN(_xlpm.p)),1)))-1) ) ), _xlpm.p ), _xlpm.base,_xlfn.XLOOKUP(_xlpm.code,'Product Code'!A:A,'Product Code'!C:C,""), IF(RIGHT(_xlpm.p,3)="-PO",_xlpm.base&" - Pull-Out",_xlpm.base) )} -> Blind Corner | H10: Complete Cabinet | I10: {=_xlfn.LET( _xlpm.p,E10, _xlpm.code,IFERROR( IF(AND(LEFT(_xlpm.p,2)="DB",ISNUMBER(SEARCH("-2",_xlpm.p))),"DB-2", IF(LEFT(_xlpm.p,3)="OC-","OC", LEFT(_xlpm.p,_xlfn.XMATCH(TRUE,ISNUMBER(--MID(_xlpm.p,_xlfn.SEQUENCE(LEN(_xlpm.p)),1)))-1) ) ), _xlpm.p ), _xlpm.productType,_xlfn.XLOOKUP(_xlpm.code,'Product Code'!A:A,'Product Code'!D:D,""), IF(OR(RIGHT(_xlpm.p,5)="-Door",RIGHT(_xlpm.p,6)="-DOORS"),_xlpm.productType&" - Door",_xlpm.productType) )} -> x | J10: x | K10: 45 | L10: 34.5 | M10: 24 | N10: =IF(ISNUMBER(SEARCH("Cabinet",F10))=FALSE,"N/A",IF(K10>=24,2,1)) -> 2 | O10: =IF(ISNUMBER(SEARCH("Cabinet",F10))=FALSE,"N/A", IF(ISNUMBER(SEARCH("DB",E10)), IF(ISNUMBER(SEARCH("-2",E10)),2,3), IF(ISNUMBER(SEARCH("-PO",E10)),1, IF(LEFT(E10,1)="B",1,0) ) ) ) -> 1
A11: F9-BBC48 | B11: 1404 | C11: =B11*0.3 -> 421.2 | D11: =C11*1.13 -> 475.956 | E11: =_xlfn.TEXTAFTER(A11,"-") -> BBC48 | F11: {=_xlfn.LET( _xlpm.p,E11, _xlpm.code,IFERROR( IF(AND(LEFT(_xlpm.p,2)="DB",ISNUMBER(SEARCH("-2",_xlpm.p))),"DB-2", IF(LEFT(_xlpm.p,3)="OC-","OC", LEFT(_xlpm.p,_xlfn.XMATCH(TRUE,ISNUMBER(--MID(_xlpm.p,_xlfn.SEQUENCE(LEN(_xlpm.p)),1)))-1) ) ), _xlpm.p ), _xlpm.productType,_xlfn.XLOOKUP(_xlpm.code,'Product Code'!A:A,'Product Code'!B:B,""), IF(OR(RIGHT(_xlpm.p,5)="-Door",RIGHT(_xlpm.p,6)="-DOORS"),_xlpm.productType&" - Door",_xlpm.productType) )} -> Base Cabinet | G11: {=_xlfn.LET( _xlpm.p,E11, _xlpm.code,IFERROR( IF(AND(LEFT(_xlpm.p,2)="DB",ISNUMBER(SEARCH("-2",_xlpm.p))),"DB-2", IF(LEFT(_xlpm.p,3)="OC-","OC", LEFT(_xlpm.p,_xlfn.XMATCH(TRUE,ISNUMBER(--MID(_xlpm.p,_xlfn.SEQUENCE(LEN(_xlpm.p)),1)))-1) ) ), _xlpm.p ), _xlpm.base,_xlfn.XLOOKUP(_xlpm.code,'Product Code'!A:A,'Product Code'!C:C,""), IF(RIGHT(_xlpm.p,3)="-PO",_xlpm.base&" - Pull-Out",_xlpm.base) )} -> Blind Corner | H11: Complete Cabinet | I11: {=_xlfn.LET( _xlpm.p,E11, _xlpm.code,IFERROR( IF(AND(LEFT(_xlpm.p,2)="DB",ISNUMBER(SEARCH("-2",_xlpm.p))),"DB-2", IF(LEFT(_xlpm.p,3)="OC-","OC", LEFT(_xlpm.p,_xlfn.XMATCH(TRUE,ISNUMBER(--MID(_xlpm.p,_xlfn.SEQUENCE(LEN(_xlpm.p)),1)))-1) ) ), _xlpm.p ), _xlpm.productType,_xlfn.XLOOKUP(_xlpm.code,'Product Code'!A:A,'Product Code'!D:D,""), IF(OR(RIGHT(_xlpm.p,5)="-Door",RIGHT(_xlpm.p,6)="-DOORS"),_xlpm.productType&" - Door",_xlpm.productType) )} -> x | J11: x | K11: 48 | L11: 34.5 | M11: 24 | N11: =IF(ISNUMBER(SEARCH("Cabinet",F11))=FALSE,"N/A",IF(K11>=24,2,1)) -> 2 | O11: =IF(ISNUMBER(SEARCH("Cabinet",F11))=FALSE,"N/A", IF(ISNUMBER(SEARCH("DB",E11)), IF(ISNUMBER(SEARCH("-2",E11)),2,3), IF(ISNUMBER(SEARCH("-PO",E11)),1, IF(LEFT(E11,1)="B",1,0) ) ) ) -> 1
A12: F9-DB12 | B12: 1059 | C12: =B12*0.3 -> 317.7 | D12: =C12*1.13 -> 359.001 | E12: =_xlfn.TEXTAFTER(A12,"-") -> DB12 | F12: {=_xlfn.LET( _xlpm.p,E12, _xlpm.code,IFERROR( IF(AND(LEFT(_xlpm.p,2)="DB",ISNUMBER(SEARCH("-2",_xlpm.p))),"DB-2", IF(LEFT(_xlpm.p,3)="OC-","OC", LEFT(_xlpm.p,_xlfn.XMATCH(TRUE,ISNUMBER(--MID(_xlpm.p,_xlfn.SEQUENCE(LEN(_xlpm.p)),1)))-1) ) ), _xlpm.p ), _xlfn.XLOOKUP(_xlpm.code,'Product Code'!A:A,'Product Code'!B:B,"") )} -> Base Cabinet | G12: Drawer | H12: Complete Cabinet | I12: {=_xlfn.LET( _xlpm.p,E12, _xlpm.code,IFERROR( IF(AND(LEFT(_xlpm.p,2)="DB",ISNUMBER(SEARCH("-2",_xlpm.p))),"DB-2", IF(LEFT(_xlpm.p,3)="OC-","OC", LEFT(_xlpm.p,_xlfn.XMATCH(TRUE,ISNUMBER(--MID(_xlpm.p,_xlfn.SEQUENCE(LEN(_xlpm.p)),1)))-1) ) ), _xlpm.p ), _xlpm.productType,_xlfn.XLOOKUP(_xlpm.code,'Product Code'!A:A,'Product Code'!D:D,""), IF(OR(RIGHT(_xlpm.p,5)="-Door",RIGHT(_xlpm.p,6)="-DOORS"),_xlpm.productType&" - Door",_xlpm.productType) )} -> x | J12: x | K12: 12 | L12: 34.5 | M12: 24 | N12: =IF(ISNUMBER(SEARCH("Cabinet",F12))=FALSE,"N/A",IF(K12>=24,2,1)) -> 1 | O12: =IF(ISNUMBER(SEARCH("Cabinet",F12))=FALSE,"N/A", IF(ISNUMBER(SEARCH("DB",E12)), IF(ISNUMBER(SEARCH("-2",E12)),2,3), IF(ISNUMBER(SEARCH("-PO",E12)),1, IF(LEFT(E12,1)="B",1,0) ) ) ) -> 3
A13: F9-DB15 | B13: 1157 | C13: =B13*0.3 -> 347.1 | D13: =C13*1.13 -> 392.223 | E13: =_xlfn.TEXTAFTER(A13,"-") -> DB15 | F13: {=_xlfn.LET( _xlpm.p,E13, _xlpm.code,IFERROR( IF(AND(LEFT(_xlpm.p,2)="DB",ISNUMBER(SEARCH("-2",_xlpm.p))),"DB-2", IF(LEFT(_xlpm.p,3)="OC-","OC", LEFT(_xlpm.p,_xlfn.XMATCH(TRUE,ISNUMBER(--MID(_xlpm.p,_xlfn.SEQUENCE(LEN(_xlpm.p)),1)))-1) ) ), _xlpm.p ), _xlfn.XLOOKUP(_xlpm.code,'Product Code'!A:A,'Product Code'!B:B,"") )} -> Base Cabinet | G13: Drawer | H13: Complete Cabinet | I13: {=_xlfn.LET( _xlpm.p,E13, _xlpm.code,IFERROR( IF(AND(LEFT(_xlpm.p,2)="DB",ISNUMBER(SEARCH("-2",_xlpm.p))),"DB-2", IF(LEFT(_xlpm.p,3)="OC-","OC", LEFT(_xlpm.p,_xlfn.XMATCH(TRUE,ISNUMBER(--MID(_xlpm.p,_xlfn.SEQUENCE(LEN(_xlpm.p)),1)))-1) ) ), _xlpm.p ), _xlpm.productType,_xlfn.XLOOKUP(_xlpm.code,'Product Code'!A:A,'Product Code'!D:D,""), IF(OR(RIGHT(_xlpm.p,5)="-Door",RIGHT(_xlpm.p,6)="-DOORS"),_xlpm.productType&" - Door",_xlpm.productType) )} -> x | J13: x | K13: 15 | L13: 34.5 | M13: 24 | N13: =IF(ISNUMBER(SEARCH("Cabinet",F13))=FALSE,"N/A",IF(K13>=24,2,1)) -> 1 | O13: =IF(ISNUMBER(SEARCH("Cabinet",F13))=FALSE,"N/A", IF(ISNUMBER(SEARCH("DB",E13)), IF(ISNUMBER(SEARCH("-2",E13)),2,3), IF(ISNUMBER(SEARCH("-PO",E13)),1, IF(LEFT(E13,1)="B",1,0) ) ) ) -> 3
A14: F9-DB18 | B14: 1202 | C14: =B14*0.3 -> 360.6 | D14: =C14*1.13 -> 407.478 | E14: =_xlfn.TEXTAFTER(A14,"-") -> DB18 | F14: {=_xlfn.LET( _xlpm.p,E14, _xlpm.code,IFERROR( IF(AND(LEFT(_xlpm.p,2)="DB",ISNUMBER(SEARCH("-2",_xlpm.p))),"DB-2", IF(LEFT(_xlpm.p,3)="OC-","OC", LEFT(_xlpm.p,_xlfn.XMATCH(TRUE,ISNUMBER(--MID(_xlpm.p,_xlfn.SEQUENCE(LEN(_xlpm.p)),1)))-1) ) ), _xlpm.p ), _xlfn.XLOOKUP(_xlpm.code,'Product Code'!A:A,'Product Code'!B:B,"") )} -> Base Cabinet | G14: Drawer | H14: Complete Cabinet | I14: {=_xlfn.LET( _xlpm.p,E14, _xlpm.code,IFERROR( IF(AND(LEFT(_xlpm.p,2)="DB",ISNUMBER(SEARCH("-2",_xlpm.p))),"DB-2", IF(LEFT(_xlpm.p,3)="OC-","OC", LEFT(_xlpm.p,_xlfn.XMATCH(TRUE,ISNUMBER(--MID(_xlpm.p,_xlfn.SEQUENCE(LEN(_xlpm.p)),1)))-1) ) ), _xlpm.p ), _xlpm.productType,_xlfn.XLOOKUP(_xlpm.code,'Product Code'!A:A,'Product Code'!D:D,""), IF(OR(RIGHT(_xlpm.p,5)="-Door",RIGHT(_xlpm.p,6)="-DOORS"),_xlpm.productType&" - Door",_xlpm.productType) )} -> x | J14: x | K14: 18 | L14: 34.5 | M14: 24 | N14: =IF(ISNUMBER(SEARCH("Cabinet",F14))=FALSE,"N/A",IF(K14>=24,2,1)) -> 1 | O14: =IF(ISNUMBER(SEARCH("Cabinet",F14))=FALSE,"N/A", IF(ISNUMBER(SEARCH("DB",E14)), IF(ISNUMBER(SEARCH("-2",E14)),2,3), IF(ISNUMBER(SEARCH("-PO",E14)),1, IF(LEFT(E14,1)="B",1,0) ) ) ) -> 3
A15: F9-DB21 | B15: 1306 | C15: =B15*0.3 -> 391.8 | D15: =C15*1.13 -> 442.734 | E15: =_xlfn.TEXTAFTER(A15,"-") -> DB21 | F15: {=_xlfn.LET( _xlpm.p,E15, _xlpm.code,IFERROR( IF(AND(LEFT(_xlpm.p,2)="DB",ISNUMBER(SEARCH("-2",_xlpm.p))),"DB-2", IF(LEFT(_xlpm.p,3)="OC-","OC", LEFT(_xlpm.p,_xlfn.XMATCH(TRUE,ISNUMBER(--MID(_xlpm.p,_xlfn.SEQUENCE(LEN(_xlpm.p)),1)))-1) ) ), _xlpm.p ), _xlfn.XLOOKUP(_xlpm.code,'Product Code'!A:A,'Product Code'!B:B,"") )} -> Base Cabinet | G15: Drawer | H15: Complete Cabinet | I15: {=_xlfn.LET( _xlpm.p,E15, _xlpm.code,IFERROR( IF(AND(LEFT(_xlpm.p,2)="DB",ISNUMBER(SEARCH("-2",_xlpm.p))),"DB-2", IF(LEFT(_xlpm.p,3)="OC-","OC", LEFT(_xlpm.p,_xlfn.XMATCH(TRUE,ISNUMBER(--MID(_xlpm.p,_xlfn.SEQUENCE(LEN(_xlpm.p)),1)))-1) ) ), _xlpm.p ), _xlpm.productType,_xlfn.XLOOKUP(_xlpm.code,'Product Code'!A:A,'Product Code'!D:D,""), IF(OR(RIGHT(_xlpm.p,5)="-Door",RIGHT(_xlpm.p,6)="-DOORS"),_xlpm.productType&" - Door",_xlpm.productType) )} -> x | J15: x | K15: 21 | L15: 34.5 | M15: 24 | N15: =IF(ISNUMBER(SEARCH("Cabinet",F15))=FALSE,"N/A",IF(K15>=24,2,1)) -> 1 | O15: =IF(ISNUMBER(SEARCH("Cabinet",F15))=FALSE,"N/A", IF(ISNUMBER(SEARCH("DB",E15)), IF(ISNUMBER(SEARCH("-2",E15)),2,3), IF(ISNUMBER(SEARCH("-PO",E15)),1, IF(LEFT(E15,1)="B",1,0) ) ) ) -> 3
A16: F9-DB24 | B16: 1346 | C16: =B16*0.3 -> 403.8 | D16: =C16*1.13 -> 456.294 | E16: =_xlfn.TEXTAFTER(A16,"-") -> DB24 | F16: {=_xlfn.LET( _xlpm.p,E16, _xlpm.code,IFERROR( IF(AND(LEFT(_xlpm.p,2)="DB",ISNUMBER(SEARCH("-2",_xlpm.p))),"DB-2", IF(LEFT(_xlpm.p,3)="OC-","OC", LEFT(_xlpm.p,_xlfn.XMATCH(TRUE,ISNUMBER(--MID(_xlpm.p,_xlfn.SEQUENCE(LEN(_xlpm.p)),1)))-1) ) ), _xlpm.p ), _xlfn.XLOOKUP(_xlpm.code,'Product Code'!A:A,'Product Code'!B:B,"") )} -> Base Cabinet | G16: Drawer | H16: Complete Cabinet | I16: {=_xlfn.LET( _xlpm.p,E16, _xlpm.code,IFERROR( IF(AND(LEFT(_xlpm.p,2)="DB",ISNUMBER(SEARCH("-2",_xlpm.p))),"DB-2", IF(LEFT(_xlpm.p,3)="OC-","OC", LEFT(_xlpm.p,_xlfn.XMATCH(TRUE,ISNUMBER(--MID(_xlpm.p,_xlfn.SEQUENCE(LEN(_xlpm.p)),1)))-1) ) ), _xlpm.p ), _xlpm.productType,_xlfn.XLOOKUP(_xlpm.code,'Product Code'!A:A,'Product Code'!D:D,""), IF(OR(RIGHT(_xlpm.p,5)="-Door",RIGHT(_xlpm.p,6)="-DOORS"),_xlpm.productType&" - Door",_xlpm.productType) )} -> x | J16: x | K16: 24 | L16: 34.5 | M16: 24 | N16: =IF(ISNUMBER(SEARCH("Cabinet",F16))=FALSE,"N/A",IF(K16>=24,2,1)) -> 2 | O16: =IF(ISNUMBER(SEARCH("Cabinet",F16))=FALSE,"N/A", IF(ISNUMBER(SEARCH("DB",E16)), IF(ISNUMBER(SEARCH("-2",E16)),2,3), IF(ISNUMBER(SEARCH("-PO",E16)),1, IF(LEFT(E16,1)="B",1,0) ) ) ) -> 3
A17: F9-DB27 | B17: 1419 | C17: =B17*0.3 -> 425.7 | D17: =C17*1.13 -> 481.041 | E17: =_xlfn.TEXTAFTER(A17,"-") -> DB27 | F17: {=_xlfn.LET( _xlpm.p,E17, _xlpm.code,IFERROR( IF(AND(LEFT(_xlpm.p,2)="DB",ISNUMBER(SEARCH("-2",_xlpm.p))),"DB-2", IF(LEFT(_xlpm.p,3)="OC-","OC", LEFT(_xlpm.p,_xlfn.XMATCH(TRUE,ISNUMBER(--MID(_xlpm.p,_xlfn.SEQUENCE(LEN(_xlpm.p)),1)))-1) ) ), _xlpm.p ), _xlfn.XLOOKUP(_xlpm.code,'Product Code'!A:A,'Product Code'!B:B,"") )} -> Base Cabinet | G17: Drawer | H17: Complete Cabinet | I17: {=_xlfn.LET( _xlpm.p,E17, _xlpm.code,IFERROR( IF(AND(LEFT(_xlpm.p,2)="DB",ISNUMBER(SEARCH("-2",_xlpm.p))),"DB-2", IF(LEFT(_xlpm.p,3)="OC-","OC", LEFT(_xlpm.p,_xlfn.XMATCH(TRUE,ISNUMBER(--MID(_xlpm.p,_xlfn.SEQUENCE(LEN(_xlpm.p)),1)))-1) ) ), _xlpm.p ), _xlpm.productType,_xlfn.XLOOKUP(_xlpm.code,'Product Code'!A:A,'Product Code'!D:D,""), IF(OR(RIGHT(_xlpm.p,5)="-Door",RIGHT(_xlpm.p,6)="-DOORS"),_xlpm.productType&" - Door",_xlpm.productType) )} -> x | J17: x | K17: 27 | L17: 34.5 | M17: 24 | N17: =IF(ISNUMBER(SEARCH("Cabinet",F17))=FALSE,"N/A",IF(K17>=24,2,1)) -> 2 | O17: =IF(ISNUMBER(SEARCH("Cabinet",F17))=FALSE,"N/A", IF(ISNUMBER(SEARCH("DB",E17)), IF(ISNUMBER(SEARCH("-2",E17)),2,3), IF(ISNUMBER(SEARCH("-PO",E17)),1, IF(LEFT(E17,1)="B",1,0) ) ) ) -> 3
A18: F9-DB27-2 | B18: 1122 | C18: =B18*0.3 -> 336.6 | D18: =C18*1.13 -> 380.358 | E18: =_xlfn.TEXTAFTER(A18,"-") -> DB27-2 | F18: {=_xlfn.LET( _xlpm.p,E18, _xlpm.code,IFERROR( IF(AND(LEFT(_xlpm.p,2)="DB",ISNUMBER(SEARCH("-2",_xlpm.p))),"DB-2", IF(LEFT(_xlpm.p,3)="OC-","OC", LEFT(_xlpm.p,_xlfn.XMATCH(TRUE,ISNUMBER(--MID(_xlpm.p,_xlfn.SEQUENCE(LEN(_xlpm.p)),1)))-1) ) ), _xlpm.p ), _xlfn.XLOOKUP(_xlpm.code,'Product Code'!A:A,'Product Code'!B:B,"") )} -> Base Cabinet | G18: Drawer | H18: Complete Cabinet | I18: {=_xlfn.LET( _xlpm.p,E18, _xlpm.code,IFERROR( IF(AND(LEFT(_xlpm.p,2)="DB",ISNUMBER(SEARCH("-2",_xlpm.p))),"DB-2", IF(LEFT(_xlpm.p,3)="OC-","OC", LEFT(_xlpm.p,_xlfn.XMATCH(TRUE,ISNUMBER(--MID(_xlpm.p,_xlfn.SEQUENCE(LEN(_xlpm.p)),1)))-1) ) ), _xlpm.p ), _xlpm.productType,_xlfn.XLOOKUP(_xlpm.code,'Product Code'!A:A,'Product Code'!D:D,""), IF(OR(RIGHT(_xlpm.p,5)="-Door",RIGHT(_xlpm.p,6)="-DOORS"),_xlpm.productType&" - Door",_xlpm.productType) )} -> x | J18: x | K18: 27 | L18: 34.5 | M18: 24 | N18: =IF(ISNUMBER(SEARCH("Cabinet",F18))=FALSE,"N/A",IF(K18>=24,2,1)) -> 2 | O18: =IF(ISNUMBER(SEARCH("Cabinet",F18))=FALSE,"N/A", IF(ISNUMBER(SEARCH("DB",E18)), IF(ISNUMBER(SEARCH("-2",E18)),2,3), IF(ISNUMBER(SEARCH("-PO",E18)),1, IF(LEFT(E18,1)="B",1,0) ) ) ) -> 2
A19: F9-DB30 | B19: 1490 | C19: =B19*0.3 -> 447 | D19: =C19*1.13 -> 505.11 | E19: =_xlfn.TEXTAFTER(A19,"-") -> DB30 | F19: {=_xlfn.LET( _xlpm.p,E19, _xlpm.code,IFERROR( IF(AND(LEFT(_xlpm.p,2)="DB",ISNUMBER(SEARCH("-2",_xlpm.p))),"DB-2", IF(LEFT(_xlpm.p,3)="OC-","OC", LEFT(_xlpm.p,_xlfn.XMATCH(TRUE,ISNUMBER(--MID(_xlpm.p,_xlfn.SEQUENCE(LEN(_xlpm.p)),1)))-1) ) ), _xlpm.p ), _xlfn.XLOOKUP(_xlpm.code,'Product Code'!A:A,'Product Code'!B:B,"") )} -> Base Cabinet | G19: Drawer | H19: Complete Cabinet | I19: {=_xlfn.LET( _xlpm.p,E19, _xlpm.code,IFERROR( IF(AND(LEFT(_xlpm.p,2)="DB",ISNUMBER(SEARCH("-2",_xlpm.p))),"DB-2", IF(LEFT(_xlpm.p,3)="OC-","OC", LEFT(_xlpm.p,_xlfn.XMATCH(TRUE,ISNUMBER(--MID(_xlpm.p,_xlfn.SEQUENCE(LEN(_xlpm.p)),1)))-1) ) ), _xlpm.p ), _xlpm.productType,_xlfn.XLOOKUP(_xlpm.code,'Product Code'!A:A,'Product Code'!D:D,""), IF(OR(RIGHT(_xlpm.p,5)="-Door",RIGHT(_xlpm.p,6)="-DOORS"),_xlpm.productType&" - Door",_xlpm.productType) )} -> x | J19: x | K19: 30 | L19: 34.5 | M19: 24 | N19: =IF(ISNUMBER(SEARCH("Cabinet",F19))=FALSE,"N/A",IF(K19>=24,2,1)) -> 2 | O19: =IF(ISNUMBER(SEARCH("Cabinet",F19))=FALSE,"N/A", IF(ISNUMBER(SEARCH("DB",E19)), IF(ISNUMBER(SEARCH("-2",E19)),2,3), IF(ISNUMBER(SEARCH("-PO",E19)),1, IF(LEFT(E19,1)="B",1,0) ) ) ) -> 3
A20: F9-DB30-2 | B20: 1211 | C20: =B20*0.3 -> 363.3 | D20: =C20*1.13 -> 410.529 | E20: =_xlfn.TEXTAFTER(A20,"-") -> DB30-2 | F20: {=_xlfn.LET( _xlpm.p,E20, _xlpm.code,IFERROR( IF(AND(LEFT(_xlpm.p,2)="DB",ISNUMBER(SEARCH("-2",_xlpm.p))),"DB-2", IF(LEFT(_xlpm.p,3)="OC-","OC", LEFT(_xlpm.p,_xlfn.XMATCH(TRUE,ISNUMBER(--MID(_xlpm.p,_xlfn.SEQUENCE(LEN(_xlpm.p)),1)))-1) ) ), _xlpm.p ), _xlfn.XLOOKUP(_xlpm.code,'Product Code'!A:A,'Product Code'!B:B,"") )} -> Base Cabinet | G20: Drawer | H20: Complete Cabinet | I20: {=_xlfn.LET( _xlpm.p,E20, _xlpm.code,IFERROR( IF(AND(LEFT(_xlpm.p,2)="DB",ISNUMBER(SEARCH("-2",_xlpm.p))),"DB-2", IF(LEFT(_xlpm.p,3)="OC-","OC", LEFT(_xlpm.p,_xlfn.XMATCH(TRUE,ISNUMBER(--MID(_xlpm.p,_xlfn.SEQUENCE(LEN(_xlpm.p)),1)))-1) ) ), _xlpm.p ), _xlpm.productType,_xlfn.XLOOKUP(_xlpm.code,'Product Code'!A:A,'Product Code'!D:D,""), IF(OR(RIGHT(_xlpm.p,5)="-Door",RIGHT(_xlpm.p,6)="-DOORS"),_xlpm.productType&" - Door",_xlpm.productType) )} -> x | J20: x | K20: 30 | L20: 34.5 | M20: 24 | N20: =IF(ISNUMBER(SEARCH("Cabinet",F20))=FALSE,"N/A",IF(K20>=24,2,1)) -> 2 | O20: =IF(ISNUMBER(SEARCH("Cabinet",F20))=FALSE,"N/A", IF(ISNUMBER(SEARCH("DB",E20)), IF(ISNUMBER(SEARCH("-2",E20)),2,3), IF(ISNUMBER(SEARCH("-PO",E20)),1, IF(LEFT(E20,1)="B",1,0) ) ) ) -> 2
A21: F9-DB33 | B21: 1552 | C21: =B21*0.3 -> 465.6 | D21: =C21*1.13 -> 526.128 | E21: =_xlfn.TEXTAFTER(A21,"-") -> DB33 | F21: {=_xlfn.LET( _xlpm.p,E21, _xlpm.code,IFERROR( IF(AND(LEFT(_xlpm.p,2)="DB",ISNUMBER(SEARCH("-2",_xlpm.p))),"DB-2", IF(LEFT(_xlpm.p,3)="OC-","OC", LEFT(_xlpm.p,_xlfn.XMATCH(TRUE,ISNUMBER(--MID(_xlpm.p,_xlfn.SEQUENCE(LEN(_xlpm.p)),1)))-1) ) ), _xlpm.p ), _xlfn.XLOOKUP(_xlpm.code,'Product Code'!A:A,'Product Code'!B:B,"") )} -> Base Cabinet | G21: Drawer | H21: Complete Cabinet | I21: {=_xlfn.LET( _xlpm.p,E21, _xlpm.code,IFERROR( IF(AND(LEFT(_xlpm.p,2)="DB",ISNUMBER(SEARCH("-2",_xlpm.p))),"DB-2", IF(LEFT(_xlpm.p,3)="OC-","OC", LEFT(_xlpm.p,_xlfn.XMATCH(TRUE,ISNUMBER(--MID(_xlpm.p,_xlfn.SEQUENCE(LEN(_xlpm.p)),1)))-1) ) ), _xlpm.p ), _xlpm.productType,_xlfn.XLOOKUP(_xlpm.code,'Product Code'!A:A,'Product Code'!D:D,""), IF(OR(RIGHT(_xlpm.p,5)="-Door",RIGHT(_xlpm.p,6)="-DOORS"),_xlpm.productType&" - Door",_xlpm.productType) )} -> x | J21: x | K21: 33 | L21: 34.5 | M21: 24 | N21: =IF(ISNUMBER(SEARCH("Cabinet",F21))=FALSE,"N/A",IF(K21>=24,2,1)) -> 2 | O21: =IF(ISNUMBER(SEARCH("Cabinet",F21))=FALSE,"N/A", IF(ISNUMBER(SEARCH("DB",E21)), IF(ISNUMBER(SEARCH("-2",E21)),2,3), IF(ISNUMBER(SEARCH("-PO",E21)),1, IF(LEFT(E21,1)="B",1,0) ) ) ) -> 3
A22: F9-DB36 | B22: 1620 | C22: =B22*0.3 -> 486 | D22: =C22*1.13 -> 549.18 | E22: =_xlfn.TEXTAFTER(A22,"-") -> DB36 | F22: {=_xlfn.LET( _xlpm.p,E22, _xlpm.code,IFERROR( IF(AND(LEFT(_xlpm.p,2)="DB",ISNUMBER(SEARCH("-2",_xlpm.p))),"DB-2", IF(LEFT(_xlpm.p,3)="OC-","OC", LEFT(_xlpm.p,_xlfn.XMATCH(TRUE,ISNUMBER(--MID(_xlpm.p,_xlfn.SEQUENCE(LEN(_xlpm.p)),1)))-1) ) ), _xlpm.p ), _xlfn.XLOOKUP(_xlpm.code,'Product Code'!A:A,'Product Code'!B:B,"") )} -> Base Cabinet | G22: Drawer | H22: Complete Cabinet | I22: {=_xlfn.LET( _xlpm.p,E22, _xlpm.code,IFERROR( IF(AND(LEFT(_xlpm.p,2)="DB",ISNUMBER(SEARCH("-2",_xlpm.p))),"DB-2", IF(LEFT(_xlpm.p,3)="OC-","OC", LEFT(_xlpm.p,_xlfn.XMATCH(TRUE,ISNUMBER(--MID(_xlpm.p,_xlfn.SEQUENCE(LEN(_xlpm.p)),1)))-1) ) ), _xlpm.p ), _xlpm.productType,_xlfn.XLOOKUP(_xlpm.code,'Product Code'!A:A,'Product Code'!D:D,""), IF(OR(RIGHT(_xlpm.p,5)="-Door",RIGHT(_xlpm.p,6)="-DOORS"),_xlpm.productType&" - Door",_xlpm.productType) )} -> x | J22: x | K22: 36 | L22: 34.5 | M22: 24 | N22: =IF(ISNUMBER(SEARCH("Cabinet",F22))=FALSE,"N/A",IF(K22>=24,2,1)) -> 2 | O22: =IF(ISNUMBER(SEARCH("Cabinet",F22))=FALSE,"N/A", IF(ISNUMBER(SEARCH("DB",E22)), IF(ISNUMBER(SEARCH("-2",E22)),2,3), IF(ISNUMBER(SEARCH("-PO",E22)),1, IF(LEFT(E22,1)="B",1,0) ) ) ) -> 3
A23: F9-FSB33*19.75(10-1/8) | B23: 871 | C23: =B23*0.3 -> 261.3 | D23: =C23*1.13 -> 295.269 | E23: =_xlfn.TEXTAFTER(A23,"-") -> FSB33*19.75(10-1/8) | F23: {=_xlfn.LET( _xlpm.p,E23, _xlpm.code,IFERROR( IF(AND(LEFT(_xlpm.p,2)="DB",ISNUMBER(SEARCH("-2",_xlpm.p))),"DB-2", IF(LEFT(_xlpm.p,3)="OC-","OC", LEFT(_xlpm.p,_xlfn.XMATCH(TRUE,ISNUMBER(--MID(_xlpm.p,_xlfn.SEQUENCE(LEN(_xlpm.p)),1)))-1) ) ), _xlpm.p ), _xlfn.XLOOKUP(_xlpm.code,'Product Code'!A:A,'Product Code'!B:B,"") )} -> Base Cabinet | G23: {=_xlfn.LET( _xlpm.p,E23, _xlpm.code,IFERROR( IF(AND(LEFT(_xlpm.p,2)="DB",ISNUMBER(SEARCH("-2",_xlpm.p))),"DB-2", IF(LEFT(_xlpm.p,3)="OC-","OC", LEFT(_xlpm.p,_xlfn.XMATCH(TRUE,ISNUMBER(--MID(_xlpm.p,_xlfn.SEQUENCE(LEN(_xlpm.p)),1)))-1) ) ), _xlpm.p ), _xlpm.base,_xlfn.XLOOKUP(_xlpm.code,'Product Code'!A:A,'Product Code'!C:C,""), IF(RIGHT(_xlpm.p,3)="-PO",_xlpm.base&" - Pull-Out",_xlpm.base) )} -> Farmhouse Sink | H23: Complete Cabinet | I23: {=_xlfn.LET( _xlpm.p,E23, _xlpm.code,IFERROR( IF(AND(LEFT(_xlpm.p,2)="DB",ISNUMBER(SEARCH("-2",_xlpm.p))),"DB-2", IF(LEFT(_xlpm.p,3)="OC-","OC", LEFT(_xlpm.p,_xlfn.XMATCH(TRUE,ISNUMBER(--MID(_xlpm.p,_xlfn.SEQUENCE(LEN(_xlpm.p)),1)))-1) ) ), _xlpm.p ), _xlpm.productType,_xlfn.XLOOKUP(_xlpm.code,'Product Code'!A:A,'Product Code'!D:D,""), IF(OR(RIGHT(_xlpm.p,5)="-Door",RIGHT(_xlpm.p,6)="-DOORS"),_xlpm.productType&" - Door",_xlpm.productType) )} -> x | J23: x | K23: 33 | L23: 34.5 | M23: 24 | N23: =IF(ISNUMBER(SEARCH("Cabinet",F23))=FALSE,"N/A",IF(K23>=24,2,1)) -> 2 | O23: =IF(ISNUMBER(SEARCH("Cabinet",F23))=FALSE,"N/A", IF(ISNUMBER(SEARCH("DB",E23)), IF(ISNUMBER(SEARCH("-2",E23)),2,3), IF(ISNUMBER(SEARCH("-PO",E23)),1, IF(LEFT(E23,1)="B",1,0) ) ) ) -> 0
A24: F9-FSB36*19.75(10-1/8) | B24: 937 | C24: =B24*0.3 -> 281.1 | D24: =C24*1.13 -> 317.643 | E24: =_xlfn.TEXTAFTER(A24,"-") -> FSB36*19.75(10-1/8) | F24: {=_xlfn.LET( _xlpm.p,E24, _xlpm.code,IFERROR( IF(AND(LEFT(_xlpm.p,2)="DB",ISNUMBER(SEARCH("-2",_xlpm.p))),"DB-2", IF(LEFT(_xlpm.p,3)="OC-","OC", LEFT(_xlpm.p,_xlfn.XMATCH(TRUE,ISNUMBER(--MID(_xlpm.p,_xlfn.SEQUENCE(LEN(_xlpm.p)),1)))-1) ) ), _xlpm.p ), _xlfn.XLOOKUP(_xlpm.code,'Product Code'!A:A,'Product Code'!B:B,"") )} -> Base Cabinet | G24: {=_xlfn.LET( _xlpm.p,E24, _xlpm.code,IFERROR( IF(AND(LEFT(_xlpm.p,2)="DB",ISNUMBER(SEARCH("-2",_xlpm.p))),"DB-2", IF(LEFT(_xlpm.p,3)="OC-","OC", LEFT(_xlpm.p,_xlfn.XMATCH(TRUE,ISNUMBER(--MID(_xlpm.p,_xlfn.SEQUENCE(LEN(_xlpm.p)),1)))-1) ) ), _xlpm.p ), _xlpm.base,_xlfn.XLOOKUP(_xlpm.code,'Product Code'!A:A,'Product Code'!C:C,""), IF(RIGHT(_xlpm.p,3)="-PO",_xlpm.base&" - Pull-Out",_xlpm.base) )} -> Farmhouse Sink | H24: Complete Cabinet | I24: {=_xlfn.LET( _xlpm.p,E24, _xlpm.code,IFERROR( IF(AND(LEFT(_xlpm.p,2)="DB",ISNUMBER(SEARCH("-2",_xlpm.p))),"DB-2", IF(LEFT(_xlpm.p,3)="OC-","OC", LEFT(_xlpm.p,_xlfn.XMATCH(TRUE,ISNUMBER(--MID(_xlpm.p,_xlfn.SEQUENCE(LEN(_xlpm.p)),1)))-1) ) ), _xlpm.p ), _xlpm.productType,_xlfn.XLOOKUP(_xlpm.code,'Product Code'!A:A,'Product Code'!D:D,""), IF(OR(RIGHT(_xlpm.p,5)="-Door",RIGHT(_xlpm.p,6)="-DOORS"),_xlpm.productType&" - Door",_xlpm.productType) )} -> x | J24: x | K24: 36 | L24: 34.5 | M24: 24 | N24: =IF(ISNUMBER(SEARCH("Cabinet",F24))=FALSE,"N/A",IF(K24>=24,2,1)) -> 2 | O24: =IF(ISNUMBER(SEARCH("Cabinet",F24))=FALSE,"N/A", IF(ISNUMBER(SEARCH("DB",E24)), IF(ISNUMBER(SEARCH("-2",E24)),2,3), IF(ISNUMBER(SEARCH("-PO",E24)),1, IF(LEFT(E24,1)="B",1,0) ) ) ) -> 0
A25: F9-LS3309 | B25: 1383 | C25: =B25*0.3 -> 414.9 | D25: =C25*1.13 -> 468.837 | E25: =_xlfn.TEXTAFTER(A25,"-") -> LS3309 | F25: {=_xlfn.LET( _xlpm.p,E25, _xlpm.code,IFERROR( IF(AND(LEFT(_xlpm.p,2)="DB",ISNUMBER(SEARCH("-2",_xlpm.p))),"DB-2", IF(LEFT(_xlpm.p,3)="OC-","OC", LEFT(_xlpm.p,_xlfn.XMATCH(TRUE,ISNUMBER(--MID(_xlpm.p,_xlfn.SEQUENCE(LEN(_xlpm.p)),1)))-1) ) ), _xlpm.p ), _xlfn.XLOOKUP(_xlpm.code,'Product Code'!A:A,'Product Code'!B:B,"") )} -> Base Cabinet | G25: {=_xlfn.LET( _xlpm.p,E25, _xlpm.code,IFERROR( IF(AND(LEFT(_xlpm.p,2)="DB",ISNUMBER(SEARCH("-2",_xlpm.p))),"DB-2", IF(LEFT(_xlpm.p,3)="OC-","OC", LEFT(_xlpm.p,_xlfn.XMATCH(TRUE,ISNUMBER(--MID(_xlpm.p,_xlfn.SEQUENCE(LEN(_xlpm.p)),1)))-1) ) ), _xlpm.p ), _xlpm.base,_xlfn.XLOOKUP(_xlpm.code,'Product Code'!A:A,'Product Code'!C:C,""), IF(RIGHT(_xlpm.p,3)="-PO",_xlpm.base&" - Pull-Out",_xlpm.base) )} -> Corner (90deg) | H25: Complete Cabinet | I25: {=_xlfn.LET( _xlpm.p,E25, _xlpm.code,IFERROR( IF(AND(LEFT(_xlpm.p,2)="DB",ISNUMBER(SEARCH("-2",_xlpm.p))),"DB-2", IF(LEFT(_xlpm.p,3)="OC-","OC", LEFT(_xlpm.p,_xlfn.XMATCH(TRUE,ISNUMBER(--MID(_xlpm.p,_xlfn.SEQUENCE(LEN(_xlpm.p)),1)))-1) ) ), _xlpm.p ), _xlpm.productType,_xlfn.XLOOKUP(_xlpm.code,'Product Code'!A:A,'Product Code'!D:D,""), IF(OR(RIGHT(_xlpm.p,5)="-Door",RIGHT(_xlpm.p,6)="-DOORS"),_xlpm.productType&" - Door",_xlpm.productType) )} -> x | J25: x | K25: 33 | L25: 34.5 | M25: 24 | N25: =IF(ISNUMBER(SEARCH("Cabinet",F25))=FALSE,"N/A",IF(K25>=24,2,1)) -> 2 | O25: =IF(ISNUMBER(SEARCH("Cabinet",F25))=FALSE,"N/A", IF(ISNUMBER(SEARCH("DB",E25)), IF(ISNUMBER(SEARCH("-2",E25)),2,3), IF(ISNUMBER(SEARCH("-PO",E25)),1, IF(LEFT(E25,1)="B",1,0) ) ) ) -> 0
A26: F9-LS3612 | B26: 1478 | C26: =B26*0.3 -> 443.4 | D26: =C26*1.13 -> 501.042 | E26: =_xlfn.TEXTAFTER(A26,"-") -> LS3612 | F26: {=_xlfn.LET( _xlpm.p,E26, _xlpm.code,IFERROR( IF(AND(LEFT(_xlpm.p,2)="DB",ISNUMBER(SEARCH("-2",_xlpm.p))),"DB-2", IF(LEFT(_xlpm.p,3)="OC-","OC", LEFT(_xlpm.p,_xlfn.XMATCH(TRUE,ISNUMBER(--MID(_xlpm.p,_xlfn.SEQUENCE(LEN(_xlpm.p)),1)))-1) ) ), _xlpm.p ), _xlfn.XLOOKUP(_xlpm.code,'Product Code'!A:A,'Product Code'!B:B,"") )} -> Base Cabinet | G26: {=_xlfn.LET( _xlpm.p,E26, _xlpm.code,IFERROR( IF(AND(LEFT(_xlpm.p,2)="DB",ISNUMBER(SEARCH("-2",_xlpm.p))),"DB-2", IF(LEFT(_xlpm.p,3)="OC-","OC", LEFT(_xlpm.p,_xlfn.XMATCH(TRUE,ISNUMBER(--MID(_xlpm.p,_xlfn.SEQUENCE(LEN(_xlpm.p)),1)))-1) ) ), _xlpm.p ), _xlpm.base,_xlfn.XLOOKUP(_xlpm.code,'Product Code'!A:A,'Product Code'!C:C,""), IF(RIGHT(_xlpm.p,3)="-PO",_xlpm.base&" - Pull-Out",_xlpm.base) )} -> Corner (90deg) | H26: Complete Cabinet | I26: {=_xlfn.LET( _xlpm.p,E26, _xlpm.code,IFERROR( IF(AND(LEFT(_xlpm.p,2)="DB",ISNUMBER(SEARCH("-2",_xlpm.p))),"DB-2", IF(LEFT(_xlpm.p,3)="OC-","OC", LEFT(_xlpm.p,_xlfn.XMATCH(TRUE,ISNUMBER(--MID(_xlpm.p,_xlfn.SEQUENCE(LEN(_xlpm.p)),1)))-1) ) ), _xlpm.p ), _xlpm.productType,_xlfn.XLOOKUP(_xlpm.code,'Product Code'!A:A,'Product Code'!D:D,""), IF(OR(RIGHT(_xlpm.p,5)="-Door",RIGHT(_xlpm.p,6)="-DOORS"),_xlpm.productType&" - Door",_xlpm.productType) )} -> x | J26: x | K26: 36 | L26: 34.5 | M26: 24 | N26: 0 | O26: 3
A27: F9-SP06 | B27: 554 | C27: =B27*0.3 -> 166.2 | E27: =_xlfn.TEXTAFTER(A27,"-") -> SP06 | F27: {=_xlfn.LET( _xlpm.p,E27, _xlpm.code,IFERROR( IF(AND(LEFT(_xlpm.p,2)="DB",ISNUMBER(SEARCH("-2",_xlpm.p))),"DB-2", IF(LEFT(_xlpm.p,3)="OC-","OC", LEFT(_xlpm.p,_xlfn.XMATCH(TRUE,ISNUMBER(--MID(_xlpm.p,_xlfn.SEQUENCE(LEN(_xlpm.p)),1)))-1) ) ), _xlpm.p ), _xlfn.XLOOKUP(_xlpm.code,'Product Code'!A:A,'Product Code'!B:B,"") )} -> Base Cabinet | G27: {=_xlfn.LET( _xlpm.p,E27, _xlpm.code,IFERROR( IF(AND(LEFT(_xlpm.p,2)="DB",ISNUMBER(SEARCH("-2",_xlpm.p))),"DB-2", IF(LEFT(_xlpm.p,3)="OC-","OC", LEFT(_xlpm.p,_xlfn.XMATCH(TRUE,ISNUMBER(--MID(_xlpm.p,_xlfn.SEQUENCE(LEN(_xlpm.p)),1)))-1) ) ), _xlpm.p ), _xlpm.base,_xlfn.XLOOKUP(_xlpm.code,'Product Code'!A:A,'Product Code'!C:C,""), IF(RIGHT(_xlpm.p,3)="-PO",_xlpm.base&" - Pull-Out",_xlpm.base) )} -> Spice Rack - Pull-Out | H27: Complete Cabinet | I27: {=_xlfn.LET( _xlpm.p,E27, _xlpm.code,IFERROR( IF(AND(LEFT(_xlpm.p,2)="DB",ISNUMBER(SEARCH("-2",_xlpm.p))),"DB-2", IF(LEFT(_xlpm.p,3)="OC-","OC", LEFT(_xlpm.p,_xlfn.XMATCH(TRUE,ISNUMBER(--MID(_xlpm.p,_xlfn.SEQUENCE(LEN(_xlpm.p)),1)))-1) ) ), _xlpm.p ), _xlpm.productType,_xlfn.XLOOKUP(_xlpm.code,'Product Code'!A:A,'Product Code'!D:D,""), IF(OR(RIGHT(_xlpm.p,5)="-Door",RIGHT(_xlpm.p,6)="-DOORS"),_xlpm.productType&" - Door",_xlpm.productType) )} -> x | J27: x | K27: 6 | L27: 34.5 | M27: 24 | N27: 0 | O27: 3
A28: F9-SP09 | B28: 611 | C28: =B28*0.3 -> 183.3 | D28: =C28*1.13 -> 207.129 | E28: =_xlfn.TEXTAFTER(A28,"-") -> SP09 | F28: {=_xlfn.LET( _xlpm.p,E28, _xlpm.code,IFERROR( IF(AND(LEFT(_xlpm.p,2)="DB",ISNUMBER(SEARCH("-2",_xlpm.p))),"DB-2", IF(LEFT(_xlpm.p,3)="OC-","OC", LEFT(_xlpm.p,_xlfn.XMATCH(TRUE,ISNUMBER(--MID(_xlpm.p,_xlfn.SEQUENCE(LEN(_xlpm.p)),1)))-1) ) ), _xlpm.p ), _xlfn.XLOOKUP(_xlpm.code,'Product Code'!A:A,'Product Code'!B:B,"") )} -> Base Cabinet | G28: {=_xlfn.LET( _xlpm.p,E28, _xlpm.code,IFERROR( IF(AND(LEFT(_xlpm.p,2)="DB",ISNUMBER(SEARCH("-2",_xlpm.p))),"DB-2", IF(LEFT(_xlpm.p,3)="OC-","OC", LEFT(_xlpm.p,_xlfn.XMATCH(TRUE,ISNUMBER(--MID(_xlpm.p,_xlfn.SEQUENCE(LEN(_xlpm.p)),1)))-1) ) ), _xlpm.p ), _xlpm.base,_xlfn.XLOOKUP(_xlpm.code,'Product Code'!A:A,'Product Code'!C:C,""), IF(RIGHT(_xlpm.p,3)="-PO",_xlpm.base&" - Pull-Out",_xlpm.base) )} -> Spice Rack - Pull-Out | H28: Complete Cabinet | I28: {=_xlfn.LET( _xlpm.p,E28, _xlpm.code,IFERROR( IF(AND(LEFT(_xlpm.p,2)="DB",ISNUMBER(SEARCH("-2",_xlpm.p))),"DB-2", IF(LEFT(_xlpm.p,3)="OC-","OC", LEFT(_xlpm.p,_xlfn.XMATCH(TRUE,ISNUMBER(--MID(_xlpm.p,_xlfn.SEQUENCE(LEN(_xlpm.p)),1)))-1) ) ), _xlpm.p ), _xlpm.productType,_xlfn.XLOOKUP(_xlpm.code,'Product Code'!A:A,'Product Code'!D:D,""), IF(OR(RIGHT(_xlpm.p,5)="-Door",RIGHT(_xlpm.p,6)="-DOORS"),_xlpm.productType&" - Door",_xlpm.productType) )} -> x | J28: x | K28: 9 | L28: 34.5 | M28: 24 | N28: 0 | O28: 3
A29: F9-SP12 | B29: 660 | C29: =B29*0.3 -> 198 | D29: =C29*1.13 -> 223.74 | E29: =_xlfn.TEXTAFTER(A29,"-") -> SP12 | F29: {=_xlfn.LET( _xlpm.p,E29, _xlpm.code,IFERROR( IF(AND(LEFT(_xlpm.p,2)="DB",ISNUMBER(SEARCH("-2",_xlpm.p))),"DB-2", IF(LEFT(_xlpm.p,3)="OC-","OC", LEFT(_xlpm.p,_xlfn.XMATCH(TRUE,ISNUMBER(--MID(_xlpm.p,_xlfn.SEQUENCE(LEN(_xlpm.p)),1)))-1) ) ), _xlpm.p ), _xlfn.XLOOKUP(_xlpm.code,'Product Code'!A:A,'Product Code'!B:B,"") )} -> Base Cabinet | G29: {=_xlfn.LET( _xlpm.p,E29, _xlpm.code,IFERROR( IF(AND(LEFT(_xlpm.p,2)="DB",ISNUMBER(SEARCH("-2",_xlpm.p))),"DB-2", IF(LEFT(_xlpm.p,3)="OC-","OC", LEFT(_xlpm.p,_xlfn.XMATCH(TRUE,ISNUMBER(--MID(_xlpm.p,_xlfn.SEQUENCE(LEN(_xlpm.p)),1)))-1) ) ), _xlpm.p ), _xlpm.base,_xlfn.XLOOKUP(_xlpm.code,'Product Code'!A:A,'Product Code'!C:C,""), IF(RIGHT(_xlpm.p,3)="-PO",_xlpm.base&" - Pull-Out",_xlpm.base) )} -> Spice Rack - Pull-Out | H29: Complete Cabinet | I29: {=_xlfn.LET( _xlpm.p,E29, _xlpm.code,IFERROR( IF(AND(LEFT(_xlpm.p,2)="DB",ISNUMBER(SEARCH("-2",_xlpm.p))),"DB-2", IF(LEFT(_xlpm.p,3)="OC-","OC", LEFT(_xlpm.p,_xlfn.XMATCH(TRUE,ISNUMBER(--MID(_xlpm.p,_xlfn.SEQUENCE(LEN(_xlpm.p)),1)))-1) ) ), _xlpm.p ), _xlpm.productType,_xlfn.XLOOKUP(_xlpm.code,'Product Code'!A:A,'Product Code'!D:D,""), IF(OR(RIGHT(_xlpm.p,5)="-Door",RIGHT(_xlpm.p,6)="-DOORS"),_xlpm.productType&" - Door",_xlpm.productType) )} -> x | J29: x | K29: 12 | L29: 34.5 | M29: 24 | N29: 0 | O29: 3
A30: F9-BMC27 | B30: 1241 | C30: =B30*0.3 -> 372.3 | E30: =_xlfn.TEXTAFTER(A30,"-") -> BMC27 | F30: {=_xlfn.LET( _xlpm.p,E30, _xlpm.code,IFERROR( IF(AND(LEFT(_xlpm.p,2)="DB",ISNUMBER(SEARCH("-2",_xlpm.p))),"DB-2", IF(LEFT(_xlpm.p,3)="OC-","OC", LEFT(_xlpm.p,_xlfn.XMATCH(TRUE,ISNUMBER(--MID(_xlpm.p,_xlfn.SEQUENCE(LEN(_xlpm.p)),1)))-1) ) ), _xlpm.p ), _xlfn.XLOOKUP(_xlpm.code,'Product Code'!A:A,'Product Code'!B:B,"") )} -> Base Microwave Cabinet | G30: {=_xlfn.LET( _xlpm.p,E30, _xlpm.code,IFERROR( IF(AND(LEFT(_xlpm.p,2)="DB",ISNUMBER(SEARCH("-2",_xlpm.p))),"DB-2", IF(LEFT(_xlpm.p,3)="OC-","OC", LEFT(_xlpm.p,_xlfn.XMATCH(TRUE,ISNUMBER(--MID(_xlpm.p,_xlfn.SEQUENCE(LEN(_xlpm.p)),1)))-1) ) ), _xlpm.p ), _xlpm.base,_xlfn.XLOOKUP(_xlpm.code,'Product Code'!A:A,'Product Code'!C:C,""), IF(RIGHT(_xlpm.p,3)="-PO",_xlpm.base&" - Pull-Out",_xlpm.base) )} -> 0 | I30: {=_xlfn.LET( _xlpm.p,E30, _xlpm.code,IFERROR( IF(AND(LEFT(_xlpm.p,2)="DB",ISNUMBER(SEARCH("-2",_xlpm.p))),"DB-2", IF(LEFT(_xlpm.p,3)="OC-","OC", LEFT(_xlpm.p,_xlfn.XMATCH(TRUE,ISNUMBER(--MID(_xlpm.p,_xlfn.SEQUENCE(LEN(_xlpm.p)),1)))-1) ) ), _xlpm.p ), _xlpm.productType,_xlfn.XLOOKUP(_xlpm.code,'Product Code'!A:A,'Product Code'!D:D,""), IF(OR(RIGHT(_xlpm.p,5)="-Door",RIGHT(_xlpm.p,6)="-DOORS"),_xlpm.productType&" - Door",_xlpm.productType) )} -> - | N30: 0 | O30: 3
A31: F9-FB09 | B31: 492 | C31: =B31*0.3 -> 147.6 | E31: =_xlfn.TEXTAFTER(A31,"-") -> FB09 | F31: {=_xlfn.LET( _xlpm.p,E31, _xlpm.code,IFERROR( IF(AND(LEFT(_xlpm.p,2)="DB",ISNUMBER(SEARCH("-2",_xlpm.p))),"DB-2", IF(LEFT(_xlpm.p,3)="OC-","OC", LEFT(_xlpm.p,_xlfn.XMATCH(TRUE,ISNUMBER(--MID(_xlpm.p,_xlfn.SEQUENCE(LEN(_xlpm.p)),1)))-1) ) ), _xlpm.p ), _xlfn.XLOOKUP(_xlpm.code,'Product Code'!A:A,'Product Code'!B:B,"") )} -> Bathroom - Base Cabinet | G31: {=_xlfn.LET( _xlpm.p,E31, _xlpm.code,IFERROR( IF(AND(LEFT(_xlpm.p,2)="DB",ISNUMBER(SEARCH("-2",_xlpm.p))),"DB-2", IF(LEFT(_xlpm.p,3)="OC-","OC", LEFT(_xlpm.p,_xlfn.XMATCH(TRUE,ISNUMBER(--MID(_xlpm.p,_xlfn.SEQUENCE(LEN(_xlpm.p)),1)))-1) ) ), _xlpm.p ), _xlpm.base,_xlfn.XLOOKUP(_xlpm.code,'Product Code'!A:A,'Product Code'!C:C,""), IF(RIGHT(_xlpm.p,3)="-PO",_xlpm.base&" - Pull-Out",_xlpm.base) )} -> 0 | I31: {=_xlfn.LET( _xlpm.p,E31, _xlpm.code,IFERROR( IF(AND(LEFT(_xlpm.p,2)="DB",ISNUMBER(SEARCH("-2",_xlpm.p))),"DB-2", IF(LEFT(_xlpm.p,3)="OC-","OC", LEFT(_xlpm.p,_xlfn.XMATCH(TRUE,ISNUMBER(--MID(_xlpm.p,_xlfn.SEQUENCE(LEN(_xlpm.p)),1)))-1) ) ), _xlpm.p ), _xlpm.productType,_xlfn.XLOOKUP(_xlpm.code,'Product Code'!A:A,'Product Code'!D:D,""), IF(OR(RIGHT(_xlpm.p,5)="-Door",RIGHT(_xlpm.p,6)="-DOORS"),_xlpm.productType&" - Door",_xlpm.productType) )} -> - | N31: 0 | O31: 3
A32: F9-FB12 | B32: 545 | C32: =B32*0.3 -> 163.5 | E32: =_xlfn.TEXTAFTER(A32,"-") -> FB12 | F32: {=_xlfn.LET( _xlpm.p,E32, _xlpm.code,IFERROR( IF(AND(LEFT(_xlpm.p,2)="DB",ISNUMBER(SEARCH("-2",_xlpm.p))),"DB-2", IF(LEFT(_xlpm.p,3)="OC-","OC", LEFT(_xlpm.p,_xlfn.XMATCH(TRUE,ISNUMBER(--MID(_xlpm.p,_xlfn.SEQUENCE(LEN(_xlpm.p)),1)))-1) ) ), _xlpm.p ), _xlfn.XLOOKUP(_xlpm.code,'Product Code'!A:A,'Product Code'!B:B,"") )} -> Bathroom - Base Cabinet | G32: {=_xlfn.LET( _xlpm.p,E32, _xlpm.code,IFERROR( IF(AND(LEFT(_xlpm.p,2)="DB",ISNUMBER(SEARCH("-2",_xlpm.p))),"DB-2", IF(LEFT(_xlpm.p,3)="OC-","OC", LEFT(_xlpm.p,_xlfn.XMATCH(TRUE,ISNUMBER(--MID(_xlpm.p,_xlfn.SEQUENCE(LEN(_xlpm.p)),1)))-1) ) ), _xlpm.p ), _xlpm.base,_xlfn.XLOOKUP(_xlpm.code,'Product Code'!A:A,'Product Code'!C:C,""), IF(RIGHT(_xlpm.p,3)="-PO",_xlpm.base&" - Pull-Out",_xlpm.base) )} -> 0 | I32: {=_xlfn.LET( _xlpm.p,E32, _xlpm.code,IFERROR( IF(AND(LEFT(_xlpm.p,2)="DB",ISNUMBER(SEARCH("-2",_xlpm.p))),"DB-2", IF(LEFT(_xlpm.p,3)="OC-","OC", LEFT(_xlpm.p,_xlfn.XMATCH(TRUE,ISNUMBER(--MID(_xlpm.p,_xlfn.SEQUENCE(LEN(_xlpm.p)),1)))-1) ) ), _xlpm.p ), _xlpm.productType,_xlfn.XLOOKUP(_xlpm.code,'Product Code'!A:A,'Product Code'!D:D,""), IF(OR(RIGHT(_xlpm.p,5)="-Door",RIGHT(_xlpm.p,6)="-DOORS"),_xlpm.productType&" - Door",_xlpm.productType) )} -> - | N32: 0 | O32: 2
A33: F9-FB15 | B33: 616 | C33: =B33*0.3 -> 184.8 | E33: =_xlfn.TEXTAFTER(A33,"-") -> FB15 | F33: {=_xlfn.LET( _xlpm.p,E33, _xlpm.code,IFERROR( IF(AND(LEFT(_xlpm.p,2)="DB",ISNUMBER(SEARCH("-2",_xlpm.p))),"DB-2", IF(LEFT(_xlpm.p,3)="OC-","OC", LEFT(_xlpm.p,_xlfn.XMATCH(TRUE,ISNUMBER(--MID(_xlpm.p,_xlfn.SEQUENCE(LEN(_xlpm.p)),1)))-1) ) ), _xlpm.p ), _xlfn.XLOOKUP(_xlpm.code,'Product Code'!A:A,'Product Code'!B:B,"") )} -> Bathroom - Base Cabinet | G33: {=_xlfn.LET( _xlpm.p,E33, _xlpm.code,IFERROR( IF(AND(LEFT(_xlpm.p,2)="DB",ISNUMBER(SEARCH("-2",_xlpm.p))),"DB-2", IF(LEFT(_xlpm.p,3)="OC-","OC", LEFT(_xlpm.p,_xlfn.XMATCH(TRUE,ISNUMBER(--MID(_xlpm.p,_xlfn.SEQUENCE(LEN(_xlpm.p)),1)))-1) ) ), _xlpm.p ), _xlpm.base,_xlfn.XLOOKUP(_xlpm.code,'Product Code'!A:A,'Product Code'!C:C,""), IF(RIGHT(_xlpm.p,3)="-PO",_xlpm.base&" - Pull-Out",_xlpm.base) )} -> 0 | I33: {=_xlfn.LET( _xlpm.p,E33, _xlpm.code,IFERROR( IF(AND(LEFT(_xlpm.p,2)="DB",ISNUMBER(SEARCH("-2",_xlpm.p))),"DB-2", IF(LEFT(_xlpm.p,3)="OC-","OC", LEFT(_xlpm.p,_xlfn.XMATCH(TRUE,ISNUMBER(--MID(_xlpm.p,_xlfn.SEQUENCE(LEN(_xlpm.p)),1)))-1) ) ), _xlpm.p ), _xlpm.productType,_xlfn.XLOOKUP(_xlpm.code,'Product Code'!A:A,'Product Code'!D:D,""), IF(OR(RIGHT(_xlpm.p,5)="-Door",RIGHT(_xlpm.p,6)="-DOORS"),_xlpm.productType&" - Door",_xlpm.productType) )} -> - | N33: 0 | O33: 3
A34: F9-FB18 | B34: 670 | C34: =B34*0.3 -> 201 | E34: =_xlfn.TEXTAFTER(A34,"-") -> FB18 | F34: {=_xlfn.LET( _xlpm.p,E34, _xlpm.code,IFERROR( IF(AND(LEFT(_xlpm.p,2)="DB",ISNUMBER(SEARCH("-2",_xlpm.p))),"DB-2", IF(LEFT(_xlpm.p,3)="OC-","OC", LEFT(_xlpm.p,_xlfn.XMATCH(TRUE,ISNUMBER(--MID(_xlpm.p,_xlfn.SEQUENCE(LEN(_xlpm.p)),1)))-1) ) ), _xlpm.p ), _xlfn.XLOOKUP(_xlpm.code,'Product Code'!A:A,'Product Code'!B:B,"") )} -> Bathroom - Base Cabinet | G34: {=_xlfn.LET( _xlpm.p,E34, _xlpm.code,IFERROR( IF(AND(LEFT(_xlpm.p,2)="DB",ISNUMBER(SEARCH("-2",_xlpm.p))),"DB-2", IF(LEFT(_xlpm.p,3)="OC-","OC", LEFT(_xlpm.p,_xlfn.XMATCH(TRUE,ISNUMBER(--MID(_xlpm.p,_xlfn.SEQUENCE(LEN(_xlpm.p)),1)))-1) ) ), _xlpm.p ), _xlpm.base,_xlfn.XLOOKUP(_xlpm.code,'Product Code'!A:A,'Product Code'!C:C,""), IF(RIGHT(_xlpm.p,3)="-PO",_xlpm.base&" - Pull-Out",_xlpm.base) )} -> 0 | I34: {=_xlfn.LET( _xlpm.p,E34, _xlpm.code,IFERROR( IF(AND(LEFT(_xlpm.p,2)="DB",ISNUMBER(SEARCH("-2",_xlpm.p))),"DB-2", IF(LEFT(_xlpm.p,3)="OC-","OC", LEFT(_xlpm.p,_xlfn.XMATCH(TRUE,ISNUMBER(--MID(_xlpm.p,_xlfn.SEQUENCE(LEN(_xlpm.p)),1)))-1) ) ), _xlpm.p ), _xlpm.productType,_xlfn.XLOOKUP(_xlpm.code,'Product Code'!A:A,'Product Code'!D:D,""), IF(OR(RIGHT(_xlpm.p,5)="-Door",RIGHT(_xlpm.p,6)="-DOORS"),_xlpm.productType&" - Door",_xlpm.productType) )} -> - | N34: 0 | O34: 2
A35: F9-FB21 | B35: 732 | C35: =B35*0.3 -> 219.6 | E35: =_xlfn.TEXTAFTER(A35,"-") -> FB21 | F35: {=_xlfn.LET( _xlpm.p,E35, _xlpm.code,IFERROR( IF(AND(LEFT(_xlpm.p,2)="DB",ISNUMBER(SEARCH("-2",_xlpm.p))),"DB-2", IF(LEFT(_xlpm.p,3)="OC-","OC", LEFT(_xlpm.p,_xlfn.XMATCH(TRUE,ISNUMBER(--MID(_xlpm.p,_xlfn.SEQUENCE(LEN(_xlpm.p)),1)))-1) ) ), _xlpm.p ), _xlfn.XLOOKUP(_xlpm.code,'Product Code'!A:A,'Product Code'!B:B,"") )} -> Bathroom - Base Cabinet | G35: {=_xlfn.LET( _xlpm.p,E35, _xlpm.code,IFERROR( IF(AND(LEFT(_xlpm.p,2)="DB",ISNUMBER(SEARCH("-2",_xlpm.p))),"DB-2", IF(LEFT(_xlpm.p,3)="OC-","OC", LEFT(_xlpm.p,_xlfn.XMATCH(TRUE,ISNUMBER(--MID(_xlpm.p,_xlfn.SEQUENCE(LEN(_xlpm.p)),1)))-1) ) ), _xlpm.p ), _xlpm.base,_xlfn.XLOOKUP(_xlpm.code,'Product Code'!A:A,'Product Code'!C:C,""), IF(RIGHT(_xlpm.p,3)="-PO",_xlpm.base&" - Pull-Out",_xlpm.base) )} -> 0 | I35: {=_xlfn.LET( _xlpm.p,E35, _xlpm.code,IFERROR( IF(AND(LEFT(_xlpm.p,2)="DB",ISNUMBER(SEARCH("-2",_xlpm.p))),"DB-2", IF(LEFT(_xlpm.p,3)="OC-","OC", LEFT(_xlpm.p,_xlfn.XMATCH(TRUE,ISNUMBER(--MID(_xlpm.p,_xlfn.SEQUENCE(LEN(_xlpm.p)),1)))-1) ) ), _xlpm.p ), _xlpm.productType,_xlfn.XLOOKUP(_xlpm.code,'Product Code'!A:A,'Product Code'!D:D,""), IF(OR(RIGHT(_xlpm.p,5)="-Door",RIGHT(_xlpm.p,6)="-DOORS"),_xlpm.productType&" - Door",_xlpm.productType) )} -> - | N35: 0 | O35: 3
A36: F9-FB24 | B36: 817 | C36: =B36*0.3 -> 245.1 | E36: =_xlfn.TEXTAFTER(A36,"-") -> FB24 | F36: {=_xlfn.LET( _xlpm.p,E36, _xlpm.code,IFERROR( IF(AND(LEFT(_xlpm.p,2)="DB",ISNUMBER(SEARCH("-2",_xlpm.p))),"DB-2", IF(LEFT(_xlpm.p,3)="OC-","OC", LEFT(_xlpm.p,_xlfn.XMATCH(TRUE,ISNUMBER(--MID(_xlpm.p,_xlfn.SEQUENCE(LEN(_xlpm.p)),1)))-1) ) ), _xlpm.p ), _xlfn.XLOOKUP(_xlpm.code,'Product Code'!A:A,'Product Code'!B:B,"") )} -> Bathroom - Base Cabinet | G36: {=_xlfn.LET( _xlpm.p,E36, _xlpm.code,IFERROR( IF(AND(LEFT(_xlpm.p,2)="DB",ISNUMBER(SEARCH("-2",_xlpm.p))),"DB-2", IF(LEFT(_xlpm.p,3)="OC-","OC", LEFT(_xlpm.p,_xlfn.XMATCH(TRUE,ISNUMBER(--MID(_xlpm.p,_xlfn.SEQUENCE(LEN(_xlpm.p)),1)))-1) ) ), _xlpm.p ), _xlpm.base,_xlfn.XLOOKUP(_xlpm.code,'Product Code'!A:A,'Product Code'!C:C,""), IF(RIGHT(_xlpm.p,3)="-PO",_xlpm.base&" - Pull-Out",_xlpm.base) )} -> 0 | I36: {=_xlfn.LET( _xlpm.p,E36, _xlpm.code,IFERROR( IF(AND(LEFT(_xlpm.p,2)="DB",ISNUMBER(SEARCH("-2",_xlpm.p))),"DB-2", IF(LEFT(_xlpm.p,3)="OC-","OC", LEFT(_xlpm.p,_xlfn.XMATCH(TRUE,ISNUMBER(--MID(_xlpm.p,_xlfn.SEQUENCE(LEN(_xlpm.p)),1)))-1) ) ), _xlpm.p ), _xlpm.productType,_xlfn.XLOOKUP(_xlpm.code,'Product Code'!A:A,'Product Code'!D:D,""), IF(OR(RIGHT(_xlpm.p,5)="-Door",RIGHT(_xlpm.p,6)="-DOORS"),_xlpm.productType&" - Door",_xlpm.productType) )} -> - | N36: 0 | O36: 3
A37: F9-FB27 | B37: 875 | C37: =B37*0.3 -> 262.5 | E37: =_xlfn.TEXTAFTER(A37,"-") -> FB27 | F37: {=_xlfn.LET( _xlpm.p,E37, _xlpm.code,IFERROR( IF(AND(LEFT(_xlpm.p,2)="DB",ISNUMBER(SEARCH("-2",_xlpm.p))),"DB-2", IF(LEFT(_xlpm.p,3)="OC-","OC", LEFT(_xlpm.p,_xlfn.XMATCH(TRUE,ISNUMBER(--MID(_xlpm.p,_xlfn.SEQUENCE(LEN(_xlpm.p)),1)))-1) ) ), _xlpm.p ), _xlfn.XLOOKUP(_xlpm.code,'Product Code'!A:A,'Product Code'!B:B,"") )} -> Bathroom - Base Cabinet | G37: {=_xlfn.LET( _xlpm.p,E37, _xlpm.code,IFERROR( IF(AND(LEFT(_xlpm.p,2)="DB",ISNUMBER(SEARCH("-2",_xlpm.p))),"DB-2", IF(LEFT(_xlpm.p,3)="OC-","OC", LEFT(_xlpm.p,_xlfn.XMATCH(TRUE,ISNUMBER(--MID(_xlpm.p,_xlfn.SEQUENCE(LEN(_xlpm.p)),1)))-1) ) ), _xlpm.p ), _xlpm.base,_xlfn.XLOOKUP(_xlpm.code,'Product Code'!A:A,'Product Code'!C:C,""), IF(RIGHT(_xlpm.p,3)="-PO",_xlpm.base&" - Pull-Out",_xlpm.base) )} -> 0 | I37: {=_xlfn.LET( _xlpm.p,E37, _xlpm.code,IFERROR( IF(AND(LEFT(_xlpm.p,2)="DB",ISNUMBER(SEARCH("-2",_xlpm.p))),"DB-2", IF(LEFT(_xlpm.p,3)="OC-","OC", LEFT(_xlpm.p,_xlfn.XMATCH(TRUE,ISNUMBER(--MID(_xlpm.p,_xlfn.SEQUENCE(LEN(_xlpm.p)),1)))-1) ) ), _xlpm.p ), _xlpm.productType,_xlfn.XLOOKUP(_xlpm.code,'Product Code'!A:A,'Product Code'!D:D,""), IF(OR(RIGHT(_xlpm.p,5)="-Door",RIGHT(_xlpm.p,6)="-DOORS"),_xlpm.productType&" - Door",_xlpm.productType) )} -> - | N37: =IF(ISNUMBER(SEARCH("Cabinet",F37))=FALSE,"N/A",IF(K37>=24,2,1)) -> 1 | O37: =IF(ISNUMBER(SEARCH("Cabinet",F37))=FALSE,"N/A", IF(ISNUMBER(SEARCH("DB",E37)), IF(ISNUMBER(SEARCH("-2",E37)),2,3), IF(ISNUMBER(SEARCH("-PO",E37)),1, IF(LEFT(E37,1)="B",1,0) ) ) ) -> 0
A38: F9-FB30 | B38: 937 | C38: =B38*0.3 -> 281.1 | E38: =_xlfn.TEXTAFTER(A38,"-") -> FB30 | F38: {=_xlfn.LET( _xlpm.p,E38, _xlpm.code,IFERROR( IF(AND(LEFT(_xlpm.p,2)="DB",ISNUMBER(SEARCH("-2",_xlpm.p))),"DB-2", IF(LEFT(_xlpm.p,3)="OC-","OC", LEFT(_xlpm.p,_xlfn.XMATCH(TRUE,ISNUMBER(--MID(_xlpm.p,_xlfn.SEQUENCE(LEN(_xlpm.p)),1)))-1) ) ), _xlpm.p ), _xlfn.XLOOKUP(_xlpm.code,'Product Code'!A:A,'Product Code'!B:B,"") )} -> Bathroom - Base Cabinet | G38: {=_xlfn.LET( _xlpm.p,E38, _xlpm.code,IFERROR( IF(AND(LEFT(_xlpm.p,2)="DB",ISNUMBER(SEARCH("-2",_xlpm.p))),"DB-2", IF(LEFT(_xlpm.p,3)="OC-","OC", LEFT(_xlpm.p,_xlfn.XMATCH(TRUE,ISNUMBER(--MID(_xlpm.p,_xlfn.SEQUENCE(LEN(_xlpm.p)),1)))-1) ) ), _xlpm.p ), _xlpm.base,_xlfn.XLOOKUP(_xlpm.code,'Product Code'!A:A,'Product Code'!C:C,""), IF(RIGHT(_xlpm.p,3)="-PO",_xlpm.base&" - Pull-Out",_xlpm.base) )} -> 0 | I38: {=_xlfn.LET( _xlpm.p,E38, _xlpm.code,IFERROR( IF(AND(LEFT(_xlpm.p,2)="DB",ISNUMBER(SEARCH("-2",_xlpm.p))),"DB-2", IF(LEFT(_xlpm.p,3)="OC-","OC", LEFT(_xlpm.p,_xlfn.XMATCH(TRUE,ISNUMBER(--MID(_xlpm.p,_xlfn.SEQUENCE(LEN(_xlpm.p)),1)))-1) ) ), _xlpm.p ), _xlpm.productType,_xlfn.XLOOKUP(_xlpm.code,'Product Code'!A:A,'Product Code'!D:D,""), IF(OR(RIGHT(_xlpm.p,5)="-Door",RIGHT(_xlpm.p,6)="-DOORS"),_xlpm.productType&" - Door",_xlpm.productType) )} -> - | N38: =IF(ISNUMBER(SEARCH("Cabinet",F38))=FALSE,"N/A",IF(K38>=24,2,1)) -> 1 | O38: =IF(ISNUMBER(SEARCH("Cabinet",F38))=FALSE,"N/A", IF(ISNUMBER(SEARCH("DB",E38)), IF(ISNUMBER(SEARCH("-2",E38)),2,3), IF(ISNUMBER(SEARCH("-PO",E38)),1, IF(LEFT(E38,1)="B",1,0) ) ) ) -> 0
A39: F9-FB33 | B39: 991 | C39: =B39*0.3 -> 297.3 | E39: =_xlfn.TEXTAFTER(A39,"-") -> FB33 | F39: {=_xlfn.LET( _xlpm.p,E39, _xlpm.code,IFERROR( IF(AND(LEFT(_xlpm.p,2)="DB",ISNUMBER(SEARCH("-2",_xlpm.p))),"DB-2", IF(LEFT(_xlpm.p,3)="OC-","OC", LEFT(_xlpm.p,_xlfn.XMATCH(TRUE,ISNUMBER(--MID(_xlpm.p,_xlfn.SEQUENCE(LEN(_xlpm.p)),1)))-1) ) ), _xlpm.p ), _xlfn.XLOOKUP(_xlpm.code,'Product Code'!A:A,'Product Code'!B:B,"") )} -> Bathroom - Base Cabinet | G39: {=_xlfn.LET( _xlpm.p,E39, _xlpm.code,IFERROR( IF(AND(LEFT(_xlpm.p,2)="DB",ISNUMBER(SEARCH("-2",_xlpm.p))),"DB-2", IF(LEFT(_xlpm.p,3)="OC-","OC", LEFT(_xlpm.p,_xlfn.XMATCH(TRUE,ISNUMBER(--MID(_xlpm.p,_xlfn.SEQUENCE(LEN(_xlpm.p)),1)))-1) ) ), _xlpm.p ), _xlpm.base,_xlfn.XLOOKUP(_xlpm.code,'Product Code'!A:A,'Product Code'!C:C,""), IF(RIGHT(_xlpm.p,3)="-PO",_xlpm.base&" - Pull-Out",_xlpm.base) )} -> 0 | I39: {=_xlfn.LET( _xlpm.p,E39, _xlpm.code,IFERROR( IF(AND(LEFT(_xlpm.p,2)="DB",ISNUMBER(SEARCH("-2",_xlpm.p))),"DB-2", IF(LEFT(_xlpm.p,3)="OC-","OC", LEFT(_xlpm.p,_xlfn.XMATCH(TRUE,ISNUMBER(--MID(_xlpm.p,_xlfn.SEQUENCE(LEN(_xlpm.p)),1)))-1) ) ), _xlpm.p ), _xlpm.productType,_xlfn.XLOOKUP(_xlpm.code,'Product Code'!A:A,'Product Code'!D:D,""), IF(OR(RIGHT(_xlpm.p,5)="-Door",RIGHT(_xlpm.p,6)="-DOORS"),_xlpm.productType&" - Door",_xlpm.productType) )} -> - | N39: =IF(ISNUMBER(SEARCH("Cabinet",F39))=FALSE,"N/A",IF(K39>=24,2,1)) -> 1 | O39: =IF(ISNUMBER(SEARCH("Cabinet",F39))=FALSE,"N/A", IF(ISNUMBER(SEARCH("DB",E39)), IF(ISNUMBER(SEARCH("-2",E39)),2,3), IF(ISNUMBER(SEARCH("-PO",E39)),1, IF(LEFT(E39,1)="B",1,0) ) ) ) -> 0
A40: F9-FB36 | B40: 1046 | C40: =B40*0.3 -> 313.8 | E40: =_xlfn.TEXTAFTER(A40,"-") -> FB36 | F40: {=_xlfn.LET( _xlpm.p,E40, _xlpm.code,IFERROR( IF(AND(LEFT(_xlpm.p,2)="DB",ISNUMBER(SEARCH("-2",_xlpm.p))),"DB-2", IF(LEFT(_xlpm.p,3)="OC-","OC", LEFT(_xlpm.p,_xlfn.XMATCH(TRUE,ISNUMBER(--MID(_xlpm.p,_xlfn.SEQUENCE(LEN(_xlpm.p)),1)))-1) ) ), _xlpm.p ), _xlfn.XLOOKUP(_xlpm.code,'Product Code'!A:A,'Product Code'!B:B,"") )} -> Bathroom - Base Cabinet | G40: {=_xlfn.LET( _xlpm.p,E40, _xlpm.code,IFERROR( IF(AND(LEFT(_xlpm.p,2)="DB",ISNUMBER(SEARCH("-2",_xlpm.p))),"DB-2", IF(LEFT(_xlpm.p,3)="OC-","OC", LEFT(_xlpm.p,_xlfn.XMATCH(TRUE,ISNUMBER(--MID(_xlpm.p,_xlfn.SEQUENCE(LEN(_xlpm.p)),1)))-1) ) ), _xlpm.p ), _xlpm.base,_xlfn.XLOOKUP(_xlpm.code,'Product Code'!A:A,'Product Code'!C:C,""), IF(RIGHT(_xlpm.p,3)="-PO",_xlpm.base&" - Pull-Out",_xlpm.base) )} -> 0 | I40: {=_xlfn.LET( _xlpm.p,E40, _xlpm.code,IFERROR( IF(AND(LEFT(_xlpm.p,2)="DB",ISNUMBER(SEARCH("-2",_xlpm.p))),"DB-2", IF(LEFT(_xlpm.p,3)="OC-","OC", LEFT(_xlpm.p,_xlfn.XMATCH(TRUE,ISNUMBER(--MID(_xlpm.p,_xlfn.SEQUENCE(LEN(_xlpm.p)),1)))-1) ) ), _xlpm.p ), _xlpm.productType,_xlfn.XLOOKUP(_xlpm.code,'Product Code'!A:A,'Product Code'!D:D,""), IF(OR(RIGHT(_xlpm.p,5)="-Door",RIGHT(_xlpm.p,6)="-DOORS"),_xlpm.productType&" - Door",_xlpm.productType) )} -> - | N40: =IF(ISNUMBER(SEARCH("Cabinet",F40))=FALSE,"N/A",IF(K40>=24,2,1)) -> 1 | O40: =IF(ISNUMBER(SEARCH("Cabinet",F40))=FALSE,"N/A", IF(ISNUMBER(SEARCH("DB",E40)), IF(ISNUMBER(SEARCH("-2",E40)),2,3), IF(ISNUMBER(SEARCH("-PO",E40)),1, IF(LEFT(E40,1)="B",1,0) ) ) ) -> 0
A41: F9-FB39 | B41: 1109 | C41: =B41*0.3 -> 332.7 | E41: =_xlfn.TEXTAFTER(A41,"-") -> FB39 | F41: {=_xlfn.LET( _xlpm.p,E41, _xlpm.code,IFERROR( IF(AND(LEFT(_xlpm.p,2)="DB",ISNUMBER(SEARCH("-2",_xlpm.p))),"DB-2", IF(LEFT(_xlpm.p,3)="OC-","OC", LEFT(_xlpm.p,_xlfn.XMATCH(TRUE,ISNUMBER(--MID(_xlpm.p,_xlfn.SEQUENCE(LEN(_xlpm.p)),1)))-1) ) ), _xlpm.p ), _xlfn.XLOOKUP(_xlpm.code,'Product Code'!A:A,'Product Code'!B:B,"") )} -> Bathroom - Base Cabinet | G41: {=_xlfn.LET( _xlpm.p,E41, _xlpm.code,IFERROR( IF(AND(LEFT(_xlpm.p,2)="DB",ISNUMBER(SEARCH("-2",_xlpm.p))),"DB-2", IF(LEFT(_xlpm.p,3)="OC-","OC", LEFT(_xlpm.p,_xlfn.XMATCH(TRUE,ISNUMBER(--MID(_xlpm.p,_xlfn.SEQUENCE(LEN(_xlpm.p)),1)))-1) ) ), _xlpm.p ), _xlpm.base,_xlfn.XLOOKUP(_xlpm.code,'Product Code'!A:A,'Product Code'!C:C,""), IF(RIGHT(_xlpm.p,3)="-PO",_xlpm.base&" - Pull-Out",_xlpm.base) )} -> 0 | I41: {=_xlfn.LET( _xlpm.p,E41, _xlpm.code,IFERROR( IF(AND(LEFT(_xlpm.p,2)="DB",ISNUMBER(SEARCH("-2",_xlpm.p))),"DB-2", IF(LEFT(_xlpm.p,3)="OC-","OC", LEFT(_xlpm.p,_xlfn.XMATCH(TRUE,ISNUMBER(--MID(_xlpm.p,_xlfn.SEQUENCE(LEN(_xlpm.p)),1)))-1) ) ), _xlpm.p ), _xlpm.productType,_xlfn.XLOOKUP(_xlpm.code,'Product Code'!A:A,'Product Code'!D:D,""), IF(OR(RIGHT(_xlpm.p,5)="-Door",RIGHT(_xlpm.p,6)="-DOORS"),_xlpm.productType&" - Door",_xlpm.productType) )} -> - | N41: =IF(ISNUMBER(SEARCH("Cabinet",F41))=FALSE,"N/A",IF(K41>=24,2,1)) -> 1 | O41: =IF(ISNUMBER(SEARCH("Cabinet",F41))=FALSE,"N/A", IF(ISNUMBER(SEARCH("DB",E41)), IF(ISNUMBER(SEARCH("-2",E41)),2,3), IF(ISNUMBER(SEARCH("-PO",E41)),1, IF(LEFT(E41,1)="B",1,0) ) ) ) -> 0
A42: F9-FB42 | B42: 1140 | C42: =B42*0.3 -> 342 | E42: =_xlfn.TEXTAFTER(A42,"-") -> FB42 | F42: {=_xlfn.LET( _xlpm.p,E42, _xlpm.code,IFERROR( IF(AND(LEFT(_xlpm.p,2)="DB",ISNUMBER(SEARCH("-2",_xlpm.p))),"DB-2", IF(LEFT(_xlpm.p,3)="OC-","OC", LEFT(_xlpm.p,_xlfn.XMATCH(TRUE,ISNUMBER(--MID(_xlpm.p,_xlfn.SEQUENCE(LEN(_xlpm.p)),1)))-1) ) ), _xlpm.p ), _xlfn.XLOOKUP(_xlpm.code,'Product Code'!A:A,'Product Code'!B:B,"") )} -> Bathroom - Base Cabinet | G42: {=_xlfn.LET( _xlpm.p,E42, _xlpm.code,IFERROR( IF(AND(LEFT(_xlpm.p,2)="DB",ISNUMBER(SEARCH("-2",_xlpm.p))),"DB-2", IF(LEFT(_xlpm.p,3)="OC-","OC", LEFT(_xlpm.p,_xlfn.XMATCH(TRUE,ISNUMBER(--MID(_xlpm.p,_xlfn.SEQUENCE(LEN(_xlpm.p)),1)))-1) ) ), _xlpm.p ), _xlpm.base,_xlfn.XLOOKUP(_xlpm.code,'Product Code'!A:A,'Product Code'!C:C,""), IF(RIGHT(_xlpm.p,3)="-PO",_xlpm.base&" - Pull-Out",_xlpm.base) )} -> 0 | I42: {=_xlfn.LET( _xlpm.p,E42, _xlpm.code,IFERROR( IF(AND(LEFT(_xlpm.p,2)="DB",ISNUMBER(SEARCH("-2",_xlpm.p))),"DB-2", IF(LEFT(_xlpm.p,3)="OC-","OC", LEFT(_xlpm.p,_xlfn.XMATCH(TRUE,ISNUMBER(--MID(_xlpm.p,_xlfn.SEQUENCE(LEN(_xlpm.p)),1)))-1) ) ), _xlpm.p ), _xlpm.productType,_xlfn.XLOOKUP(_xlpm.code,'Product Code'!A:A,'Product Code'!D:D,""), IF(OR(RIGHT(_xlpm.p,5)="-Door",RIGHT(_xlpm.p,6)="-DOORS"),_xlpm.productType&" - Door",_xlpm.productType) )} -> - | N42: =IF(ISNUMBER(SEARCH("Cabinet",F42))=FALSE,"N/A",IF(K42>=24,2,1)) -> 1 | O42: =IF(ISNUMBER(SEARCH("Cabinet",F42))=FALSE,"N/A", IF(ISNUMBER(SEARCH("DB",E42)), IF(ISNUMBER(SEARCH("-2",E42)),2,3), IF(ISNUMBER(SEARCH("-PO",E42)),1, IF(LEFT(E42,1)="B",1,0) ) ) ) -> 0
A43: F9-VDB1221 | B43: 1013 | C43: =B43*0.3 -> 303.9 | E43: =_xlfn.TEXTAFTER(A43,"-") -> VDB1221 | F43: {=_xlfn.LET( _xlpm.p,E43, _xlpm.code,IFERROR( IF(AND(LEFT(_xlpm.p,2)="DB",ISNUMBER(SEARCH("-2",_xlpm.p))),"DB-2", IF(LEFT(_xlpm.p,3)="OC-","OC", LEFT(_xlpm.p,_xlfn.XMATCH(TRUE,ISNUMBER(--MID(_xlpm.p,_xlfn.SEQUENCE(LEN(_xlpm.p)),1)))-1) ) ), _xlpm.p ), _xlfn.XLOOKUP(_xlpm.code,'Product Code'!A:A,'Product Code'!B:B,"") )} -> Bathroom - Base Cabinet | G43: {=_xlfn.LET( _xlpm.p,E43, _xlpm.code,IFERROR( IF(AND(LEFT(_xlpm.p,2)="DB",ISNUMBER(SEARCH("-2",_xlpm.p))),"DB-2", IF(LEFT(_xlpm.p,3)="OC-","OC", LEFT(_xlpm.p,_xlfn.XMATCH(TRUE,ISNUMBER(--MID(_xlpm.p,_xlfn.SEQUENCE(LEN(_xlpm.p)),1)))-1) ) ), _xlpm.p ), _xlpm.base,_xlfn.XLOOKUP(_xlpm.code,'Product Code'!A:A,'Product Code'!C:C,""), IF(RIGHT(_xlpm.p,3)="-PO",_xlpm.base&" - Pull-Out",_xlpm.base) )} -> Drawer | I43: {=_xlfn.LET( _xlpm.p,E43, _xlpm.code,IFERROR( IF(AND(LEFT(_xlpm.p,2)="DB",ISNUMBER(SEARCH("-2",_xlpm.p))),"DB-2", IF(LEFT(_xlpm.p,3)="OC-","OC", LEFT(_xlpm.p,_xlfn.XMATCH(TRUE,ISNUMBER(--MID(_xlpm.p,_xlfn.SEQUENCE(LEN(_xlpm.p)),1)))-1) ) ), _xlpm.p ), _xlpm.productType,_xlfn.XLOOKUP(_xlpm.code,'Product Code'!A:A,'Product Code'!D:D,""), IF(OR(RIGHT(_xlpm.p,5)="-Door",RIGHT(_xlpm.p,6)="-DOORS"),_xlpm.productType&" - Door",_xlpm.productType) )} -> - | N43: =IF(ISNUMBER(SEARCH("Cabinet",F43))=FALSE,"N/A",IF(K43>=24,2,1)) -> 1 | O43: =IF(ISNUMBER(SEARCH("Cabinet",F43))=FALSE,"N/A", IF(ISNUMBER(SEARCH("DB",E43)), IF(ISNUMBER(SEARCH("-2",E43)),2,3), IF(ISNUMBER(SEARCH("-PO",E43)),1, IF(LEFT(E43,1)="B",1,0) ) ) ) -> 3
A44: F9-VDB1521 | B44: 1098 | C44: =B44*0.3 -> 329.4 | E44: =_xlfn.TEXTAFTER(A44,"-") -> VDB1521 | F44: {=_xlfn.LET( _xlpm.p,E44, _xlpm.code,IFERROR( IF(AND(LEFT(_xlpm.p,2)="DB",ISNUMBER(SEARCH("-2",_xlpm.p))),"DB-2", IF(LEFT(_xlpm.p,3)="OC-","OC", LEFT(_xlpm.p,_xlfn.XMATCH(TRUE,ISNUMBER(--MID(_xlpm.p,_xlfn.SEQUENCE(LEN(_xlpm.p)),1)))-1) ) ), _xlpm.p ), _xlfn.XLOOKUP(_xlpm.code,'Product Code'!A:A,'Product Code'!B:B,"") )} -> Bathroom - Base Cabinet | G44: {=_xlfn.LET( _xlpm.p,E44, _xlpm.code,IFERROR( IF(AND(LEFT(_xlpm.p,2)="DB",ISNUMBER(SEARCH("-2",_xlpm.p))),"DB-2", IF(LEFT(_xlpm.p,3)="OC-","OC", LEFT(_xlpm.p,_xlfn.XMATCH(TRUE,ISNUMBER(--MID(_xlpm.p,_xlfn.SEQUENCE(LEN(_xlpm.p)),1)))-1) ) ), _xlpm.p ), _xlpm.base,_xlfn.XLOOKUP(_xlpm.code,'Product Code'!A:A,'Product Code'!C:C,""), IF(RIGHT(_xlpm.p,3)="-PO",_xlpm.base&" - Pull-Out",_xlpm.base) )} -> Drawer | I44: {=_xlfn.LET( _xlpm.p,E44, _xlpm.code,IFERROR( IF(AND(LEFT(_xlpm.p,2)="DB",ISNUMBER(SEARCH("-2",_xlpm.p))),"DB-2", IF(LEFT(_xlpm.p,3)="OC-","OC", LEFT(_xlpm.p,_xlfn.XMATCH(TRUE,ISNUMBER(--MID(_xlpm.p,_xlfn.SEQUENCE(LEN(_xlpm.p)),1)))-1) ) ), _xlpm.p ), _xlpm.productType,_xlfn.XLOOKUP(_xlpm.code,'Product Code'!A:A,'Product Code'!D:D,""), IF(OR(RIGHT(_xlpm.p,5)="-Door",RIGHT(_xlpm.p,6)="-DOORS"),_xlpm.productType&" - Door",_xlpm.productType) )} -> - | N44: =IF(ISNUMBER(SEARCH("Cabinet",F44))=FALSE,"N/A",IF(K44>=24,2,1)) -> 1 | O44: =IF(ISNUMBER(SEARCH("Cabinet",F44))=FALSE,"N/A", IF(ISNUMBER(SEARCH("DB",E44)), IF(ISNUMBER(SEARCH("-2",E44)),2,3), IF(ISNUMBER(SEARCH("-PO",E44)),1, IF(LEFT(E44,1)="B",1,0) ) ) ) -> 3
A45: F9-VDB1821 | B45: 1141 | C45: =B45*0.3 -> 342.3 | E45: =_xlfn.TEXTAFTER(A45,"-") -> VDB1821 | F45: {=_xlfn.LET( _xlpm.p,E45, _xlpm.code,IFERROR( IF(AND(LEFT(_xlpm.p,2)="DB",ISNUMBER(SEARCH("-2",_xlpm.p))),"DB-2", IF(LEFT(_xlpm.p,3)="OC-","OC", LEFT(_xlpm.p,_xlfn.XMATCH(TRUE,ISNUMBER(--MID(_xlpm.p,_xlfn.SEQUENCE(LEN(_xlpm.p)),1)))-1) ) ), _xlpm.p ), _xlfn.XLOOKUP(_xlpm.code,'Product Code'!A:A,'Product Code'!B:B,"") )} -> Bathroom - Base Cabinet | G45: {=_xlfn.LET( _xlpm.p,E45, _xlpm.code,IFERROR( IF(AND(LEFT(_xlpm.p,2)="DB",ISNUMBER(SEARCH("-2",_xlpm.p))),"DB-2", IF(LEFT(_xlpm.p,3)="OC-","OC", LEFT(_xlpm.p,_xlfn.XMATCH(TRUE,ISNUMBER(--MID(_xlpm.p,_xlfn.SEQUENCE(LEN(_xlpm.p)),1)))-1) ) ), _xlpm.p ), _xlpm.base,_xlfn.XLOOKUP(_xlpm.code,'Product Code'!A:A,'Product Code'!C:C,""), IF(RIGHT(_xlpm.p,3)="-PO",_xlpm.base&" - Pull-Out",_xlpm.base) )} -> Drawer | I45: {=_xlfn.LET( _xlpm.p,E45, _xlpm.code,IFERROR( IF(AND(LEFT(_xlpm.p,2)="DB",ISNUMBER(SEARCH("-2",_xlpm.p))),"DB-2", IF(LEFT(_xlpm.p,3)="OC-","OC", LEFT(_xlpm.p,_xlfn.XMATCH(TRUE,ISNUMBER(--MID(_xlpm.p,_xlfn.SEQUENCE(LEN(_xlpm.p)),1)))-1) ) ), _xlpm.p ), _xlpm.productType,_xlfn.XLOOKUP(_xlpm.code,'Product Code'!A:A,'Product Code'!D:D,""), IF(OR(RIGHT(_xlpm.p,5)="-Door",RIGHT(_xlpm.p,6)="-DOORS"),_xlpm.productType&" - Door",_xlpm.productType) )} -> - | N45: =IF(ISNUMBER(SEARCH("Cabinet",F45))=FALSE,"N/A",IF(K45>=24,2,1)) -> 1 | O45: =IF(ISNUMBER(SEARCH("Cabinet",F45))=FALSE,"N/A", IF(ISNUMBER(SEARCH("DB",E45)), IF(ISNUMBER(SEARCH("-2",E45)),2,3), IF(ISNUMBER(SEARCH("-PO",E45)),1, IF(LEFT(E45,1)="B",1,0) ) ) ) -> 3
A46: F9-VS2421 | B46: 798 | C46: =B46*0.3 -> 239.4 | E46: =_xlfn.TEXTAFTER(A46,"-") -> VS2421 | F46: {=_xlfn.LET( _xlpm.p,E46, _xlpm.code,IFERROR( IF(AND(LEFT(_xlpm.p,2)="DB",ISNUMBER(SEARCH("-2",_xlpm.p))),"DB-2", IF(LEFT(_xlpm.p,3)="OC-","OC", LEFT(_xlpm.p,_xlfn.XMATCH(TRUE,ISNUMBER(--MID(_xlpm.p,_xlfn.SEQUENCE(LEN(_xlpm.p)),1)))-1) ) ), _xlpm.p ), _xlfn.XLOOKUP(_xlpm.code,'Product Code'!A:A,'Product Code'!B:B,"") )} -> Bathroom - Base Cabinet | G46: {=_xlfn.LET( _xlpm.p,E46, _xlpm.code,IFERROR( IF(AND(LEFT(_xlpm.p,2)="DB",ISNUMBER(SEARCH("-2",_xlpm.p))),"DB-2", IF(LEFT(_xlpm.p,3)="OC-","OC", LEFT(_xlpm.p,_xlfn.XMATCH(TRUE,ISNUMBER(--MID(_xlpm.p,_xlfn.SEQUENCE(LEN(_xlpm.p)),1)))-1) ) ), _xlpm.p ), _xlpm.base,_xlfn.XLOOKUP(_xlpm.code,'Product Code'!A:A,'Product Code'!C:C,""), IF(RIGHT(_xlpm.p,3)="-PO",_xlpm.base&" - Pull-Out",_xlpm.base) )} -> Sink | I46: {=_xlfn.LET( _xlpm.p,E46, _xlpm.code,IFERROR( IF(AND(LEFT(_xlpm.p,2)="DB",ISNUMBER(SEARCH("-2",_xlpm.p))),"DB-2", IF(LEFT(_xlpm.p,3)="OC-","OC", LEFT(_xlpm.p,_xlfn.XMATCH(TRUE,ISNUMBER(--MID(_xlpm.p,_xlfn.SEQUENCE(LEN(_xlpm.p)),1)))-1) ) ), _xlpm.p ), _xlpm.productType,_xlfn.XLOOKUP(_xlpm.code,'Product Code'!A:A,'Product Code'!D:D,""), IF(OR(RIGHT(_xlpm.p,5)="-Door",RIGHT(_xlpm.p,6)="-DOORS"),_xlpm.productType&" - Door",_xlpm.productType) )} -> - | N46: =IF(ISNUMBER(SEARCH("Cabinet",F46))=FALSE,"N/A",IF(K46>=24,2,1)) -> 1 | O46: =IF(ISNUMBER(SEARCH("Cabinet",F46))=FALSE,"N/A", IF(ISNUMBER(SEARCH("DB",E46)), IF(ISNUMBER(SEARCH("-2",E46)),2,3), IF(ISNUMBER(SEARCH("-PO",E46)),1, IF(LEFT(E46,1)="B",1,0) ) ) ) -> 0
A47: F9-VS3021 | B47: 910 | C47: =B47*0.3 -> 273 | E47: =_xlfn.TEXTAFTER(A47,"-") -> VS3021 | F47: {=_xlfn.LET( _xlpm.p,E47, _xlpm.code,IFERROR( IF(AND(LEFT(_xlpm.p,2)="DB",ISNUMBER(SEARCH("-2",_xlpm.p))),"DB-2", IF(LEFT(_xlpm.p,3)="OC-","OC", LEFT(_xlpm.p,_xlfn.XMATCH(TRUE,ISNUMBER(--MID(_xlpm.p,_xlfn.SEQUENCE(LEN(_xlpm.p)),1)))-1) ) ), _xlpm.p ), _xlfn.XLOOKUP(_xlpm.code,'Product Code'!A:A,'Product Code'!B:B,"") )} -> Bathroom - Base Cabinet | G47: {=_xlfn.LET( _xlpm.p,E47, _xlpm.code,IFERROR( IF(AND(LEFT(_xlpm.p,2)="DB",ISNUMBER(SEARCH("-2",_xlpm.p))),"DB-2", IF(LEFT(_xlpm.p,3)="OC-","OC", LEFT(_xlpm.p,_xlfn.XMATCH(TRUE,ISNUMBER(--MID(_xlpm.p,_xlfn.SEQUENCE(LEN(_xlpm.p)),1)))-1) ) ), _xlpm.p ), _xlpm.base,_xlfn.XLOOKUP(_xlpm.code,'Product Code'!A:A,'Product Code'!C:C,""), IF(RIGHT(_xlpm.p,3)="-PO",_xlpm.base&" - Pull-Out",_xlpm.base) )} -> Sink | I47: {=_xlfn.LET( _xlpm.p,E47, _xlpm.code,IFERROR( IF(AND(LEFT(_xlpm.p,2)="DB",ISNUMBER(SEARCH("-2",_xlpm.p))),"DB-2", IF(LEFT(_xlpm.p,3)="OC-","OC", LEFT(_xlpm.p,_xlfn.XMATCH(TRUE,ISNUMBER(--MID(_xlpm.p,_xlfn.SEQUENCE(LEN(_xlpm.p)),1)))-1) ) ), _xlpm.p ), _xlpm.productType,_xlfn.XLOOKUP(_xlpm.code,'Product Code'!A:A,'Product Code'!D:D,""), IF(OR(RIGHT(_xlpm.p,5)="-Door",RIGHT(_xlpm.p,6)="-DOORS"),_xlpm.productType&" - Door",_xlpm.productType) )} -> - | N47: =IF(ISNUMBER(SEARCH("Cabinet",F47))=FALSE,"N/A",IF(K47>=24,2,1)) -> 1 | O47: =IF(ISNUMBER(SEARCH("Cabinet",F47))=FALSE,"N/A", IF(ISNUMBER(SEARCH("DB",E47)), IF(ISNUMBER(SEARCH("-2",E47)),2,3), IF(ISNUMBER(SEARCH("-PO",E47)),1, IF(LEFT(E47,1)="B",1,0) ) ) ) -> 0
A48: F9-ROD15 | B48: 101 | C48: =B48*0.3 -> 30.3 | E48: =_xlfn.TEXTAFTER(A48,"-") -> ROD15 | F48: {=_xlfn.LET( _xlpm.p,E48, _xlpm.code,IFERROR( IF(AND(LEFT(_xlpm.p,2)="DB",ISNUMBER(SEARCH("-2",_xlpm.p))),"DB-2", IF(LEFT(_xlpm.p,3)="OC-","OC", LEFT(_xlpm.p,_xlfn.XMATCH(TRUE,ISNUMBER(--MID(_xlpm.p,_xlfn.SEQUENCE(LEN(_xlpm.p)),1)))-1) ) ), _xlpm.p ), _xlfn.XLOOKUP(_xlpm.code,'Product Code'!A:A,'Product Code'!B:B,"") )} -> cote dessous tiroir | G48: {=_xlfn.LET( _xlpm.p,E48, _xlpm.code,IFERROR( IF(AND(LEFT(_xlpm.p,2)="DB",ISNUMBER(SEARCH("-2",_xlpm.p))),"DB-2", IF(LEFT(_xlpm.p,3)="OC-","OC", LEFT(_xlpm.p,_xlfn.XMATCH(TRUE,ISNUMBER(--MID(_xlpm.p,_xlfn.SEQUENCE(LEN(_xlpm.p)),1)))-1) ) ), _xlpm.p ), _xlpm.base,_xlfn.XLOOKUP(_xlpm.code,'Product Code'!A:A,'Product Code'!C:C,""), IF(RIGHT(_xlpm.p,3)="-PO",_xlpm.base&" - Pull-Out",_xlpm.base) )} -> 0 | I48: {=_xlfn.LET( _xlpm.p,E48, _xlpm.code,IFERROR( IF(AND(LEFT(_xlpm.p,2)="DB",ISNUMBER(SEARCH("-2",_xlpm.p))),"DB-2", IF(LEFT(_xlpm.p,3)="OC-","OC", LEFT(_xlpm.p,_xlfn.XMATCH(TRUE,ISNUMBER(--MID(_xlpm.p,_xlfn.SEQUENCE(LEN(_xlpm.p)),1)))-1) ) ), _xlpm.p ), _xlpm.productType,_xlfn.XLOOKUP(_xlpm.code,'Product Code'!A:A,'Product Code'!D:D,""), IF(OR(RIGHT(_xlpm.p,5)="-Door",RIGHT(_xlpm.p,6)="-DOORS"),_xlpm.productType&" - Door",_xlpm.productType) )} -> - | N48: N/A | O48: N/A
A49: F9-ROD18 | B49: 115 | C49: =B49*0.3 -> 34.5 | E49: =_xlfn.TEXTAFTER(A49,"-") -> ROD18 | F49: {=_xlfn.LET( _xlpm.p,E49, _xlpm.code,IFERROR( IF(AND(LEFT(_xlpm.p,2)="DB",ISNUMBER(SEARCH("-2",_xlpm.p))),"DB-2", IF(LEFT(_xlpm.p,3)="OC-","OC", LEFT(_xlpm.p,_xlfn.XMATCH(TRUE,ISNUMBER(--MID(_xlpm.p,_xlfn.SEQUENCE(LEN(_xlpm.p)),1)))-1) ) ), _xlpm.p ), _xlfn.XLOOKUP(_xlpm.code,'Product Code'!A:A,'Product Code'!B:B,"") )} -> cote dessous tiroir | G49: {=_xlfn.LET( _xlpm.p,E49, _xlpm.code,IFERROR( IF(AND(LEFT(_xlpm.p,2)="DB",ISNUMBER(SEARCH("-2",_xlpm.p))),"DB-2", IF(LEFT(_xlpm.p,3)="OC-","OC", LEFT(_xlpm.p,_xlfn.XMATCH(TRUE,ISNUMBER(--MID(_xlpm.p,_xlfn.SEQUENCE(LEN(_xlpm.p)),1)))-1) ) ), _xlpm.p ), _xlpm.base,_xlfn.XLOOKUP(_xlpm.code,'Product Code'!A:A,'Product Code'!C:C,""), IF(RIGHT(_xlpm.p,3)="-PO",_xlpm.base&" - Pull-Out",_xlpm.base) )} -> 0 | I49: {=_xlfn.LET( _xlpm.p,E49, _xlpm.code,IFERROR( IF(AND(LEFT(_xlpm.p,2)="DB",ISNUMBER(SEARCH("-2",_xlpm.p))),"DB-2", IF(LEFT(_xlpm.p,3)="OC-","OC", LEFT(_xlpm.p,_xlfn.XMATCH(TRUE,ISNUMBER(--MID(_xlpm.p,_xlfn.SEQUENCE(LEN(_xlpm.p)),1)))-1) ) ), _xlpm.p ), _xlpm.productType,_xlfn.XLOOKUP(_xlpm.code,'Product Code'!A:A,'Product Code'!D:D,""), IF(OR(RIGHT(_xlpm.p,5)="-Door",RIGHT(_xlpm.p,6)="-DOORS"),_xlpm.productType&" - Door",_xlpm.productType) )} -> - | N49: N/A | O49: N/A
A50: F9-ROD21 | B50: 130 | C50: =B50*0.3 -> 39 | E50: =_xlfn.TEXTAFTER(A50,"-") -> ROD21 | F50: {=_xlfn.LET( _xlpm.p,E50, _xlpm.code,IFERROR( IF(AND(LEFT(_xlpm.p,2)="DB",ISNUMBER(SEARCH("-2",_xlpm.p))),"DB-2", IF(LEFT(_xlpm.p,3)="OC-","OC", LEFT(_xlpm.p,_xlfn.XMATCH(TRUE,ISNUMBER(--MID(_xlpm.p,_xlfn.SEQUENCE(LEN(_xlpm.p)),1)))-1) ) ), _xlpm.p ), _xlfn.XLOOKUP(_xlpm.code,'Product Code'!A:A,'Product Code'!B:B,"") )} -> cote dessous tiroir | G50: {=_xlfn.LET( _xlpm.p,E50, _xlpm.code,IFERROR( IF(AND(LEFT(_xlpm.p,2)="DB",ISNUMBER(SEARCH("-2",_xlpm.p))),"DB-2", IF(LEFT(_xlpm.p,3)="OC-","OC", LEFT(_xlpm.p,_xlfn.XMATCH(TRUE,ISNUMBER(--MID(_xlpm.p,_xlfn.SEQUENCE(LEN(_xlpm.p)),1)))-1) ) ), _xlpm.p ), _xlpm.base,_xlfn.XLOOKUP(_xlpm.code,'Product Code'!A:A,'Product Code'!C:C,""), IF(RIGHT(_xlpm.p,3)="-PO",_xlpm.base&" - Pull-Out",_xlpm.base) )} -> 0 | I50: {=_xlfn.LET( _xlpm.p,E50, _xlpm.code,IFERROR( IF(AND(LEFT(_xlpm.p,2)="DB",ISNUMBER(SEARCH("-2",_xlpm.p))),"DB-2", IF(LEFT(_xlpm.p,3)="OC-","OC", LEFT(_xlpm.p,_xlfn.XMATCH(TRUE,ISNUMBER(--MID(_xlpm.p,_xlfn.SEQUENCE(LEN(_xlpm.p)),1)))-1) ) ), _xlpm.p ), _xlpm.productType,_xlfn.XLOOKUP(_xlpm.code,'Product Code'!A:A,'Product Code'!D:D,""), IF(OR(RIGHT(_xlpm.p,5)="-Door",RIGHT(_xlpm.p,6)="-DOORS"),_xlpm.productType&" - Door",_xlpm.productType) )} -> - | N50: N/A | O50: N/A
A51: F9-ROD24 | B51: 144 | C51: =B51*0.3 -> 43.2 | E51: =_xlfn.TEXTAFTER(A51,"-") -> ROD24 | F51: {=_xlfn.LET( _xlpm.p,E51, _xlpm.code,IFERROR( IF(AND(LEFT(_xlpm.p,2)="DB",ISNUMBER(SEARCH("-2",_xlpm.p))),"DB-2", IF(LEFT(_xlpm.p,3)="OC-","OC", LEFT(_xlpm.p,_xlfn.XMATCH(TRUE,ISNUMBER(--MID(_xlpm.p,_xlfn.SEQUENCE(LEN(_xlpm.p)),1)))-1) ) ), _xlpm.p ), _xlfn.XLOOKUP(_xlpm.code,'Product Code'!A:A,'Product Code'!B:B,"") )} -> cote dessous tiroir | G51: {=_xlfn.LET( _xlpm.p,E51, _xlpm.code,IFERROR( IF(AND(LEFT(_xlpm.p,2)="DB",ISNUMBER(SEARCH("-2",_xlpm.p))),"DB-2", IF(LEFT(_xlpm.p,3)="OC-","OC", LEFT(_xlpm.p,_xlfn.XMATCH(TRUE,ISNUMBER(--MID(_xlpm.p,_xlfn.SEQUENCE(LEN(_xlpm.p)),1)))-1) ) ), _xlpm.p ), _xlpm.base,_xlfn.XLOOKUP(_xlpm.code,'Product Code'!A:A,'Product Code'!C:C,""), IF(RIGHT(_xlpm.p,3)="-PO",_xlpm.base&" - Pull-Out",_xlpm.base) )} -> 0 | I51: {=_xlfn.LET( _xlpm.p,E51, _xlpm.code,IFERROR( IF(AND(LEFT(_xlpm.p,2)="DB",ISNUMBER(SEARCH("-2",_xlpm.p))),"DB-2", IF(LEFT(_xlpm.p,3)="OC-","OC", LEFT(_xlpm.p,_xlfn.XMATCH(TRUE,ISNUMBER(--MID(_xlpm.p,_xlfn.SEQUENCE(LEN(_xlpm.p)),1)))-1) ) ), _xlpm.p ), _xlpm.productType,_xlfn.XLOOKUP(_xlpm.code,'Product Code'!A:A,'Product Code'!D:D,""), IF(OR(RIGHT(_xlpm.p,5)="-Door",RIGHT(_xlpm.p,6)="-DOORS"),_xlpm.productType&" - Door",_xlpm.productType) )} -> - | N51: N/A | O51: N/A
A52: F9-ROD27 | B52: 160 | C52: =B52*0.3 -> 48 | E52: =_xlfn.TEXTAFTER(A52,"-") -> ROD27 | F52: {=_xlfn.LET( _xlpm.p,E52, _xlpm.code,IFERROR( IF(AND(LEFT(_xlpm.p,2)="DB",ISNUMBER(SEARCH("-2",_xlpm.p))),"DB-2", IF(LEFT(_xlpm.p,3)="OC-","OC", LEFT(_xlpm.p,_xlfn.XMATCH(TRUE,ISNUMBER(--MID(_xlpm.p,_xlfn.SEQUENCE(LEN(_xlpm.p)),1)))-1) ) ), _xlpm.p ), _xlfn.XLOOKUP(_xlpm.code,'Product Code'!A:A,'Product Code'!B:B,"") )} -> cote dessous tiroir | G52: {=_xlfn.LET( _xlpm.p,E52, _xlpm.code,IFERROR( IF(AND(LEFT(_xlpm.p,2)="DB",ISNUMBER(SEARCH("-2",_xlpm.p))),"DB-2", IF(LEFT(_xlpm.p,3)="OC-","OC", LEFT(_xlpm.p,_xlfn.XMATCH(TRUE,ISNUMBER(--MID(_xlpm.p,_xlfn.SEQUENCE(LEN(_xlpm.p)),1)))-1) ) ), _xlpm.p ), _xlpm.base,_xlfn.XLOOKUP(_xlpm.code,'Product Code'!A:A,'Product Code'!C:C,""), IF(RIGHT(_xlpm.p,3)="-PO",_xlpm.base&" - Pull-Out",_xlpm.base) )} -> 0 | I52: {=_xlfn.LET( _xlpm.p,E52, _xlpm.code,IFERROR( IF(AND(LEFT(_xlpm.p,2)="DB",ISNUMBER(SEARCH("-2",_xlpm.p))),"DB-2", IF(LEFT(_xlpm.p,3)="OC-","OC", LEFT(_xlpm.p,_xlfn.XMATCH(TRUE,ISNUMBER(--MID(_xlpm.p,_xlfn.SEQUENCE(LEN(_xlpm.p)),1)))-1) ) ), _xlpm.p ), _xlpm.productType,_xlfn.XLOOKUP(_xlpm.code,'Product Code'!A:A,'Product Code'!D:D,""), IF(OR(RIGHT(_xlpm.p,5)="-Door",RIGHT(_xlpm.p,6)="-DOORS"),_xlpm.productType&" - Door",_xlpm.productType) )} -> - | N52: N/A | O52: N/A
A53: F9-ROD30 | B53: 175 | C53: =B53*0.3 -> 52.5 | E53: =_xlfn.TEXTAFTER(A53,"-") -> ROD30 | F53: {=_xlfn.LET( _xlpm.p,E53, _xlpm.code,IFERROR( IF(AND(LEFT(_xlpm.p,2)="DB",ISNUMBER(SEARCH("-2",_xlpm.p))),"DB-2", IF(LEFT(_xlpm.p,3)="OC-","OC", LEFT(_xlpm.p,_xlfn.XMATCH(TRUE,ISNUMBER(--MID(_xlpm.p,_xlfn.SEQUENCE(LEN(_xlpm.p)),1)))-1) ) ), _xlpm.p ), _xlfn.XLOOKUP(_xlpm.code,'Product Code'!A:A,'Product Code'!B:B,"") )} -> cote dessous tiroir | G53: {=_xlfn.LET( _xlpm.p,E53, _xlpm.code,IFERROR( IF(AND(LEFT(_xlpm.p,2)="DB",ISNUMBER(SEARCH("-2",_xlpm.p))),"DB-2", IF(LEFT(_xlpm.p,3)="OC-","OC", LEFT(_xlpm.p,_xlfn.XMATCH(TRUE,ISNUMBER(--MID(_xlpm.p,_xlfn.SEQUENCE(LEN(_xlpm.p)),1)))-1) ) ), _xlpm.p ), _xlpm.base,_xlfn.XLOOKUP(_xlpm.code,'Product Code'!A:A,'Product Code'!C:C,""), IF(RIGHT(_xlpm.p,3)="-PO",_xlpm.base&" - Pull-Out",_xlpm.base) )} -> 0 | I53: {=_xlfn.LET( _xlpm.p,E53, _xlpm.code,IFERROR( IF(AND(LEFT(_xlpm.p,2)="DB",ISNUMBER(SEARCH("-2",_xlpm.p))),"DB-2", IF(LEFT(_xlpm.p,3)="OC-","OC", LEFT(_xlpm.p,_xlfn.XMATCH(TRUE,ISNUMBER(--MID(_xlpm.p,_xlfn.SEQUENCE(LEN(_xlpm.p)),1)))-1) ) ), _xlpm.p ), _xlpm.productType,_xlfn.XLOOKUP(_xlpm.code,'Product Code'!A:A,'Product Code'!D:D,""), IF(OR(RIGHT(_xlpm.p,5)="-Door",RIGHT(_xlpm.p,6)="-DOORS"),_xlpm.productType&" - Door",_xlpm.productType) )} -> - | N53: N/A | O53: N/A
A54: F9-ROD33 | B54: 189 | C54: =B54*0.3 -> 56.7 | E54: =_xlfn.TEXTAFTER(A54,"-") -> ROD33 | F54: {=_xlfn.LET( _xlpm.p,E54, _xlpm.code,IFERROR( IF(AND(LEFT(_xlpm.p,2)="DB",ISNUMBER(SEARCH("-2",_xlpm.p))),"DB-2", IF(LEFT(_xlpm.p,3)="OC-","OC", LEFT(_xlpm.p,_xlfn.XMATCH(TRUE,ISNUMBER(--MID(_xlpm.p,_xlfn.SEQUENCE(LEN(_xlpm.p)),1)))-1) ) ), _xlpm.p ), _xlfn.XLOOKUP(_xlpm.code,'Product Code'!A:A,'Product Code'!B:B,"") )} -> cote dessous tiroir | G54: {=_xlfn.LET( _xlpm.p,E54, _xlpm.code,IFERROR( IF(AND(LEFT(_xlpm.p,2)="DB",ISNUMBER(SEARCH("-2",_xlpm.p))),"DB-2", IF(LEFT(_xlpm.p,3)="OC-","OC", LEFT(_xlpm.p,_xlfn.XMATCH(TRUE,ISNUMBER(--MID(_xlpm.p,_xlfn.SEQUENCE(LEN(_xlpm.p)),1)))-1) ) ), _xlpm.p ), _xlpm.base,_xlfn.XLOOKUP(_xlpm.code,'Product Code'!A:A,'Product Code'!C:C,""), IF(RIGHT(_xlpm.p,3)="-PO",_xlpm.base&" - Pull-Out",_xlpm.base) )} -> 0 | I54: {=_xlfn.LET( _xlpm.p,E54, _xlpm.code,IFERROR( IF(AND(LEFT(_xlpm.p,2)="DB",ISNUMBER(SEARCH("-2",_xlpm.p))),"DB-2", IF(LEFT(_xlpm.p,3)="OC-","OC", LEFT(_xlpm.p,_xlfn.XMATCH(TRUE,ISNUMBER(--MID(_xlpm.p,_xlfn.SEQUENCE(LEN(_xlpm.p)),1)))-1) ) ), _xlpm.p ), _xlpm.productType,_xlfn.XLOOKUP(_xlpm.code,'Product Code'!A:A,'Product Code'!D:D,""), IF(OR(RIGHT(_xlpm.p,5)="-Door",RIGHT(_xlpm.p,6)="-DOORS"),_xlpm.productType&" - Door",_xlpm.productType) )} -> - | N54: N/A | O54: N/A
A55: F9-ROD36 | B55: 215 | C55: =B55*0.3 -> 64.5 | E55: =_xlfn.TEXTAFTER(A55,"-") -> ROD36 | F55: {=_xlfn.LET( _xlpm.p,E55, _xlpm.code,IFERROR( IF(AND(LEFT(_xlpm.p,2)="DB",ISNUMBER(SEARCH("-2",_xlpm.p))),"DB-2", IF(LEFT(_xlpm.p,3)="OC-","OC", LEFT(_xlpm.p,_xlfn.XMATCH(TRUE,ISNUMBER(--MID(_xlpm.p,_xlfn.SEQUENCE(LEN(_xlpm.p)),1)))-1) ) ), _xlpm.p ), _xlfn.XLOOKUP(_xlpm.code,'Product Code'!A:A,'Product Code'!B:B,"") )} -> cote dessous tiroir | G55: {=_xlfn.LET( _xlpm.p,E55, _xlpm.code,IFERROR( IF(AND(LEFT(_xlpm.p,2)="DB",ISNUMBER(SEARCH("-2",_xlpm.p))),"DB-2", IF(LEFT(_xlpm.p,3)="OC-","OC", LEFT(_xlpm.p,_xlfn.XMATCH(TRUE,ISNUMBER(--MID(_xlpm.p,_xlfn.SEQUENCE(LEN(_xlpm.p)),1)))-1) ) ), _xlpm.p ), _xlpm.base,_xlfn.XLOOKUP(_xlpm.code,'Product Code'!A:A,'Product Code'!C:C,""), IF(RIGHT(_xlpm.p,3)="-PO",_xlpm.base&" - Pull-Out",_xlpm.base) )} -> 0 | I55: {=_xlfn.LET( _xlpm.p,E55, _xlpm.code,IFERROR( IF(AND(LEFT(_xlpm.p,2)="DB",ISNUMBER(SEARCH("-2",_xlpm.p))),"DB-2", IF(LEFT(_xlpm.p,3)="OC-","OC", LEFT(_xlpm.p,_xlfn.XMATCH(TRUE,ISNUMBER(--MID(_xlpm.p,_xlfn.SEQUENCE(LEN(_xlpm.p)),1)))-1) ) ), _xlpm.p ), _xlpm.productType,_xlfn.XLOOKUP(_xlpm.code,'Product Code'!A:A,'Product Code'!D:D,""), IF(OR(RIGHT(_xlpm.p,5)="-Door",RIGHT(_xlpm.p,6)="-DOORS"),_xlpm.productType&" - Door",_xlpm.productType) )} -> - | N55: N/A | O55: N/A
A56: F9-BDD12.75*36 | B56: 150 | C56: =B56*0.3 -> 45 | D56: =C56*1.25 -> 56.25 | E56: =_xlfn.TEXTAFTER(A56,"-") -> BDD12.75*36 | F56: {=_xlfn.LET( _xlpm.p,E56, _xlpm.code,IFERROR( IF(AND(LEFT(_xlpm.p,2)="DB",ISNUMBER(SEARCH("-2",_xlpm.p))),"DB-2", IF(LEFT(_xlpm.p,3)="OC-","OC", LEFT(_xlpm.p,_xlfn.XMATCH(TRUE,ISNUMBER(--MID(_xlpm.p,_xlfn.SEQUENCE(LEN(_xlpm.p)),1)))-1) ) ), _xlpm.p ), _xlpm.productType,_xlfn.XLOOKUP(_xlpm.code,'Product Code'!A:A,'Product Code'!B:B,""), IF(OR(RIGHT(_xlpm.p,5)="-Door",RIGHT(_xlpm.p,6)="-DOORS"),_xlpm.productType&" - Door",_xlpm.productType) )} -> Dummy Door | G56: {=_xlfn.LET( _xlpm.p,E56, _xlpm.code,IFERROR( IF(AND(LEFT(_xlpm.p,2)="DB",ISNUMBER(SEARCH("-2",_xlpm.p))),"DB-2", IF(LEFT(_xlpm.p,3)="OC-","OC", LEFT(_xlpm.p,_xlfn.XMATCH(TRUE,ISNUMBER(--MID(_xlpm.p,_xlfn.SEQUENCE(LEN(_xlpm.p)),1)))-1) ) ), _xlpm.p ), _xlpm.base,_xlfn.XLOOKUP(_xlpm.code,'Product Code'!A:A,'Product Code'!C:C,""), IF(RIGHT(_xlpm.p,3)="-PO",_xlpm.base&" - Pull-Out",_xlpm.base) )} -> Base End | H56: N/A | I56: {=_xlfn.LET( _xlpm.p,E56, _xlpm.code,IFERROR( IF(AND(LEFT(_xlpm.p,2)="DB",ISNUMBER(SEARCH("-2",_xlpm.p))),"DB-2", IF(LEFT(_xlpm.p,3)="OC-","OC", LEFT(_xlpm.p,_xlfn.XMATCH(TRUE,ISNUMBER(--MID(_xlpm.p,_xlfn.SEQUENCE(LEN(_xlpm.p)),1)))-1) ) ), _xlpm.p ), _xlpm.productType,_xlfn.XLOOKUP(_xlpm.code,'Product Code'!A:A,'Product Code'!D:D,""), IF(OR(RIGHT(_xlpm.p,5)="-Door",RIGHT(_xlpm.p,6)="-DOORS"),_xlpm.productType&" - Door",_xlpm.productType) )} -> x | J56: x | K56: 12.75 | L56: 36 | M56: =3/4 -> 0.75 | N56: N/A | O56: N/A
A57: F9-BDD21.75*36 | B57: 238 | C57: =B57*0.3 -> 71.4 | D57: =C57*1.25 -> 89.25 | E57: =_xlfn.TEXTAFTER(A57,"-") -> BDD21.75*36 | F57: {=_xlfn.LET( _xlpm.p,E57, _xlpm.code,IFERROR( IF(AND(LEFT(_xlpm.p,2)="DB",ISNUMBER(SEARCH("-2",_xlpm.p))),"DB-2", IF(LEFT(_xlpm.p,3)="OC-","OC", LEFT(_xlpm.p,_xlfn.XMATCH(TRUE,ISNUMBER(--MID(_xlpm.p,_xlfn.SEQUENCE(LEN(_xlpm.p)),1)))-1) ) ), _xlpm.p ), _xlpm.productType,_xlfn.XLOOKUP(_xlpm.code,'Product Code'!A:A,'Product Code'!B:B,""), IF(OR(RIGHT(_xlpm.p,5)="-Door",RIGHT(_xlpm.p,6)="-DOORS"),_xlpm.productType&" - Door",_xlpm.productType) )} -> Dummy Door | G57: {=_xlfn.LET( _xlpm.p,E57, _xlpm.code,IFERROR( IF(AND(LEFT(_xlpm.p,2)="DB",ISNUMBER(SEARCH("-2",_xlpm.p))),"DB-2", IF(LEFT(_xlpm.p,3)="OC-","OC", LEFT(_xlpm.p,_xlfn.XMATCH(TRUE,ISNUMBER(--MID(_xlpm.p,_xlfn.SEQUENCE(LEN(_xlpm.p)),1)))-1) ) ), _xlpm.p ), _xlpm.base,_xlfn.XLOOKUP(_xlpm.code,'Product Code'!A:A,'Product Code'!C:C,""), IF(RIGHT(_xlpm.p,3)="-PO",_xlpm.base&" - Pull-Out",_xlpm.base) )} -> Base End | H57: N/A | I57: {=_xlfn.LET( _xlpm.p,E57, _xlpm.code,IFERROR( IF(AND(LEFT(_xlpm.p,2)="DB",ISNUMBER(SEARCH("-2",_xlpm.p))),"DB-2", IF(LEFT(_xlpm.p,3)="OC-","OC", LEFT(_xlpm.p,_xlfn.XMATCH(TRUE,ISNUMBER(--MID(_xlpm.p,_xlfn.SEQUENCE(LEN(_xlpm.p)),1)))-1) ) ), _xlpm.p ), _xlpm.productType,_xlfn.XLOOKUP(_xlpm.code,'Product Code'!A:A,'Product Code'!D:D,""), IF(OR(RIGHT(_xlpm.p,5)="-Door",RIGHT(_xlpm.p,6)="-DOORS"),_xlpm.productType&" - Door",_xlpm.productType) )} -> x | J57: x | K57: 21.75 | L57: 36 | M57: =3/4 -> 0.75 | N57: N/A | O57: N/A
A58: F9-BDD24.75*36 | B58: 250 | C58: =B58*0.3 -> 75 | D58: =C58*1.25 -> 93.75 | E58: =_xlfn.TEXTAFTER(A58,"-") -> BDD24.75*36 | F58: {=_xlfn.LET( _xlpm.p,E58, _xlpm.code,IFERROR( IF(AND(LEFT(_xlpm.p,2)="DB",ISNUMBER(SEARCH("-2",_xlpm.p))),"DB-2", IF(LEFT(_xlpm.p,3)="OC-","OC", LEFT(_xlpm.p,_xlfn.XMATCH(TRUE,ISNUMBER(--MID(_xlpm.p,_xlfn.SEQUENCE(LEN(_xlpm.p)),1)))-1) ) ), _xlpm.p ), _xlfn.XLOOKUP(_xlpm.code,'Product Code'!A:A,'Product Code'!B:B,"") )} -> Dummy Door | G58: {=_xlfn.LET( _xlpm.p,E58, _xlpm.code,IFERROR( IF(AND(LEFT(_xlpm.p,2)="DB",ISNUMBER(SEARCH("-2",_xlpm.p))),"DB-2", IF(LEFT(_xlpm.p,3)="OC-","OC", LEFT(_xlpm.p,_xlfn.XMATCH(TRUE,ISNUMBER(--MID(_xlpm.p,_xlfn.SEQUENCE(LEN(_xlpm.p)),1)))-1) ) ), _xlpm.p ), _xlpm.base,_xlfn.XLOOKUP(_xlpm.code,'Product Code'!A:A,'Product Code'!C:C,""), IF(RIGHT(_xlpm.p,3)="-PO",_xlpm.base&" - Pull-Out",_xlpm.base) )} -> Base End | H58: N/A | I58: {=_xlfn.LET( _xlpm.p,E58, _xlpm.code,IFERROR( IF(AND(LEFT(_xlpm.p,2)="DB",ISNUMBER(SEARCH("-2",_xlpm.p))),"DB-2", IF(LEFT(_xlpm.p,3)="OC-","OC", LEFT(_xlpm.p,_xlfn.XMATCH(TRUE,ISNUMBER(--MID(_xlpm.p,_xlfn.SEQUENCE(LEN(_xlpm.p)),1)))-1) ) ), _xlpm.p ), _xlpm.productType,_xlfn.XLOOKUP(_xlpm.code,'Product Code'!A:A,'Product Code'!D:D,""), IF(OR(RIGHT(_xlpm.p,5)="-Door",RIGHT(_xlpm.p,6)="-DOORS"),_xlpm.productType&" - Door",_xlpm.productType) )} -> x | J58: x | K58: 24.75 | L58: 36 | M58: =3/4 -> 0.75 | N58: N/A | O58: N/A
A59: F9-BDD2430 | B59: 192 | C59: =B59*0.3 -> 57.6 | D59: =C59*1.25 -> 72 | E59: =_xlfn.TEXTAFTER(A59,"-") -> BDD2430 | F59: {=_xlfn.LET( _xlpm.p,E59, _xlpm.code,IFERROR( IF(AND(LEFT(_xlpm.p,2)="DB",ISNUMBER(SEARCH("-2",_xlpm.p))),"DB-2", IF(LEFT(_xlpm.p,3)="OC-","OC", LEFT(_xlpm.p,_xlfn.XMATCH(TRUE,ISNUMBER(--MID(_xlpm.p,_xlfn.SEQUENCE(LEN(_xlpm.p)),1)))-1) ) ), _xlpm.p ), _xlfn.XLOOKUP(_xlpm.code,'Product Code'!A:A,'Product Code'!B:B,"") )} -> Dummy Door | G59: {=_xlfn.LET( _xlpm.p,E59, _xlpm.code,IFERROR( IF(AND(LEFT(_xlpm.p,2)="DB",ISNUMBER(SEARCH("-2",_xlpm.p))),"DB-2", IF(LEFT(_xlpm.p,3)="OC-","OC", LEFT(_xlpm.p,_xlfn.XMATCH(TRUE,ISNUMBER(--MID(_xlpm.p,_xlfn.SEQUENCE(LEN(_xlpm.p)),1)))-1) ) ), _xlpm.p ), _xlpm.base,_xlfn.XLOOKUP(_xlpm.code,'Product Code'!A:A,'Product Code'!C:C,""), IF(RIGHT(_xlpm.p,3)="-PO",_xlpm.base&" - Pull-Out",_xlpm.base) )} -> Base End | H59: N/A | I59: {=_xlfn.LET( _xlpm.p,E59, _xlpm.code,IFERROR( IF(AND(LEFT(_xlpm.p,2)="DB",ISNUMBER(SEARCH("-2",_xlpm.p))),"DB-2", IF(LEFT(_xlpm.p,3)="OC-","OC", LEFT(_xlpm.p,_xlfn.XMATCH(TRUE,ISNUMBER(--MID(_xlpm.p,_xlfn.SEQUENCE(LEN(_xlpm.p)),1)))-1) ) ), _xlpm.p ), _xlpm.productType,_xlfn.XLOOKUP(_xlpm.code,'Product Code'!A:A,'Product Code'!D:D,""), IF(OR(RIGHT(_xlpm.p,5)="-Door",RIGHT(_xlpm.p,6)="-DOORS"),_xlpm.productType&" - Door",_xlpm.productType) )} -> x | J59: x | K59: 24 | L59: 30 | M59: =3/4 -> 0.75 | N59: N/A | O59: N/A
A60: F9-BDD25.75*36 | B60: 256 | C60: =B60*0.3 -> 76.8 | D60: =C60*1.25 -> 96 | E60: =_xlfn.TEXTAFTER(A60,"-") -> BDD25.75*36 | F60: {=_xlfn.LET( _xlpm.p,E60, _xlpm.code,IFERROR( IF(AND(LEFT(_xlpm.p,2)="DB",ISNUMBER(SEARCH("-2",_xlpm.p))),"DB-2", IF(LEFT(_xlpm.p,3)="OC-","OC", LEFT(_xlpm.p,_xlfn.XMATCH(TRUE,ISNUMBER(--MID(_xlpm.p,_xlfn.SEQUENCE(LEN(_xlpm.p)),1)))-1) ) ), _xlpm.p ), _xlfn.XLOOKUP(_xlpm.code,'Product Code'!A:A,'Product Code'!B:B,"") )} -> Dummy Door | G60: {=_xlfn.LET( _xlpm.p,E60, _xlpm.code,IFERROR( IF(AND(LEFT(_xlpm.p,2)="DB",ISNUMBER(SEARCH("-2",_xlpm.p))),"DB-2", IF(LEFT(_xlpm.p,3)="OC-","OC", LEFT(_xlpm.p,_xlfn.XMATCH(TRUE,ISNUMBER(--MID(_xlpm.p,_xlfn.SEQUENCE(LEN(_xlpm.p)),1)))-1) ) ), _xlpm.p ), _xlpm.base,_xlfn.XLOOKUP(_xlpm.code,'Product Code'!A:A,'Product Code'!C:C,""), IF(RIGHT(_xlpm.p,3)="-PO",_xlpm.base&" - Pull-Out",_xlpm.base) )} -> Base End | H60: N/A | I60: {=_xlfn.LET( _xlpm.p,E60, _xlpm.code,IFERROR( IF(AND(LEFT(_xlpm.p,2)="DB",ISNUMBER(SEARCH("-2",_xlpm.p))),"DB-2", IF(LEFT(_xlpm.p,3)="OC-","OC", LEFT(_xlpm.p,_xlfn.XMATCH(TRUE,ISNUMBER(--MID(_xlpm.p,_xlfn.SEQUENCE(LEN(_xlpm.p)),1)))-1) ) ), _xlpm.p ), _xlpm.productType,_xlfn.XLOOKUP(_xlpm.code,'Product Code'!A:A,'Product Code'!D:D,""), IF(OR(RIGHT(_xlpm.p,5)="-Door",RIGHT(_xlpm.p,6)="-DOORS"),_xlpm.productType&" - Door",_xlpm.productType) )} -> x | J60: x | K60: 25.75 | L60: 36 | M60: =3/4 -> 0.75 | N60: N/A | O60: N/A
A61: F9-BDD2730 | B61: 223 | C61: =B61*0.3 -> 66.9 | D61: =C61*1.25 -> 83.625 | E61: =_xlfn.TEXTAFTER(A61,"-") -> BDD2730 | F61: {=_xlfn.LET( _xlpm.p,E61, _xlpm.code,IFERROR( IF(AND(LEFT(_xlpm.p,2)="DB",ISNUMBER(SEARCH("-2",_xlpm.p))),"DB-2", IF(LEFT(_xlpm.p,3)="OC-","OC", LEFT(_xlpm.p,_xlfn.XMATCH(TRUE,ISNUMBER(--MID(_xlpm.p,_xlfn.SEQUENCE(LEN(_xlpm.p)),1)))-1) ) ), _xlpm.p ), _xlfn.XLOOKUP(_xlpm.code,'Product Code'!A:A,'Product Code'!B:B,"") )} -> Dummy Door | G61: {=_xlfn.LET( _xlpm.p,E61, _xlpm.code,IFERROR( IF(AND(LEFT(_xlpm.p,2)="DB",ISNUMBER(SEARCH("-2",_xlpm.p))),"DB-2", IF(LEFT(_xlpm.p,3)="OC-","OC", LEFT(_xlpm.p,_xlfn.XMATCH(TRUE,ISNUMBER(--MID(_xlpm.p,_xlfn.SEQUENCE(LEN(_xlpm.p)),1)))-1) ) ), _xlpm.p ), _xlpm.base,_xlfn.XLOOKUP(_xlpm.code,'Product Code'!A:A,'Product Code'!C:C,""), IF(RIGHT(_xlpm.p,3)="-PO",_xlpm.base&" - Pull-Out",_xlpm.base) )} -> Base End | H61: N/A | I61: {=_xlfn.LET( _xlpm.p,E61, _xlpm.code,IFERROR( IF(AND(LEFT(_xlpm.p,2)="DB",ISNUMBER(SEARCH("-2",_xlpm.p))),"DB-2", IF(LEFT(_xlpm.p,3)="OC-","OC", LEFT(_xlpm.p,_xlfn.XMATCH(TRUE,ISNUMBER(--MID(_xlpm.p,_xlfn.SEQUENCE(LEN(_xlpm.p)),1)))-1) ) ), _xlpm.p ), _xlpm.productType,_xlfn.XLOOKUP(_xlpm.code,'Product Code'!A:A,'Product Code'!D:D,""), IF(OR(RIGHT(_xlpm.p,5)="-Door",RIGHT(_xlpm.p,6)="-DOORS"),_xlpm.productType&" - Door",_xlpm.productType) )} -> x | J61: x | K61: 27 | L61: 30 | M61: =3/4 -> 0.75 | N61: N/A | O61: N/A
A62: F9-BDD3030 | B62: 257 | C62: =B62*0.3 -> 77.1 | D62: =C62*1.25 -> 96.375 | E62: =_xlfn.TEXTAFTER(A62,"-") -> BDD3030 | F62: {=_xlfn.LET( _xlpm.p,E62, _xlpm.code,IFERROR( IF(AND(LEFT(_xlpm.p,2)="DB",ISNUMBER(SEARCH("-2",_xlpm.p))),"DB-2", IF(LEFT(_xlpm.p,3)="OC-","OC", LEFT(_xlpm.p,_xlfn.XMATCH(TRUE,ISNUMBER(--MID(_xlpm.p,_xlfn.SEQUENCE(LEN(_xlpm.p)),1)))-1) ) ), _xlpm.p ), _xlfn.XLOOKUP(_xlpm.code,'Product Code'!A:A,'Product Code'!B:B,"") )} -> Dummy Door | G62: {=_xlfn.LET( _xlpm.p,E62, _xlpm.code,IFERROR( IF(AND(LEFT(_xlpm.p,2)="DB",ISNUMBER(SEARCH("-2",_xlpm.p))),"DB-2", IF(LEFT(_xlpm.p,3)="OC-","OC", LEFT(_xlpm.p,_xlfn.XMATCH(TRUE,ISNUMBER(--MID(_xlpm.p,_xlfn.SEQUENCE(LEN(_xlpm.p)),1)))-1) ) ), _xlpm.p ), _xlpm.base,_xlfn.XLOOKUP(_xlpm.code,'Product Code'!A:A,'Product Code'!C:C,""), IF(RIGHT(_xlpm.p,3)="-PO",_xlpm.base&" - Pull-Out",_xlpm.base) )} -> Base End | H62: N/A | I62: {=_xlfn.LET( _xlpm.p,E62, _xlpm.code,IFERROR( IF(AND(LEFT(_xlpm.p,2)="DB",ISNUMBER(SEARCH("-2",_xlpm.p))),"DB-2", IF(LEFT(_xlpm.p,3)="OC-","OC", LEFT(_xlpm.p,_xlfn.XMATCH(TRUE,ISNUMBER(--MID(_xlpm.p,_xlfn.SEQUENCE(LEN(_xlpm.p)),1)))-1) ) ), _xlpm.p ), _xlpm.productType,_xlfn.XLOOKUP(_xlpm.code,'Product Code'!A:A,'Product Code'!D:D,""), IF(OR(RIGHT(_xlpm.p,5)="-Door",RIGHT(_xlpm.p,6)="-DOORS"),_xlpm.productType&" - Door",_xlpm.productType) )} -> x | J62: x | K62: 30 | L62: 30 | M62: =3/4 -> 0.75 | N62: N/A | O62: N/A
A63: F9-BDD3330 | B63: 290 | C63: =B63*0.3 -> 87 | D63: =C63*1.25 -> 108.75 | E63: =_xlfn.TEXTAFTER(A63,"-") -> BDD3330 | F63: {=_xlfn.LET( _xlpm.p,E63, _xlpm.code,IFERROR( IF(AND(LEFT(_xlpm.p,2)="DB",ISNUMBER(SEARCH("-2",_xlpm.p))),"DB-2", IF(LEFT(_xlpm.p,3)="OC-","OC", LEFT(_xlpm.p,_xlfn.XMATCH(TRUE,ISNUMBER(--MID(_xlpm.p,_xlfn.SEQUENCE(LEN(_xlpm.p)),1)))-1) ) ), _xlpm.p ), _xlfn.XLOOKUP(_xlpm.code,'Product Code'!A:A,'Product Code'!B:B,"") )} -> Dummy Door | G63: {=_xlfn.LET( _xlpm.p,E63, _xlpm.code,IFERROR( IF(AND(LEFT(_xlpm.p,2)="DB",ISNUMBER(SEARCH("-2",_xlpm.p))),"DB-2", IF(LEFT(_xlpm.p,3)="OC-","OC", LEFT(_xlpm.p,_xlfn.XMATCH(TRUE,ISNUMBER(--MID(_xlpm.p,_xlfn.SEQUENCE(LEN(_xlpm.p)),1)))-1) ) ), _xlpm.p ), _xlpm.base,_xlfn.XLOOKUP(_xlpm.code,'Product Code'!A:A,'Product Code'!C:C,""), IF(RIGHT(_xlpm.p,3)="-PO",_xlpm.base&" - Pull-Out",_xlpm.base) )} -> Base End | H63: N/A | I63: {=_xlfn.LET( _xlpm.p,E63, _xlpm.code,IFERROR( IF(AND(LEFT(_xlpm.p,2)="DB",ISNUMBER(SEARCH("-2",_xlpm.p))),"DB-2", IF(LEFT(_xlpm.p,3)="OC-","OC", LEFT(_xlpm.p,_xlfn.XMATCH(TRUE,ISNUMBER(--MID(_xlpm.p,_xlfn.SEQUENCE(LEN(_xlpm.p)),1)))-1) ) ), _xlpm.p ), _xlpm.productType,_xlfn.XLOOKUP(_xlpm.code,'Product Code'!A:A,'Product Code'!D:D,""), IF(OR(RIGHT(_xlpm.p,5)="-Door",RIGHT(_xlpm.p,6)="-DOORS"),_xlpm.productType&" - Door",_xlpm.productType) )} -> x | J63: x | K63: 33 | L63: 30 | M63: =3/4 -> 0.75 | N63: N/A | O63: N/A
A64: F9-BDD37.5x36 | B64: 365 | C64: =B64*0.3 -> 109.5 | D64: =C64*1.25 -> 136.875 | E64: =_xlfn.TEXTAFTER(A64,"-") -> BDD37.5x36 | F64: {=_xlfn.LET( _xlpm.p,E64, _xlpm.code,IFERROR( IF(AND(LEFT(_xlpm.p,2)="DB",ISNUMBER(SEARCH("-2",_xlpm.p))),"DB-2", IF(LEFT(_xlpm.p,3)="OC-","OC", LEFT(_xlpm.p,_xlfn.XMATCH(TRUE,ISNUMBER(--MID(_xlpm.p,_xlfn.SEQUENCE(LEN(_xlpm.p)),1)))-1) ) ), _xlpm.p ), _xlfn.XLOOKUP(_xlpm.code,'Product Code'!A:A,'Product Code'!B:B,"") )} -> Dummy Door | G64: {=_xlfn.LET( _xlpm.p,E64, _xlpm.code,IFERROR( IF(AND(LEFT(_xlpm.p,2)="DB",ISNUMBER(SEARCH("-2",_xlpm.p))),"DB-2", IF(LEFT(_xlpm.p,3)="OC-","OC", LEFT(_xlpm.p,_xlfn.XMATCH(TRUE,ISNUMBER(--MID(_xlpm.p,_xlfn.SEQUENCE(LEN(_xlpm.p)),1)))-1) ) ), _xlpm.p ), _xlpm.base,_xlfn.XLOOKUP(_xlpm.code,'Product Code'!A:A,'Product Code'!C:C,""), IF(RIGHT(_xlpm.p,3)="-PO",_xlpm.base&" - Pull-Out",_xlpm.base) )} -> Base End | H64: N/A | I64: {=_xlfn.LET( _xlpm.p,E64, _xlpm.code,IFERROR( IF(AND(LEFT(_xlpm.p,2)="DB",ISNUMBER(SEARCH("-2",_xlpm.p))),"DB-2", IF(LEFT(_xlpm.p,3)="OC-","OC", LEFT(_xlpm.p,_xlfn.XMATCH(TRUE,ISNUMBER(--MID(_xlpm.p,_xlfn.SEQUENCE(LEN(_xlpm.p)),1)))-1) ) ), _xlpm.p ), _xlpm.productType,_xlfn.XLOOKUP(_xlpm.code,'Product Code'!A:A,'Product Code'!D:D,""), IF(OR(RIGHT(_xlpm.p,5)="-Door",RIGHT(_xlpm.p,6)="-DOORS"),_xlpm.productType&" - Door",_xlpm.productType) )} -> x | J64: x | K64: 37.5 | L64: 36 | M64: =3/4 -> 0.75 | N64: N/A | O64: N/A
A65: F9-BDD49.75*36 | B65: 535 | C65: =B65*0.3 -> 160.5 | D65: =C65*1.25 -> 200.625 | E65: =_xlfn.TEXTAFTER(A65,"-") -> BDD49.75*36 | F65: {=_xlfn.LET( _xlpm.p,E65, _xlpm.code,IFERROR( IF(AND(LEFT(_xlpm.p,2)="DB",ISNUMBER(SEARCH("-2",_xlpm.p))),"DB-2", IF(LEFT(_xlpm.p,3)="OC-","OC", LEFT(_xlpm.p,_xlfn.XMATCH(TRUE,ISNUMBER(--MID(_xlpm.p,_xlfn.SEQUENCE(LEN(_xlpm.p)),1)))-1) ) ), _xlpm.p ), _xlfn.XLOOKUP(_xlpm.code,'Product Code'!A:A,'Product Code'!B:B,"") )} -> Dummy Door | G65: {=_xlfn.LET( _xlpm.p,E65, _xlpm.code,IFERROR( IF(AND(LEFT(_xlpm.p,2)="DB",ISNUMBER(SEARCH("-2",_xlpm.p))),"DB-2", IF(LEFT(_xlpm.p,3)="OC-","OC", LEFT(_xlpm.p,_xlfn.XMATCH(TRUE,ISNUMBER(--MID(_xlpm.p,_xlfn.SEQUENCE(LEN(_xlpm.p)),1)))-1) ) ), _xlpm.p ), _xlpm.base,_xlfn.XLOOKUP(_xlpm.code,'Product Code'!A:A,'Product Code'!C:C,""), IF(RIGHT(_xlpm.p,3)="-PO",_xlpm.base&" - Pull-Out",_xlpm.base) )} -> Base End | H65: N/A | I65: {=_xlfn.LET( _xlpm.p,E65, _xlpm.code,IFERROR( IF(AND(LEFT(_xlpm.p,2)="DB",ISNUMBER(SEARCH("-2",_xlpm.p))),"DB-2", IF(LEFT(_xlpm.p,3)="OC-","OC", LEFT(_xlpm.p,_xlfn.XMATCH(TRUE,ISNUMBER(--MID(_xlpm.p,_xlfn.SEQUENCE(LEN(_xlpm.p)),1)))-1) ) ), _xlpm.p ), _xlpm.productType,_xlfn.XLOOKUP(_xlpm.code,'Product Code'!A:A,'Product Code'!D:D,""), IF(OR(RIGHT(_xlpm.p,5)="-Door",RIGHT(_xlpm.p,6)="-DOORS"),_xlpm.productType&" - Door",_xlpm.productType) )} -> x | J65: x | K65: 49.75 | L65: 36 | M65: =3/4 -> 0.75 | N65: N/A | O65: N/A
A66: F9-CM2.5X120 | B66: 240 | C66: =B66*0.3 -> 72 | E66: =_xlfn.TEXTAFTER(A66,"-") -> CM2.5X120 | F66: {=_xlfn.LET( _xlpm.p,E66, _xlpm.code,IFERROR( IF(AND(LEFT(_xlpm.p,2)="DB",ISNUMBER(SEARCH("-2",_xlpm.p))),"DB-2", IF(LEFT(_xlpm.p,3)="OC-","OC", LEFT(_xlpm.p,_xlfn.XMATCH(TRUE,ISNUMBER(--MID(_xlpm.p,_xlfn.SEQUENCE(LEN(_xlpm.p)),1)))-1) ) ), _xlpm.p ), _xlfn.XLOOKUP(_xlpm.code,'Product Code'!A:A,'Product Code'!B:B,"") )} -> Fillers | G66: {=_xlfn.LET( _xlpm.p,E66, _xlpm.code,IFERROR( IF(AND(LEFT(_xlpm.p,2)="DB",ISNUMBER(SEARCH("-2",_xlpm.p))),"DB-2", IF(LEFT(_xlpm.p,3)="OC-","OC", LEFT(_xlpm.p,_xlfn.XMATCH(TRUE,ISNUMBER(--MID(_xlpm.p,_xlfn.SEQUENCE(LEN(_xlpm.p)),1)))-1) ) ), _xlpm.p ), _xlpm.base,_xlfn.XLOOKUP(_xlpm.code,'Product Code'!A:A,'Product Code'!C:C,""), IF(RIGHT(_xlpm.p,3)="-PO",_xlpm.base&" - Pull-Out",_xlpm.base) )} -> Filler , mais quel type? | I66: {=_xlfn.LET( _xlpm.p,E66, _xlpm.code,IFERROR( IF(AND(LEFT(_xlpm.p,2)="DB",ISNUMBER(SEARCH("-2",_xlpm.p))),"DB-2", IF(LEFT(_xlpm.p,3)="OC-","OC", LEFT(_xlpm.p,_xlfn.XMATCH(TRUE,ISNUMBER(--MID(_xlpm.p,_xlfn.SEQUENCE(LEN(_xlpm.p)),1)))-1) ) ), _xlpm.p ), _xlpm.productType,_xlfn.XLOOKUP(_xlpm.code,'Product Code'!A:A,'Product Code'!D:D,""), IF(OR(RIGHT(_xlpm.p,5)="-Door",RIGHT(_xlpm.p,6)="-DOORS"),_xlpm.productType&" - Door",_xlpm.productType) )} -> - | N66: N/A | O66: N/A
A67: F9-CM2.5X126 | B67: 268 | C67: =B67*0.3 -> 80.4 | E67: =_xlfn.TEXTAFTER(A67,"-") -> CM2.5X126 | F67: {=_xlfn.LET( _xlpm.p,E67, _xlpm.code,IFERROR( IF(AND(LEFT(_xlpm.p,2)="DB",ISNUMBER(SEARCH("-2",_xlpm.p))),"DB-2", IF(LEFT(_xlpm.p,3)="OC-","OC", LEFT(_xlpm.p,_xlfn.XMATCH(TRUE,ISNUMBER(--MID(_xlpm.p,_xlfn.SEQUENCE(LEN(_xlpm.p)),1)))-1) ) ), _xlpm.p ), _xlfn.XLOOKUP(_xlpm.code,'Product Code'!A:A,'Product Code'!B:B,"") )} -> Fillers | G67: {=_xlfn.LET( _xlpm.p,E67, _xlpm.code,IFERROR( IF(AND(LEFT(_xlpm.p,2)="DB",ISNUMBER(SEARCH("-2",_xlpm.p))),"DB-2", IF(LEFT(_xlpm.p,3)="OC-","OC", LEFT(_xlpm.p,_xlfn.XMATCH(TRUE,ISNUMBER(--MID(_xlpm.p,_xlfn.SEQUENCE(LEN(_xlpm.p)),1)))-1) ) ), _xlpm.p ), _xlpm.base,_xlfn.XLOOKUP(_xlpm.code,'Product Code'!A:A,'Product Code'!C:C,""), IF(RIGHT(_xlpm.p,3)="-PO",_xlpm.base&" - Pull-Out",_xlpm.base) )} -> Filler , mais quel type? | I67: {=_xlfn.LET( _xlpm.p,E67, _xlpm.code,IFERROR( IF(AND(LEFT(_xlpm.p,2)="DB",ISNUMBER(SEARCH("-2",_xlpm.p))),"DB-2", IF(LEFT(_xlpm.p,3)="OC-","OC", LEFT(_xlpm.p,_xlfn.XMATCH(TRUE,ISNUMBER(--MID(_xlpm.p,_xlfn.SEQUENCE(LEN(_xlpm.p)),1)))-1) ) ), _xlpm.p ), _xlpm.productType,_xlfn.XLOOKUP(_xlpm.code,'Product Code'!A:A,'Product Code'!D:D,""), IF(OR(RIGHT(_xlpm.p,5)="-Door",RIGHT(_xlpm.p,6)="-DOORS"),_xlpm.productType&" - Door",_xlpm.productType) )} -> - | N67: N/A | O67: N/A
A68: F9-CM2.5X96 | B68: 164 | C68: =B68*0.3 -> 49.2 | E68: =_xlfn.TEXTAFTER(A68,"-") -> CM2.5X96 | F68: {=_xlfn.LET( _xlpm.p,E68, _xlpm.code,IFERROR( IF(AND(LEFT(_xlpm.p,2)="DB",ISNUMBER(SEARCH("-2",_xlpm.p))),"DB-2", IF(LEFT(_xlpm.p,3)="OC-","OC", LEFT(_xlpm.p,_xlfn.XMATCH(TRUE,ISNUMBER(--MID(_xlpm.p,_xlfn.SEQUENCE(LEN(_xlpm.p)),1)))-1) ) ), _xlpm.p ), _xlfn.XLOOKUP(_xlpm.code,'Product Code'!A:A,'Product Code'!B:B,"") )} -> Fillers | G68: {=_xlfn.LET( _xlpm.p,E68, _xlpm.code,IFERROR( IF(AND(LEFT(_xlpm.p,2)="DB",ISNUMBER(SEARCH("-2",_xlpm.p))),"DB-2", IF(LEFT(_xlpm.p,3)="OC-","OC", LEFT(_xlpm.p,_xlfn.XMATCH(TRUE,ISNUMBER(--MID(_xlpm.p,_xlfn.SEQUENCE(LEN(_xlpm.p)),1)))-1) ) ), _xlpm.p ), _xlpm.base,_xlfn.XLOOKUP(_xlpm.code,'Product Code'!A:A,'Product Code'!C:C,""), IF(RIGHT(_xlpm.p,3)="-PO",_xlpm.base&" - Pull-Out",_xlpm.base) )} -> Filler , mais quel type? | I68: {=_xlfn.LET( _xlpm.p,E68, _xlpm.code,IFERROR( IF(AND(LEFT(_xlpm.p,2)="DB",ISNUMBER(SEARCH("-2",_xlpm.p))),"DB-2", IF(LEFT(_xlpm.p,3)="OC-","OC", LEFT(_xlpm.p,_xlfn.XMATCH(TRUE,ISNUMBER(--MID(_xlpm.p,_xlfn.SEQUENCE(LEN(_xlpm.p)),1)))-1) ) ), _xlpm.p ), _xlpm.productType,_xlfn.XLOOKUP(_xlpm.code,'Product Code'!A:A,'Product Code'!D:D,""), IF(OR(RIGHT(_xlpm.p,5)="-Door",RIGHT(_xlpm.p,6)="-DOORS"),_xlpm.productType&" - Door",_xlpm.productType) )} -> - | N68: N/A | O68: N/A
A69: F9-WF1.5120 | B69: 114 | C69: =B69*0.3 -> 34.2 | D69: =C69*1.35 -> 46.17 | E69: =_xlfn.TEXTAFTER(A69,"-") -> WF1.5120 | F69: {=_xlfn.LET( _xlpm.p,E69, _xlpm.code,IFERROR( IF(AND(LEFT(_xlpm.p,2)="DB",ISNUMBER(SEARCH("-2",_xlpm.p))),"DB-2", IF(LEFT(_xlpm.p,3)="OC-","OC", LEFT(_xlpm.p,_xlfn.XMATCH(TRUE,ISNUMBER(--MID(_xlpm.p,_xlfn.SEQUENCE(LEN(_xlpm.p)),1)))-1) ) ), _xlpm.p ), _xlfn.XLOOKUP(_xlpm.code,'Product Code'!A:A,'Product Code'!B:B,"") )} -> Fillers | G69: {=_xlfn.LET( _xlpm.p,E69, _xlpm.code,IFERROR( IF(AND(LEFT(_xlpm.p,2)="DB",ISNUMBER(SEARCH("-2",_xlpm.p))),"DB-2", IF(LEFT(_xlpm.p,3)="OC-","OC", LEFT(_xlpm.p,_xlfn.XMATCH(TRUE,ISNUMBER(--MID(_xlpm.p,_xlfn.SEQUENCE(LEN(_xlpm.p)),1)))-1) ) ), _xlpm.p ), _xlpm.base,_xlfn.XLOOKUP(_xlpm.code,'Product Code'!A:A,'Product Code'!C:C,""), IF(RIGHT(_xlpm.p,3)="-PO",_xlpm.base&" - Pull-Out",_xlpm.base) )} -> Base/Wall/Tall Filler | I69: {=_xlfn.LET( _xlpm.p,E69, _xlpm.code,IFERROR( IF(AND(LEFT(_xlpm.p,2)="DB",ISNUMBER(SEARCH("-2",_xlpm.p))),"DB-2", IF(LEFT(_xlpm.p,3)="OC-","OC", LEFT(_xlpm.p,_xlfn.XMATCH(TRUE,ISNUMBER(--MID(_xlpm.p,_xlfn.SEQUENCE(LEN(_xlpm.p)),1)))-1) ) ), _xlpm.p ), _xlpm.productType,_xlfn.XLOOKUP(_xlpm.code,'Product Code'!A:A,'Product Code'!D:D,""), IF(OR(RIGHT(_xlpm.p,5)="-Door",RIGHT(_xlpm.p,6)="-DOORS"),_xlpm.productType&" - Door",_xlpm.productType) )} -> x | J69: x | K69: 1.5 | L69: 120 | M69: =3/4 -> 0.75 | N69: N/A | O69: N/A
A70: F9-WF1.596 | B70: 83 | C70: =B70*0.3 -> 24.9 | D70: =C70*1.35 -> 33.615 | E70: =_xlfn.TEXTAFTER(A70,"-") -> WF1.596 | F70: {=_xlfn.LET( _xlpm.p,E70, _xlpm.code,IFERROR( IF(AND(LEFT(_xlpm.p,2)="DB",ISNUMBER(SEARCH("-2",_xlpm.p))),"DB-2", IF(LEFT(_xlpm.p,3)="OC-","OC", LEFT(_xlpm.p,_xlfn.XMATCH(TRUE,ISNUMBER(--MID(_xlpm.p,_xlfn.SEQUENCE(LEN(_xlpm.p)),1)))-1) ) ), _xlpm.p ), _xlfn.XLOOKUP(_xlpm.code,'Product Code'!A:A,'Product Code'!B:B,"") )} -> Fillers | G70: {=_xlfn.LET( _xlpm.p,E70, _xlpm.code,IFERROR( IF(AND(LEFT(_xlpm.p,2)="DB",ISNUMBER(SEARCH("-2",_xlpm.p))),"DB-2", IF(LEFT(_xlpm.p,3)="OC-","OC", LEFT(_xlpm.p,_xlfn.XMATCH(TRUE,ISNUMBER(--MID(_xlpm.p,_xlfn.SEQUENCE(LEN(_xlpm.p)),1)))-1) ) ), _xlpm.p ), _xlpm.base,_xlfn.XLOOKUP(_xlpm.code,'Product Code'!A:A,'Product Code'!C:C,""), IF(RIGHT(_xlpm.p,3)="-PO",_xlpm.base&" - Pull-Out",_xlpm.base) )} -> Base/Wall/Tall Filler | I70: {=_xlfn.LET( _xlpm.p,E70, _xlpm.code,IFERROR( IF(AND(LEFT(_xlpm.p,2)="DB",ISNUMBER(SEARCH("-2",_xlpm.p))),"DB-2", IF(LEFT(_xlpm.p,3)="OC-","OC", LEFT(_xlpm.p,_xlfn.XMATCH(TRUE,ISNUMBER(--MID(_xlpm.p,_xlfn.SEQUENCE(LEN(_xlpm.p)),1)))-1) ) ), _xlpm.p ), _xlpm.productType,_xlfn.XLOOKUP(_xlpm.code,'Product Code'!A:A,'Product Code'!D:D,""), IF(OR(RIGHT(_xlpm.p,5)="-Door",RIGHT(_xlpm.p,6)="-DOORS"),_xlpm.productType&" - Door",_xlpm.productType) )} -> x | J70: x | K70: 1.5 | L70: 96 | M70: =3/4 -> 0.75 | N70: N/A | O70: N/A
A71: F9-WF330 | B71: 47 | C71: =B71*0.3 -> 14.1 | D71: =C71*1.35 -> 19.035 | E71: =_xlfn.TEXTAFTER(A71,"-") -> WF330 | F71: {=_xlfn.LET( _xlpm.p,E71, _xlpm.code,IFERROR( IF(AND(LEFT(_xlpm.p,2)="DB",ISNUMBER(SEARCH("-2",_xlpm.p))),"DB-2", IF(LEFT(_xlpm.p,3)="OC-","OC", LEFT(_xlpm.p,_xlfn.XMATCH(TRUE,ISNUMBER(--MID(_xlpm.p,_xlfn.SEQUENCE(LEN(_xlpm.p)),1)))-1) ) ), _xlpm.p ), _xlfn.XLOOKUP(_xlpm.code,'Product Code'!A:A,'Product Code'!B:B,"") )} -> Fillers | G71: {=_xlfn.LET( _xlpm.p,E71, _xlpm.code,IFERROR( IF(AND(LEFT(_xlpm.p,2)="DB",ISNUMBER(SEARCH("-2",_xlpm.p))),"DB-2", IF(LEFT(_xlpm.p,3)="OC-","OC", LEFT(_xlpm.p,_xlfn.XMATCH(TRUE,ISNUMBER(--MID(_xlpm.p,_xlfn.SEQUENCE(LEN(_xlpm.p)),1)))-1) ) ), _xlpm.p ), _xlpm.base,_xlfn.XLOOKUP(_xlpm.code,'Product Code'!A:A,'Product Code'!C:C,""), IF(RIGHT(_xlpm.p,3)="-PO",_xlpm.base&" - Pull-Out",_xlpm.base) )} -> Base/Wall/Tall Filler | I71: {=_xlfn.LET( _xlpm.p,E71, _xlpm.code,IFERROR( IF(AND(LEFT(_xlpm.p,2)="DB",ISNUMBER(SEARCH("-2",_xlpm.p))),"DB-2", IF(LEFT(_xlpm.p,3)="OC-","OC", LEFT(_xlpm.p,_xlfn.XMATCH(TRUE,ISNUMBER(--MID(_xlpm.p,_xlfn.SEQUENCE(LEN(_xlpm.p)),1)))-1) ) ), _xlpm.p ), _xlpm.productType,_xlfn.XLOOKUP(_xlpm.code,'Product Code'!A:A,'Product Code'!D:D,""), IF(OR(RIGHT(_xlpm.p,5)="-Door",RIGHT(_xlpm.p,6)="-DOORS"),_xlpm.productType&" - Door",_xlpm.productType) )} -> x | J71: x | K71: 3 | L71: 30 | M71: =3/4 -> 0.75 | N71: N/A | O71: N/A
A72: F9-WF336 | B72: 51 | C72: =B72*0.3 -> 15.3 | D72: =C72*1.35 -> 20.655 | E72: =_xlfn.TEXTAFTER(A72,"-") -> WF336 | F72: {=_xlfn.LET( _xlpm.p,E72, _xlpm.code,IFERROR( IF(AND(LEFT(_xlpm.p,2)="DB",ISNUMBER(SEARCH("-2",_xlpm.p))),"DB-2", IF(LEFT(_xlpm.p,3)="OC-","OC", LEFT(_xlpm.p,_xlfn.XMATCH(TRUE,ISNUMBER(--MID(_xlpm.p,_xlfn.SEQUENCE(LEN(_xlpm.p)),1)))-1) ) ), _xlpm.p ), _xlfn.XLOOKUP(_xlpm.code,'Product Code'!A:A,'Product Code'!B:B,"") )} -> Fillers | G72: {=_xlfn.LET( _xlpm.p,E72, _xlpm.code,IFERROR( IF(AND(LEFT(_xlpm.p,2)="DB",ISNUMBER(SEARCH("-2",_xlpm.p))),"DB-2", IF(LEFT(_xlpm.p,3)="OC-","OC", LEFT(_xlpm.p,_xlfn.XMATCH(TRUE,ISNUMBER(--MID(_xlpm.p,_xlfn.SEQUENCE(LEN(_xlpm.p)),1)))-1) ) ), _xlpm.p ), _xlpm.base,_xlfn.XLOOKUP(_xlpm.code,'Product Code'!A:A,'Product Code'!C:C,""), IF(RIGHT(_xlpm.p,3)="-PO",_xlpm.base&" - Pull-Out",_xlpm.base) )} -> Base/Wall/Tall Filler | I72: {=_xlfn.LET( _xlpm.p,E72, _xlpm.code,IFERROR( IF(AND(LEFT(_xlpm.p,2)="DB",ISNUMBER(SEARCH("-2",_xlpm.p))),"DB-2", IF(LEFT(_xlpm.p,3)="OC-","OC", LEFT(_xlpm.p,_xlfn.XMATCH(TRUE,ISNUMBER(--MID(_xlpm.p,_xlfn.SEQUENCE(LEN(_xlpm.p)),1)))-1) ) ), _xlpm.p ), _xlpm.productType,_xlfn.XLOOKUP(_xlpm.code,'Product Code'!A:A,'Product Code'!D:D,""), IF(OR(RIGHT(_xlpm.p,5)="-Door",RIGHT(_xlpm.p,6)="-DOORS"),_xlpm.productType&" - Door",_xlpm.productType) )} -> x | J72: x | K72: 3 | L72: 36 | M72: =3/4 -> 0.75 | N72: N/A | O72: N/A
A73: F9-WF342 | B73: 96 | C73: =B73*0.3 -> 28.8 | D73: =C73*1.35 -> 38.88 | E73: =_xlfn.TEXTAFTER(A73,"-") -> WF342 | F73: {=_xlfn.LET( _xlpm.p,E73, _xlpm.code,IFERROR( IF(AND(LEFT(_xlpm.p,2)="DB",ISNUMBER(SEARCH("-2",_xlpm.p))),"DB-2", IF(LEFT(_xlpm.p,3)="OC-","OC", LEFT(_xlpm.p,_xlfn.XMATCH(TRUE,ISNUMBER(--MID(_xlpm.p,_xlfn.SEQUENCE(LEN(_xlpm.p)),1)))-1) ) ), _xlpm.p ), _xlfn.XLOOKUP(_xlpm.code,'Product Code'!A:A,'Product Code'!B:B,"") )} -> Fillers | G73: {=_xlfn.LET( _xlpm.p,E73, _xlpm.code,IFERROR( IF(AND(LEFT(_xlpm.p,2)="DB",ISNUMBER(SEARCH("-2",_xlpm.p))),"DB-2", IF(LEFT(_xlpm.p,3)="OC-","OC", LEFT(_xlpm.p,_xlfn.XMATCH(TRUE,ISNUMBER(--MID(_xlpm.p,_xlfn.SEQUENCE(LEN(_xlpm.p)),1)))-1) ) ), _xlpm.p ), _xlpm.base,_xlfn.XLOOKUP(_xlpm.code,'Product Code'!A:A,'Product Code'!C:C,""), IF(RIGHT(_xlpm.p,3)="-PO",_xlpm.base&" - Pull-Out",_xlpm.base) )} -> Base/Wall/Tall Filler | I73: {=_xlfn.LET( _xlpm.p,E73, _xlpm.code,IFERROR( IF(AND(LEFT(_xlpm.p,2)="DB",ISNUMBER(SEARCH("-2",_xlpm.p))),"DB-2", IF(LEFT(_xlpm.p,3)="OC-","OC", LEFT(_xlpm.p,_xlfn.XMATCH(TRUE,ISNUMBER(--MID(_xlpm.p,_xlfn.SEQUENCE(LEN(_xlpm.p)),1)))-1) ) ), _xlpm.p ), _xlpm.productType,_xlfn.XLOOKUP(_xlpm.code,'Product Code'!A:A,'Product Code'!D:D,""), IF(OR(RIGHT(_xlpm.p,5)="-Door",RIGHT(_xlpm.p,6)="-DOORS"),_xlpm.productType&" - Door",_xlpm.productType) )} -> x | J73: x | K73: 3 | L73: 42 | M73: =3/4 -> 0.75 | N73: N/A | O73: N/A
A74: F9-WF348 | B74: 115 | C74: =B74*0.3 -> 34.5 | D74: =C74*1.35 -> 46.575 | E74: =_xlfn.TEXTAFTER(A74,"-") -> WF348 | F74: {=_xlfn.LET( _xlpm.p,E74, _xlpm.code,IFERROR( IF(AND(LEFT(_xlpm.p,2)="DB",ISNUMBER(SEARCH("-2",_xlpm.p))),"DB-2", IF(LEFT(_xlpm.p,3)="OC-","OC", LEFT(_xlpm.p,_xlfn.XMATCH(TRUE,ISNUMBER(--MID(_xlpm.p,_xlfn.SEQUENCE(LEN(_xlpm.p)),1)))-1) ) ), _xlpm.p ), _xlfn.XLOOKUP(_xlpm.code,'Product Code'!A:A,'Product Code'!B:B,"") )} -> Fillers | G74: {=_xlfn.LET( _xlpm.p,E74, _xlpm.code,IFERROR( IF(AND(LEFT(_xlpm.p,2)="DB",ISNUMBER(SEARCH("-2",_xlpm.p))),"DB-2", IF(LEFT(_xlpm.p,3)="OC-","OC", LEFT(_xlpm.p,_xlfn.XMATCH(TRUE,ISNUMBER(--MID(_xlpm.p,_xlfn.SEQUENCE(LEN(_xlpm.p)),1)))-1) ) ), _xlpm.p ), _xlpm.base,_xlfn.XLOOKUP(_xlpm.code,'Product Code'!A:A,'Product Code'!C:C,""), IF(RIGHT(_xlpm.p,3)="-PO",_xlpm.base&" - Pull-Out",_xlpm.base) )} -> Base/Wall/Tall Filler | I74: {=_xlfn.LET( _xlpm.p,E74, _xlpm.code,IFERROR( IF(AND(LEFT(_xlpm.p,2)="DB",ISNUMBER(SEARCH("-2",_xlpm.p))),"DB-2", IF(LEFT(_xlpm.p,3)="OC-","OC", LEFT(_xlpm.p,_xlfn.XMATCH(TRUE,ISNUMBER(--MID(_xlpm.p,_xlfn.SEQUENCE(LEN(_xlpm.p)),1)))-1) ) ), _xlpm.p ), _xlpm.productType,_xlfn.XLOOKUP(_xlpm.code,'Product Code'!A:A,'Product Code'!D:D,""), IF(OR(RIGHT(_xlpm.p,5)="-Door",RIGHT(_xlpm.p,6)="-DOORS"),_xlpm.productType&" - Door",_xlpm.productType) )} -> x | J74: x | K74: 3 | L74: 48 | M74: =3/4 -> 0.75 | N74: N/A | O74: N/A
A75: F9-WF396 | B75: 133 | C75: =B75*0.3 -> 39.9 | D75: =C75*1.35 -> 53.865 | E75: =_xlfn.TEXTAFTER(A75,"-") -> WF396 | F75: {=_xlfn.LET( _xlpm.p,E75, _xlpm.code,IFERROR( IF(AND(LEFT(_xlpm.p,2)="DB",ISNUMBER(SEARCH("-2",_xlpm.p))),"DB-2", IF(LEFT(_xlpm.p,3)="OC-","OC", LEFT(_xlpm.p,_xlfn.XMATCH(TRUE,ISNUMBER(--MID(_xlpm.p,_xlfn.SEQUENCE(LEN(_xlpm.p)),1)))-1) ) ), _xlpm.p ), _xlfn.XLOOKUP(_xlpm.code,'Product Code'!A:A,'Product Code'!B:B,"") )} -> Fillers | G75: {=_xlfn.LET( _xlpm.p,E75, _xlpm.code,IFERROR( IF(AND(LEFT(_xlpm.p,2)="DB",ISNUMBER(SEARCH("-2",_xlpm.p))),"DB-2", IF(LEFT(_xlpm.p,3)="OC-","OC", LEFT(_xlpm.p,_xlfn.XMATCH(TRUE,ISNUMBER(--MID(_xlpm.p,_xlfn.SEQUENCE(LEN(_xlpm.p)),1)))-1) ) ), _xlpm.p ), _xlpm.base,_xlfn.XLOOKUP(_xlpm.code,'Product Code'!A:A,'Product Code'!C:C,""), IF(RIGHT(_xlpm.p,3)="-PO",_xlpm.base&" - Pull-Out",_xlpm.base) )} -> Base/Wall/Tall Filler | I75: {=_xlfn.LET( _xlpm.p,E75, _xlpm.code,IFERROR( IF(AND(LEFT(_xlpm.p,2)="DB",ISNUMBER(SEARCH("-2",_xlpm.p))),"DB-2", IF(LEFT(_xlpm.p,3)="OC-","OC", LEFT(_xlpm.p,_xlfn.XMATCH(TRUE,ISNUMBER(--MID(_xlpm.p,_xlfn.SEQUENCE(LEN(_xlpm.p)),1)))-1) ) ), _xlpm.p ), _xlpm.productType,_xlfn.XLOOKUP(_xlpm.code,'Product Code'!A:A,'Product Code'!D:D,""), IF(OR(RIGHT(_xlpm.p,5)="-Door",RIGHT(_xlpm.p,6)="-DOORS"),_xlpm.productType&" - Door",_xlpm.productType) )} -> x | J75: x | K75: 3 | L75: 96 | M75: =3/4 -> 0.75 | N75: N/A | O75: N/A
A76: F9-WF3X120 | B76: 182 | C76: =B76*0.3 -> 54.6 | D76: =C76*1.35 -> 73.71 | E76: =_xlfn.TEXTAFTER(A76,"-") -> WF3X120 | F76: {=_xlfn.LET( _xlpm.p,E76, _xlpm.code,IFERROR( IF(AND(LEFT(_xlpm.p,2)="DB",ISNUMBER(SEARCH("-2",_xlpm.p))),"DB-2", IF(LEFT(_xlpm.p,3)="OC-","OC", LEFT(_xlpm.p,_xlfn.XMATCH(TRUE,ISNUMBER(--MID(_xlpm.p,_xlfn.SEQUENCE(LEN(_xlpm.p)),1)))-1) ) ), _xlpm.p ), _xlfn.XLOOKUP(_xlpm.code,'Product Code'!A:A,'Product Code'!B:B,"") )} -> Fillers | G76: {=_xlfn.LET( _xlpm.p,E76, _xlpm.code,IFERROR( IF(AND(LEFT(_xlpm.p,2)="DB",ISNUMBER(SEARCH("-2",_xlpm.p))),"DB-2", IF(LEFT(_xlpm.p,3)="OC-","OC", LEFT(_xlpm.p,_xlfn.XMATCH(TRUE,ISNUMBER(--MID(_xlpm.p,_xlfn.SEQUENCE(LEN(_xlpm.p)),1)))-1) ) ), _xlpm.p ), _xlpm.base,_xlfn.XLOOKUP(_xlpm.code,'Product Code'!A:A,'Product Code'!C:C,""), IF(RIGHT(_xlpm.p,3)="-PO",_xlpm.base&" - Pull-Out",_xlpm.base) )} -> Base/Wall/Tall Filler | I76: {=_xlfn.LET( _xlpm.p,E76, _xlpm.code,IFERROR( IF(AND(LEFT(_xlpm.p,2)="DB",ISNUMBER(SEARCH("-2",_xlpm.p))),"DB-2", IF(LEFT(_xlpm.p,3)="OC-","OC", LEFT(_xlpm.p,_xlfn.XMATCH(TRUE,ISNUMBER(--MID(_xlpm.p,_xlfn.SEQUENCE(LEN(_xlpm.p)),1)))-1) ) ), _xlpm.p ), _xlpm.productType,_xlfn.XLOOKUP(_xlpm.code,'Product Code'!A:A,'Product Code'!D:D,""), IF(OR(RIGHT(_xlpm.p,5)="-Door",RIGHT(_xlpm.p,6)="-DOORS"),_xlpm.productType&" - Door",_xlpm.productType) )} -> x | J76: x | K76: 3 | L76: 120 | M76: =3/4 -> 0.75 | N76: N/A | O76: N/A
A77: F9-WF6*126 | B77: 357 | C77: =B77*0.3 -> 107.1 | D77: =C77*1.35 -> 144.585 | E77: =_xlfn.TEXTAFTER(A77,"-") -> WF6*126 | F77: {=_xlfn.LET( _xlpm.p,E77, _xlpm.code,IFERROR( IF(AND(LEFT(_xlpm.p,2)="DB",ISNUMBER(SEARCH("-2",_xlpm.p))),"DB-2", IF(LEFT(_xlpm.p,3)="OC-","OC", LEFT(_xlpm.p,_xlfn.XMATCH(TRUE,ISNUMBER(--MID(_xlpm.p,_xlfn.SEQUENCE(LEN(_xlpm.p)),1)))-1) ) ), _xlpm.p ), _xlfn.XLOOKUP(_xlpm.code,'Product Code'!A:A,'Product Code'!B:B,"") )} -> Fillers | G77: {=_xlfn.LET( _xlpm.p,E77, _xlpm.code,IFERROR( IF(AND(LEFT(_xlpm.p,2)="DB",ISNUMBER(SEARCH("-2",_xlpm.p))),"DB-2", IF(LEFT(_xlpm.p,3)="OC-","OC", LEFT(_xlpm.p,_xlfn.XMATCH(TRUE,ISNUMBER(--MID(_xlpm.p,_xlfn.SEQUENCE(LEN(_xlpm.p)),1)))-1) ) ), _xlpm.p ), _xlpm.base,_xlfn.XLOOKUP(_xlpm.code,'Product Code'!A:A,'Product Code'!C:C,""), IF(RIGHT(_xlpm.p,3)="-PO",_xlpm.base&" - Pull-Out",_xlpm.base) )} -> Base/Wall/Tall Filler | I77: {=_xlfn.LET( _xlpm.p,E77, _xlpm.code,IFERROR( IF(AND(LEFT(_xlpm.p,2)="DB",ISNUMBER(SEARCH("-2",_xlpm.p))),"DB-2", IF(LEFT(_xlpm.p,3)="OC-","OC", LEFT(_xlpm.p,_xlfn.XMATCH(TRUE,ISNUMBER(--MID(_xlpm.p,_xlfn.SEQUENCE(LEN(_xlpm.p)),1)))-1) ) ), _xlpm.p ), _xlpm.productType,_xlfn.XLOOKUP(_xlpm.code,'Product Code'!A:A,'Product Code'!D:D,""), IF(OR(RIGHT(_xlpm.p,5)="-Door",RIGHT(_xlpm.p,6)="-DOORS"),_xlpm.productType&" - Door",_xlpm.productType) )} -> x | J77: x | K77: 6 | L77: 126 | M77: =3/4 -> 0.75 | N77: N/A | O77: N/A
A78: F9-WF636 | B78: 98 | C78: =B78*0.3 -> 29.4 | D78: =C78*1.35 -> 39.69 | E78: =_xlfn.TEXTAFTER(A78,"-") -> WF636 | F78: {=_xlfn.LET( _xlpm.p,E78, _xlpm.code,IFERROR( IF(AND(LEFT(_xlpm.p,2)="DB",ISNUMBER(SEARCH("-2",_xlpm.p))),"DB-2", IF(LEFT(_xlpm.p,3)="OC-","OC", LEFT(_xlpm.p,_xlfn.XMATCH(TRUE,ISNUMBER(--MID(_xlpm.p,_xlfn.SEQUENCE(LEN(_xlpm.p)),1)))-1) ) ), _xlpm.p ), _xlfn.XLOOKUP(_xlpm.code,'Product Code'!A:A,'Product Code'!B:B,"") )} -> Fillers | G78: {=_xlfn.LET( _xlpm.p,E78, _xlpm.code,IFERROR( IF(AND(LEFT(_xlpm.p,2)="DB",ISNUMBER(SEARCH("-2",_xlpm.p))),"DB-2", IF(LEFT(_xlpm.p,3)="OC-","OC", LEFT(_xlpm.p,_xlfn.XMATCH(TRUE,ISNUMBER(--MID(_xlpm.p,_xlfn.SEQUENCE(LEN(_xlpm.p)),1)))-1) ) ), _xlpm.p ), _xlpm.base,_xlfn.XLOOKUP(_xlpm.code,'Product Code'!A:A,'Product Code'!C:C,""), IF(RIGHT(_xlpm.p,3)="-PO",_xlpm.base&" - Pull-Out",_xlpm.base) )} -> Base/Wall/Tall Filler | I78: {=_xlfn.LET( _xlpm.p,E78, _xlpm.code,IFERROR( IF(AND(LEFT(_xlpm.p,2)="DB",ISNUMBER(SEARCH("-2",_xlpm.p))),"DB-2", IF(LEFT(_xlpm.p,3)="OC-","OC", LEFT(_xlpm.p,_xlfn.XMATCH(TRUE,ISNUMBER(--MID(_xlpm.p,_xlfn.SEQUENCE(LEN(_xlpm.p)),1)))-1) ) ), _xlpm.p ), _xlpm.productType,_xlfn.XLOOKUP(_xlpm.code,'Product Code'!A:A,'Product Code'!D:D,""), IF(OR(RIGHT(_xlpm.p,5)="-Door",RIGHT(_xlpm.p,6)="-DOORS"),_xlpm.productType&" - Door",_xlpm.productType) )} -> x | J78: x | K78: 6 | L78: 36 | M78: =3/4 -> 0.75 | N78: N/A | O78: N/A
A79: F9-WF696 | B79: 278 | C79: =B79*0.3 -> 83.4 | D79: =C79*1.35 -> 112.59 | E79: =_xlfn.TEXTAFTER(A79,"-") -> WF696 | F79: {=_xlfn.LET( _xlpm.p,E79, _xlpm.code,IFERROR( IF(AND(LEFT(_xlpm.p,2)="DB",ISNUMBER(SEARCH("-2",_xlpm.p))),"DB-2", IF(LEFT(_xlpm.p,3)="OC-","OC", LEFT(_xlpm.p,_xlfn.XMATCH(TRUE,ISNUMBER(--MID(_xlpm.p,_xlfn.SEQUENCE(LEN(_xlpm.p)),1)))-1) ) ), _xlpm.p ), _xlfn.XLOOKUP(_xlpm.code,'Product Code'!A:A,'Product Code'!B:B,"") )} -> Fillers | G79: {=_xlfn.LET( _xlpm.p,E79, _xlpm.code,IFERROR( IF(AND(LEFT(_xlpm.p,2)="DB",ISNUMBER(SEARCH("-2",_xlpm.p))),"DB-2", IF(LEFT(_xlpm.p,3)="OC-","OC", LEFT(_xlpm.p,_xlfn.XMATCH(TRUE,ISNUMBER(--MID(_xlpm.p,_xlfn.SEQUENCE(LEN(_xlpm.p)),1)))-1) ) ), _xlpm.p ), _xlpm.base,_xlfn.XLOOKUP(_xlpm.code,'Product Code'!A:A,'Product Code'!C:C,""), IF(RIGHT(_xlpm.p,3)="-PO",_xlpm.base&" - Pull-Out",_xlpm.base) )} -> Base/Wall/Tall Filler | I79: {=_xlfn.LET( _xlpm.p,E79, _xlpm.code,IFERROR( IF(AND(LEFT(_xlpm.p,2)="DB",ISNUMBER(SEARCH("-2",_xlpm.p))),"DB-2", IF(LEFT(_xlpm.p,3)="OC-","OC", LEFT(_xlpm.p,_xlfn.XMATCH(TRUE,ISNUMBER(--MID(_xlpm.p,_xlfn.SEQUENCE(LEN(_xlpm.p)),1)))-1) ) ), _xlpm.p ), _xlpm.productType,_xlfn.XLOOKUP(_xlpm.code,'Product Code'!A:A,'Product Code'!D:D,""), IF(OR(RIGHT(_xlpm.p,5)="-Door",RIGHT(_xlpm.p,6)="-DOORS"),_xlpm.productType&" - Door",_xlpm.productType) )} -> x | J79: x | K79: 6 | L79: 96 | M79: =3/4 -> 0.75 | N79: N/A | O79: N/A
A80: F9-WF6X120 | B80: 339 | C80: =B80*0.3 -> 101.7 | D80: =C80*1.35 -> 137.295 | E80: =_xlfn.TEXTAFTER(A80,"-") -> WF6X120 | F80: {=_xlfn.LET( _xlpm.p,E80, _xlpm.code,IFERROR( IF(AND(LEFT(_xlpm.p,2)="DB",ISNUMBER(SEARCH("-2",_xlpm.p))),"DB-2", IF(LEFT(_xlpm.p,3)="OC-","OC", LEFT(_xlpm.p,_xlfn.XMATCH(TRUE,ISNUMBER(--MID(_xlpm.p,_xlfn.SEQUENCE(LEN(_xlpm.p)),1)))-1) ) ), _xlpm.p ), _xlfn.XLOOKUP(_xlpm.code,'Product Code'!A:A,'Product Code'!B:B,"") )} -> Fillers | G80: {=_xlfn.LET( _xlpm.p,E80, _xlpm.code,IFERROR( IF(AND(LEFT(_xlpm.p,2)="DB",ISNUMBER(SEARCH("-2",_xlpm.p))),"DB-2", IF(LEFT(_xlpm.p,3)="OC-","OC", LEFT(_xlpm.p,_xlfn.XMATCH(TRUE,ISNUMBER(--MID(_xlpm.p,_xlfn.SEQUENCE(LEN(_xlpm.p)),1)))-1) ) ), _xlpm.p ), _xlpm.base,_xlfn.XLOOKUP(_xlpm.code,'Product Code'!A:A,'Product Code'!C:C,""), IF(RIGHT(_xlpm.p,3)="-PO",_xlpm.base&" - Pull-Out",_xlpm.base) )} -> Base/Wall/Tall Filler | I80: {=_xlfn.LET( _xlpm.p,E80, _xlpm.code,IFERROR( IF(AND(LEFT(_xlpm.p,2)="DB",ISNUMBER(SEARCH("-2",_xlpm.p))),"DB-2", IF(LEFT(_xlpm.p,3)="OC-","OC", LEFT(_xlpm.p,_xlfn.XMATCH(TRUE,ISNUMBER(--MID(_xlpm.p,_xlfn.SEQUENCE(LEN(_xlpm.p)),1)))-1) ) ), _xlpm.p ), _xlpm.productType,_xlfn.XLOOKUP(_xlpm.code,'Product Code'!A:A,'Product Code'!D:D,""), IF(OR(RIGHT(_xlpm.p,5)="-Door",RIGHT(_xlpm.p,6)="-DOORS"),_xlpm.productType&" - Door",_xlpm.productType) )} -> x | J80: x | K80: 6 | L80: 120 | M80: =3/4 -> 0.75 | N80: N/A | O80: N/A
A81: F9-IBP9618 | B81: 223 | C81: =B81*0.3 -> 66.9 | E81: =_xlfn.TEXTAFTER(A81,"-") -> IBP9618 | F81: {=_xlfn.LET( _xlpm.p,E81, _xlpm.code,IFERROR( IF(AND(LEFT(_xlpm.p,2)="DB",ISNUMBER(SEARCH("-2",_xlpm.p))),"DB-2", IF(LEFT(_xlpm.p,3)="OC-","OC", LEFT(_xlpm.p,_xlfn.XMATCH(TRUE,ISNUMBER(--MID(_xlpm.p,_xlfn.SEQUENCE(LEN(_xlpm.p)),1)))-1) ) ), _xlpm.p ), _xlfn.XLOOKUP(_xlpm.code,'Product Code'!A:A,'Product Code'!B:B,"") )} -> Island Back Panel | G81: {=_xlfn.LET( _xlpm.p,E81, _xlpm.code,IFERROR( IF(AND(LEFT(_xlpm.p,2)="DB",ISNUMBER(SEARCH("-2",_xlpm.p))),"DB-2", IF(LEFT(_xlpm.p,3)="OC-","OC", LEFT(_xlpm.p,_xlfn.XMATCH(TRUE,ISNUMBER(--MID(_xlpm.p,_xlfn.SEQUENCE(LEN(_xlpm.p)),1)))-1) ) ), _xlpm.p ), _xlpm.base,_xlfn.XLOOKUP(_xlpm.code,'Product Code'!A:A,'Product Code'!C:C,""), IF(RIGHT(_xlpm.p,3)="-PO",_xlpm.base&" - Pull-Out",_xlpm.base) )} -> 0 | I81: {=_xlfn.LET( _xlpm.p,E81, _xlpm.code,IFERROR( IF(AND(LEFT(_xlpm.p,2)="DB",ISNUMBER(SEARCH("-2",_xlpm.p))),"DB-2", IF(LEFT(_xlpm.p,3)="OC-","OC", LEFT(_xlpm.p,_xlfn.XMATCH(TRUE,ISNUMBER(--MID(_xlpm.p,_xlfn.SEQUENCE(LEN(_xlpm.p)),1)))-1) ) ), _xlpm.p ), _xlpm.productType,_xlfn.XLOOKUP(_xlpm.code,'Product Code'!A:A,'Product Code'!D:D,""), IF(OR(RIGHT(_xlpm.p,5)="-Door",RIGHT(_xlpm.p,6)="-DOORS"),_xlpm.productType&" - Door",_xlpm.productType) )} -> - | N81: =IF(ISNUMBER(SEARCH("Cabinet",F81))=FALSE,"N/A",IF(K81>=24,2,1)) -> N/A | O81: =IF(ISNUMBER(SEARCH("Cabinet",F81))=FALSE,"N/A", IF(ISNUMBER(SEARCH("DB",E81)), IF(ISNUMBER(SEARCH("-2",E81)),2,3), IF(ISNUMBER(SEARCH("-PO",E81)),1, IF(LEFT(E81,1)="B",1,0) ) ) ) -> N/A
A82: F9-IBP9636 | B82: 445 | C82: =B82*0.3 -> 133.5 | E82: =_xlfn.TEXTAFTER(A82,"-") -> IBP9636 | F82: {=_xlfn.LET( _xlpm.p,E82, _xlpm.code,IFERROR( IF(AND(LEFT(_xlpm.p,2)="DB",ISNUMBER(SEARCH("-2",_xlpm.p))),"DB-2", IF(LEFT(_xlpm.p,3)="OC-","OC", LEFT(_xlpm.p,_xlfn.XMATCH(TRUE,ISNUMBER(--MID(_xlpm.p,_xlfn.SEQUENCE(LEN(_xlpm.p)),1)))-1) ) ), _xlpm.p ), _xlfn.XLOOKUP(_xlpm.code,'Product Code'!A:A,'Product Code'!B:B,"") )} -> Island Back Panel | G82: {=_xlfn.LET( _xlpm.p,E82, _xlpm.code,IFERROR( IF(AND(LEFT(_xlpm.p,2)="DB",ISNUMBER(SEARCH("-2",_xlpm.p))),"DB-2", IF(LEFT(_xlpm.p,3)="OC-","OC", LEFT(_xlpm.p,_xlfn.XMATCH(TRUE,ISNUMBER(--MID(_xlpm.p,_xlfn.SEQUENCE(LEN(_xlpm.p)),1)))-1) ) ), _xlpm.p ), _xlpm.base,_xlfn.XLOOKUP(_xlpm.code,'Product Code'!A:A,'Product Code'!C:C,""), IF(RIGHT(_xlpm.p,3)="-PO",_xlpm.base&" - Pull-Out",_xlpm.base) )} -> 0 | I82: {=_xlfn.LET( _xlpm.p,E82, _xlpm.code,IFERROR( IF(AND(LEFT(_xlpm.p,2)="DB",ISNUMBER(SEARCH("-2",_xlpm.p))),"DB-2", IF(LEFT(_xlpm.p,3)="OC-","OC", LEFT(_xlpm.p,_xlfn.XMATCH(TRUE,ISNUMBER(--MID(_xlpm.p,_xlfn.SEQUENCE(LEN(_xlpm.p)),1)))-1) ) ), _xlpm.p ), _xlpm.productType,_xlfn.XLOOKUP(_xlpm.code,'Product Code'!A:A,'Product Code'!D:D,""), IF(OR(RIGHT(_xlpm.p,5)="-Door",RIGHT(_xlpm.p,6)="-DOORS"),_xlpm.productType&" - Door",_xlpm.productType) )} -> - | N82: =IF(ISNUMBER(SEARCH("Cabinet",F82))=FALSE,"N/A",IF(K82>=24,2,1)) -> N/A | O82: =IF(ISNUMBER(SEARCH("Cabinet",F82))=FALSE,"N/A", IF(ISNUMBER(SEARCH("DB",E82)), IF(ISNUMBER(SEARCH("-2",E82)),2,3), IF(ISNUMBER(SEARCH("-PO",E82)),1, IF(LEFT(E82,1)="B",1,0) ) ) ) -> N/A
A83: F9-ISP25.75X36 | B83: 120 | C83: =B83*0.3 -> 36 | E83: =_xlfn.TEXTAFTER(A83,"-") -> ISP25.75X36 | F83: {=_xlfn.LET( _xlpm.p,E83, _xlpm.code,IFERROR( IF(AND(LEFT(_xlpm.p,2)="DB",ISNUMBER(SEARCH("-2",_xlpm.p))),"DB-2", IF(LEFT(_xlpm.p,3)="OC-","OC", LEFT(_xlpm.p,_xlfn.XMATCH(TRUE,ISNUMBER(--MID(_xlpm.p,_xlfn.SEQUENCE(LEN(_xlpm.p)),1)))-1) ) ), _xlpm.p ), _xlfn.XLOOKUP(_xlpm.code,'Product Code'!A:A,'Product Code'!B:B,"") )} -> Island Skin Panel probablement | G83: {=_xlfn.LET( _xlpm.p,E83, _xlpm.code,IFERROR( IF(AND(LEFT(_xlpm.p,2)="DB",ISNUMBER(SEARCH("-2",_xlpm.p))),"DB-2", IF(LEFT(_xlpm.p,3)="OC-","OC", LEFT(_xlpm.p,_xlfn.XMATCH(TRUE,ISNUMBER(--MID(_xlpm.p,_xlfn.SEQUENCE(LEN(_xlpm.p)),1)))-1) ) ), _xlpm.p ), _xlpm.base,_xlfn.XLOOKUP(_xlpm.code,'Product Code'!A:A,'Product Code'!C:C,""), IF(RIGHT(_xlpm.p,3)="-PO",_xlpm.base&" - Pull-Out",_xlpm.base) )} -> 0 | I83: {=_xlfn.LET( _xlpm.p,E83, _xlpm.code,IFERROR( IF(AND(LEFT(_xlpm.p,2)="DB",ISNUMBER(SEARCH("-2",_xlpm.p))),"DB-2", IF(LEFT(_xlpm.p,3)="OC-","OC", LEFT(_xlpm.p,_xlfn.XMATCH(TRUE,ISNUMBER(--MID(_xlpm.p,_xlfn.SEQUENCE(LEN(_xlpm.p)),1)))-1) ) ), _xlpm.p ), _xlpm.productType,_xlfn.XLOOKUP(_xlpm.code,'Product Code'!A:A,'Product Code'!D:D,""), IF(OR(RIGHT(_xlpm.p,5)="-Door",RIGHT(_xlpm.p,6)="-DOORS"),_xlpm.productType&" - Door",_xlpm.productType) )} -> - | N83: =IF(ISNUMBER(SEARCH("Cabinet",F83))=FALSE,"N/A",IF(K83>=24,2,1)) -> N/A | O83: =IF(ISNUMBER(SEARCH("Cabinet",F83))=FALSE,"N/A", IF(ISNUMBER(SEARCH("DB",E83)), IF(ISNUMBER(SEARCH("-2",E83)),2,3), IF(ISNUMBER(SEARCH("-PO",E83)),1, IF(LEFT(E83,1)="B",1,0) ) ) ) -> N/A
A84: F9-ISP37.75X36 | B84: 175 | C84: =B84*0.3 -> 52.5 | E84: =_xlfn.TEXTAFTER(A84,"-") -> ISP37.75X36 | F84: {=_xlfn.LET( _xlpm.p,E84, _xlpm.code,IFERROR( IF(AND(LEFT(_xlpm.p,2)="DB",ISNUMBER(SEARCH("-2",_xlpm.p))),"DB-2", IF(LEFT(_xlpm.p,3)="OC-","OC", LEFT(_xlpm.p,_xlfn.XMATCH(TRUE,ISNUMBER(--MID(_xlpm.p,_xlfn.SEQUENCE(LEN(_xlpm.p)),1)))-1) ) ), _xlpm.p ), _xlfn.XLOOKUP(_xlpm.code,'Product Code'!A:A,'Product Code'!B:B,"") )} -> Island Skin Panel probablement | G84: {=_xlfn.LET( _xlpm.p,E84, _xlpm.code,IFERROR( IF(AND(LEFT(_xlpm.p,2)="DB",ISNUMBER(SEARCH("-2",_xlpm.p))),"DB-2", IF(LEFT(_xlpm.p,3)="OC-","OC", LEFT(_xlpm.p,_xlfn.XMATCH(TRUE,ISNUMBER(--MID(_xlpm.p,_xlfn.SEQUENCE(LEN(_xlpm.p)),1)))-1) ) ), _xlpm.p ), _xlpm.base,_xlfn.XLOOKUP(_xlpm.code,'Product Code'!A:A,'Product Code'!C:C,""), IF(RIGHT(_xlpm.p,3)="-PO",_xlpm.base&" - Pull-Out",_xlpm.base) )} -> 0 | I84: {=_xlfn.LET( _xlpm.p,E84, _xlpm.code,IFERROR( IF(AND(LEFT(_xlpm.p,2)="DB",ISNUMBER(SEARCH("-2",_xlpm.p))),"DB-2", IF(LEFT(_xlpm.p,3)="OC-","OC", LEFT(_xlpm.p,_xlfn.XMATCH(TRUE,ISNUMBER(--MID(_xlpm.p,_xlfn.SEQUENCE(LEN(_xlpm.p)),1)))-1) ) ), _xlpm.p ), _xlpm.productType,_xlfn.XLOOKUP(_xlpm.code,'Product Code'!A:A,'Product Code'!D:D,""), IF(OR(RIGHT(_xlpm.p,5)="-Door",RIGHT(_xlpm.p,6)="-DOORS"),_xlpm.productType&" - Door",_xlpm.productType) )} -> - | N84: =IF(ISNUMBER(SEARCH("Cabinet",F84))=FALSE,"N/A",IF(K84>=24,2,1)) -> N/A | O84: =IF(ISNUMBER(SEARCH("Cabinet",F84))=FALSE,"N/A", IF(ISNUMBER(SEARCH("DB",E84)), IF(ISNUMBER(SEARCH("-2",E84)),2,3), IF(ISNUMBER(SEARCH("-PO",E84)),1, IF(LEFT(E84,1)="B",1,0) ) ) ) -> N/A
A85: F9-BM33*6 | B85: 189 | C85: =B85*0.3 -> 56.7 | E85: =_xlfn.TEXTAFTER(A85,"-") -> BM33*6 | F85: {=_xlfn.LET( _xlpm.p,E85, _xlpm.code,IFERROR( IF(AND(LEFT(_xlpm.p,2)="DB",ISNUMBER(SEARCH("-2",_xlpm.p))),"DB-2", IF(LEFT(_xlpm.p,3)="OC-","OC", LEFT(_xlpm.p,_xlfn.XMATCH(TRUE,ISNUMBER(--MID(_xlpm.p,_xlfn.SEQUENCE(LEN(_xlpm.p)),1)))-1) ) ), _xlpm.p ), _xlfn.XLOOKUP(_xlpm.code,'Product Code'!A:A,'Product Code'!B:B,"") )} -> Moldings | G85: {=_xlfn.LET( _xlpm.p,E85, _xlpm.code,IFERROR( IF(AND(LEFT(_xlpm.p,2)="DB",ISNUMBER(SEARCH("-2",_xlpm.p))),"DB-2", IF(LEFT(_xlpm.p,3)="OC-","OC", LEFT(_xlpm.p,_xlfn.XMATCH(TRUE,ISNUMBER(--MID(_xlpm.p,_xlfn.SEQUENCE(LEN(_xlpm.p)),1)))-1) ) ), _xlpm.p ), _xlpm.base,_xlfn.XLOOKUP(_xlpm.code,'Product Code'!A:A,'Product Code'!C:C,""), IF(RIGHT(_xlpm.p,3)="-PO",_xlpm.base&" - Pull-Out",_xlpm.base) )} -> Base molding | I85: {=_xlfn.LET( _xlpm.p,E85, _xlpm.code,IFERROR( IF(AND(LEFT(_xlpm.p,2)="DB",ISNUMBER(SEARCH("-2",_xlpm.p))),"DB-2", IF(LEFT(_xlpm.p,3)="OC-","OC", LEFT(_xlpm.p,_xlfn.XMATCH(TRUE,ISNUMBER(--MID(_xlpm.p,_xlfn.SEQUENCE(LEN(_xlpm.p)),1)))-1) ) ), _xlpm.p ), _xlpm.productType,_xlfn.XLOOKUP(_xlpm.code,'Product Code'!A:A,'Product Code'!D:D,""), IF(OR(RIGHT(_xlpm.p,5)="-Door",RIGHT(_xlpm.p,6)="-DOORS"),_xlpm.productType&" - Door",_xlpm.productType) )} -> x | N85: N/A | O85: N/A
A86: F9-BM96 | B86: 276 | C86: =B86*0.3 -> 82.8 | E86: =_xlfn.TEXTAFTER(A86,"-") -> BM96 | F86: {=_xlfn.LET( _xlpm.p,E86, _xlpm.code,IFERROR( IF(AND(LEFT(_xlpm.p,2)="DB",ISNUMBER(SEARCH("-2",_xlpm.p))),"DB-2", IF(LEFT(_xlpm.p,3)="OC-","OC", LEFT(_xlpm.p,_xlfn.XMATCH(TRUE,ISNUMBER(--MID(_xlpm.p,_xlfn.SEQUENCE(LEN(_xlpm.p)),1)))-1) ) ), _xlpm.p ), _xlfn.XLOOKUP(_xlpm.code,'Product Code'!A:A,'Product Code'!B:B,"") )} -> Moldings | G86: {=_xlfn.LET( _xlpm.p,E86, _xlpm.code,IFERROR( IF(AND(LEFT(_xlpm.p,2)="DB",ISNUMBER(SEARCH("-2",_xlpm.p))),"DB-2", IF(LEFT(_xlpm.p,3)="OC-","OC", LEFT(_xlpm.p,_xlfn.XMATCH(TRUE,ISNUMBER(--MID(_xlpm.p,_xlfn.SEQUENCE(LEN(_xlpm.p)),1)))-1) ) ), _xlpm.p ), _xlpm.base,_xlfn.XLOOKUP(_xlpm.code,'Product Code'!A:A,'Product Code'!C:C,""), IF(RIGHT(_xlpm.p,3)="-PO",_xlpm.base&" - Pull-Out",_xlpm.base) )} -> Base molding | I86: {=_xlfn.LET( _xlpm.p,E86, _xlpm.code,IFERROR( IF(AND(LEFT(_xlpm.p,2)="DB",ISNUMBER(SEARCH("-2",_xlpm.p))),"DB-2", IF(LEFT(_xlpm.p,3)="OC-","OC", LEFT(_xlpm.p,_xlfn.XMATCH(TRUE,ISNUMBER(--MID(_xlpm.p,_xlfn.SEQUENCE(LEN(_xlpm.p)),1)))-1) ) ), _xlpm.p ), _xlpm.productType,_xlfn.XLOOKUP(_xlpm.code,'Product Code'!A:A,'Product Code'!D:D,""), IF(OR(RIGHT(_xlpm.p,5)="-Door",RIGHT(_xlpm.p,6)="-DOORS"),_xlpm.productType&" - Door",_xlpm.productType) )} -> x | N86: =IF(ISNUMBER(SEARCH("Cabinet",F86))=FALSE,"N/A",IF(K86>=24,2,1)) -> N/A | O86: =IF(ISNUMBER(SEARCH("Cabinet",F86))=FALSE,"N/A", IF(ISNUMBER(SEARCH("DB",E86)), IF(ISNUMBER(SEARCH("-2",E86)),2,3), IF(ISNUMBER(SEARCH("-PO",E86)),1, IF(LEFT(E86,1)="B",1,0) ) ) ) -> N/A
A87: F9-OCM8 | B87: 54 | C87: =B87*0.3 -> 16.2 | E87: =_xlfn.TEXTAFTER(A87,"-") -> OCM8 | F87: {=_xlfn.LET( _xlpm.p,E87, _xlpm.code,IFERROR( IF(AND(LEFT(_xlpm.p,2)="DB",ISNUMBER(SEARCH("-2",_xlpm.p))),"DB-2", IF(LEFT(_xlpm.p,3)="OC-","OC", LEFT(_xlpm.p,_xlfn.XMATCH(TRUE,ISNUMBER(--MID(_xlpm.p,_xlfn.SEQUENCE(LEN(_xlpm.p)),1)))-1) ) ), _xlpm.p ), _xlfn.XLOOKUP(_xlpm.code,'Product Code'!A:A,'Product Code'!B:B,"") )} -> Moldings | G87: {=_xlfn.LET( _xlpm.p,E87, _xlpm.code,IFERROR( IF(AND(LEFT(_xlpm.p,2)="DB",ISNUMBER(SEARCH("-2",_xlpm.p))),"DB-2", IF(LEFT(_xlpm.p,3)="OC-","OC", LEFT(_xlpm.p,_xlfn.XMATCH(TRUE,ISNUMBER(--MID(_xlpm.p,_xlfn.SEQUENCE(LEN(_xlpm.p)),1)))-1) ) ), _xlpm.p ), _xlpm.base,_xlfn.XLOOKUP(_xlpm.code,'Product Code'!A:A,'Product Code'!C:C,""), IF(RIGHT(_xlpm.p,3)="-PO",_xlpm.base&" - Pull-Out",_xlpm.base) )} -> Outside Corner Molding | H87: N/A | I87: {=_xlfn.LET( _xlpm.p,E87, _xlpm.code,IFERROR( IF(AND(LEFT(_xlpm.p,2)="DB",ISNUMBER(SEARCH("-2",_xlpm.p))),"DB-2", IF(LEFT(_xlpm.p,3)="OC-","OC", LEFT(_xlpm.p,_xlfn.XMATCH(TRUE,ISNUMBER(--MID(_xlpm.p,_xlfn.SEQUENCE(LEN(_xlpm.p)),1)))-1) ) ), _xlpm.p ), _xlpm.productType,_xlfn.XLOOKUP(_xlpm.code,'Product Code'!A:A,'Product Code'!D:D,""), IF(OR(RIGHT(_xlpm.p,5)="-Door",RIGHT(_xlpm.p,6)="-DOORS"),_xlpm.productType&" - Door",_xlpm.productType) )} -> x | J87: x | K87: 96 | L87: =3/4 -> 0.75 | M87: =3/4 -> 0.75 | N87: =IF(ISNUMBER(SEARCH("Cabinet",F87))=FALSE,"N/A",IF(K87>=24,2,1)) -> N/A | O87: =IF(ISNUMBER(SEARCH("Cabinet",F87))=FALSE,"N/A", IF(ISNUMBER(SEARCH("DB",E87)), IF(ISNUMBER(SEARCH("-2",E87)),2,3), IF(ISNUMBER(SEARCH("-PO",E87)),1, IF(LEFT(E87,1)="B",1,0) ) ) ) -> N/A
A88: F9-SM1.5 | B88: 51 | C88: =B88*0.3 -> 15.3 | E88: =_xlfn.TEXTAFTER(A88,"-") -> SM1.5 | F88: {=_xlfn.LET( _xlpm.p,E88, _xlpm.code,IFERROR( IF(AND(LEFT(_xlpm.p,2)="DB",ISNUMBER(SEARCH("-2",_xlpm.p))),"DB-2", IF(LEFT(_xlpm.p,3)="OC-","OC", LEFT(_xlpm.p,_xlfn.XMATCH(TRUE,ISNUMBER(--MID(_xlpm.p,_xlfn.SEQUENCE(LEN(_xlpm.p)),1)))-1) ) ), _xlpm.p ), _xlfn.XLOOKUP(_xlpm.code,'Product Code'!A:A,'Product Code'!B:B,"") )} -> Moldings | G88: {=_xlfn.LET( _xlpm.p,E88, _xlpm.code,IFERROR( IF(AND(LEFT(_xlpm.p,2)="DB",ISNUMBER(SEARCH("-2",_xlpm.p))),"DB-2", IF(LEFT(_xlpm.p,3)="OC-","OC", LEFT(_xlpm.p,_xlfn.XMATCH(TRUE,ISNUMBER(--MID(_xlpm.p,_xlfn.SEQUENCE(LEN(_xlpm.p)),1)))-1) ) ), _xlpm.p ), _xlpm.base,_xlfn.XLOOKUP(_xlpm.code,'Product Code'!A:A,'Product Code'!C:C,""), IF(RIGHT(_xlpm.p,3)="-PO",_xlpm.base&" - Pull-Out",_xlpm.base) )} -> Scribe molding | I88: {=_xlfn.LET( _xlpm.p,E88, _xlpm.code,IFERROR( IF(AND(LEFT(_xlpm.p,2)="DB",ISNUMBER(SEARCH("-2",_xlpm.p))),"DB-2", IF(LEFT(_xlpm.p,3)="OC-","OC", LEFT(_xlpm.p,_xlfn.XMATCH(TRUE,ISNUMBER(--MID(_xlpm.p,_xlfn.SEQUENCE(LEN(_xlpm.p)),1)))-1) ) ), _xlpm.p ), _xlpm.productType,_xlfn.XLOOKUP(_xlpm.code,'Product Code'!A:A,'Product Code'!D:D,""), IF(OR(RIGHT(_xlpm.p,5)="-Door",RIGHT(_xlpm.p,6)="-DOORS"),_xlpm.productType&" - Door",_xlpm.productType) )} -> x | K88: 96 | L88: 1.5 | M88: =3/8 -> 0.375 | N88: N/A | O88: N/A
A89: F9-SM1.5X120 | B89: 79 | C89: =B89*0.3 -> 23.7 | E89: =_xlfn.TEXTAFTER(A89,"-") -> SM1.5X120 | F89: {=_xlfn.LET( _xlpm.p,E89, _xlpm.code,IFERROR( IF(AND(LEFT(_xlpm.p,2)="DB",ISNUMBER(SEARCH("-2",_xlpm.p))),"DB-2", IF(LEFT(_xlpm.p,3)="OC-","OC", LEFT(_xlpm.p,_xlfn.XMATCH(TRUE,ISNUMBER(--MID(_xlpm.p,_xlfn.SEQUENCE(LEN(_xlpm.p)),1)))-1) ) ), _xlpm.p ), _xlfn.XLOOKUP(_xlpm.code,'Product Code'!A:A,'Product Code'!B:B,"") )} -> Moldings | G89: {=_xlfn.LET( _xlpm.p,E89, _xlpm.code,IFERROR( IF(AND(LEFT(_xlpm.p,2)="DB",ISNUMBER(SEARCH("-2",_xlpm.p))),"DB-2", IF(LEFT(_xlpm.p,3)="OC-","OC", LEFT(_xlpm.p,_xlfn.XMATCH(TRUE,ISNUMBER(--MID(_xlpm.p,_xlfn.SEQUENCE(LEN(_xlpm.p)),1)))-1) ) ), _xlpm.p ), _xlpm.base,_xlfn.XLOOKUP(_xlpm.code,'Product Code'!A:A,'Product Code'!C:C,""), IF(RIGHT(_xlpm.p,3)="-PO",_xlpm.base&" - Pull-Out",_xlpm.base) )} -> Scribe molding | I89: {=_xlfn.LET( _xlpm.p,E89, _xlpm.code,IFERROR( IF(AND(LEFT(_xlpm.p,2)="DB",ISNUMBER(SEARCH("-2",_xlpm.p))),"DB-2", IF(LEFT(_xlpm.p,3)="OC-","OC", LEFT(_xlpm.p,_xlfn.XMATCH(TRUE,ISNUMBER(--MID(_xlpm.p,_xlfn.SEQUENCE(LEN(_xlpm.p)),1)))-1) ) ), _xlpm.p ), _xlpm.productType,_xlfn.XLOOKUP(_xlpm.code,'Product Code'!A:A,'Product Code'!D:D,""), IF(OR(RIGHT(_xlpm.p,5)="-Door",RIGHT(_xlpm.p,6)="-DOORS"),_xlpm.productType&" - Door",_xlpm.productType) )} -> x | K89: 120 | L89: 1.5 | M89: =3/8 -> 0.375 | N89: =IF(ISNUMBER(SEARCH("Cabinet",F89))=FALSE,"N/A",IF(K89>=24,2,1)) -> N/A | O89: =IF(ISNUMBER(SEARCH("Cabinet",F89))=FALSE,"N/A", IF(ISNUMBER(SEARCH("DB",E89)), IF(ISNUMBER(SEARCH("-2",E89)),2,3), IF(ISNUMBER(SEARCH("-PO",E89)),1, IF(LEFT(E89,1)="B",1,0) ) ) ) -> N/A
A90: F9-DWR | B90: 168 | C90: =B90*0.3 -> 50.4 | E90: =_xlfn.TEXTAFTER(A90,"-") -> DWR | F90: {=_xlfn.LET( _xlpm.p,E90, _xlpm.code,IFERROR( IF(AND(LEFT(_xlpm.p,2)="DB",ISNUMBER(SEARCH("-2",_xlpm.p))),"DB-2", IF(LEFT(_xlpm.p,3)="OC-","OC", LEFT(_xlpm.p,_xlfn.XMATCH(TRUE,ISNUMBER(--MID(_xlpm.p,_xlfn.SEQUENCE(LEN(_xlpm.p)),1)))-1) ) ), _xlpm.p ), _xlfn.XLOOKUP(_xlpm.code,'Product Code'!A:A,'Product Code'!B:B,"") )} -> Panel | G90: {=_xlfn.LET( _xlpm.p,E90, _xlpm.code,IFERROR( IF(AND(LEFT(_xlpm.p,2)="DB",ISNUMBER(SEARCH("-2",_xlpm.p))),"DB-2", IF(LEFT(_xlpm.p,3)="OC-","OC", LEFT(_xlpm.p,_xlfn.XMATCH(TRUE,ISNUMBER(--MID(_xlpm.p,_xlfn.SEQUENCE(LEN(_xlpm.p)),1)))-1) ) ), _xlpm.p ), _xlpm.base,_xlfn.XLOOKUP(_xlpm.code,'Product Code'!A:A,'Product Code'!C:C,""), IF(RIGHT(_xlpm.p,3)="-PO",_xlpm.base&" - Pull-Out",_xlpm.base) )} -> Dishwasher Return Panel | H90: N/A | I90: {=_xlfn.LET( _xlpm.p,E90, _xlpm.code,IFERROR( IF(AND(LEFT(_xlpm.p,2)="DB",ISNUMBER(SEARCH("-2",_xlpm.p))),"DB-2", IF(LEFT(_xlpm.p,3)="OC-","OC", LEFT(_xlpm.p,_xlfn.XMATCH(TRUE,ISNUMBER(--MID(_xlpm.p,_xlfn.SEQUENCE(LEN(_xlpm.p)),1)))-1) ) ), _xlpm.p ), _xlpm.productType,_xlfn.XLOOKUP(_xlpm.code,'Product Code'!A:A,'Product Code'!D:D,""), IF(OR(RIGHT(_xlpm.p,5)="-Door",RIGHT(_xlpm.p,6)="-DOORS"),_xlpm.productType&" - Door",_xlpm.productType) )} -> x | J90: x | K90: 3 | L90: 34.5 | M90: 24 | N90: =IF(ISNUMBER(SEARCH("Cabinet",F90))=FALSE,"N/A",IF(K90>=24,2,1)) -> N/A | O90: =IF(ISNUMBER(SEARCH("Cabinet",F90))=FALSE,"N/A", IF(ISNUMBER(SEARCH("DB",E90)), IF(ISNUMBER(SEARCH("-2",E90)),2,3), IF(ISNUMBER(SEARCH("-PO",E90)),1, IF(LEFT(E90,1)="B",1,0) ) ) ) -> N/A
A91: F9-RRP103.527 3/4 | B91: 482 | C91: =B91*0.3 -> 144.6 | E91: =_xlfn.TEXTAFTER(A91,"-") -> RRP103.527 3/4 | F91: {=_xlfn.LET( _xlpm.p,E91, _xlpm.code,IFERROR( IF(AND(LEFT(_xlpm.p,2)="DB",ISNUMBER(SEARCH("-2",_xlpm.p))),"DB-2", IF(LEFT(_xlpm.p,3)="OC-","OC", LEFT(_xlpm.p,_xlfn.XMATCH(TRUE,ISNUMBER(--MID(_xlpm.p,_xlfn.SEQUENCE(LEN(_xlpm.p)),1)))-1) ) ), _xlpm.p ), _xlfn.XLOOKUP(_xlpm.code,'Product Code'!A:A,'Product Code'!B:B,"") )} -> Panel | G91: {=_xlfn.LET( _xlpm.p,E91, _xlpm.code,IFERROR( IF(AND(LEFT(_xlpm.p,2)="DB",ISNUMBER(SEARCH("-2",_xlpm.p))),"DB-2", IF(LEFT(_xlpm.p,3)="OC-","OC", LEFT(_xlpm.p,_xlfn.XMATCH(TRUE,ISNUMBER(--MID(_xlpm.p,_xlfn.SEQUENCE(LEN(_xlpm.p)),1)))-1) ) ), _xlpm.p ), _xlpm.base,_xlfn.XLOOKUP(_xlpm.code,'Product Code'!A:A,'Product Code'!C:C,""), IF(RIGHT(_xlpm.p,3)="-PO",_xlpm.base&" - Pull-Out",_xlpm.base) )} -> Refrigerator Return Panel | H91: N/A | I91: {=_xlfn.LET( _xlpm.p,E91, _xlpm.code,IFERROR( IF(AND(LEFT(_xlpm.p,2)="DB",ISNUMBER(SEARCH("-2",_xlpm.p))),"DB-2", IF(LEFT(_xlpm.p,3)="OC-","OC", LEFT(_xlpm.p,_xlfn.XMATCH(TRUE,ISNUMBER(--MID(_xlpm.p,_xlfn.SEQUENCE(LEN(_xlpm.p)),1)))-1) ) ), _xlpm.p ), _xlpm.productType,_xlfn.XLOOKUP(_xlpm.code,'Product Code'!A:A,'Product Code'!D:D,""), IF(OR(RIGHT(_xlpm.p,5)="-Door",RIGHT(_xlpm.p,6)="-DOORS"),_xlpm.productType&" - Door",_xlpm.productType) )} -> x | J91: x | K91: =3/4 -> 0.75 | L91: 103.5 | M91: 27 | N91: =IF(ISNUMBER(SEARCH("Cabinet",F91))=FALSE,"N/A",IF(K91>=24,2,1)) -> N/A | O91: =IF(ISNUMBER(SEARCH("Cabinet",F91))=FALSE,"N/A", IF(ISNUMBER(SEARCH("DB",E91)), IF(ISNUMBER(SEARCH("-2",E91)),2,3), IF(ISNUMBER(SEARCH("-PO",E91)),1, IF(LEFT(E91,1)="B",1,0) ) ) ) -> N/A
A92: F9-RRP9627 7/8 | B92: 335 | C92: =B92*0.3 -> 100.5 | E92: =_xlfn.TEXTAFTER(A92,"-") -> RRP9627 7/8 | F92: {=_xlfn.LET( _xlpm.p,E92, _xlpm.code,IFERROR( IF(AND(LEFT(_xlpm.p,2)="DB",ISNUMBER(SEARCH("-2",_xlpm.p))),"DB-2", IF(LEFT(_xlpm.p,3)="OC-","OC", LEFT(_xlpm.p,_xlfn.XMATCH(TRUE,ISNUMBER(--MID(_xlpm.p,_xlfn.SEQUENCE(LEN(_xlpm.p)),1)))-1) ) ), _xlpm.p ), _xlfn.XLOOKUP(_xlpm.code,'Product Code'!A:A,'Product Code'!B:B,"") )} -> Panel | G92: {=_xlfn.LET( _xlpm.p,E92, _xlpm.code,IFERROR( IF(AND(LEFT(_xlpm.p,2)="DB",ISNUMBER(SEARCH("-2",_xlpm.p))),"DB-2", IF(LEFT(_xlpm.p,3)="OC-","OC", LEFT(_xlpm.p,_xlfn.XMATCH(TRUE,ISNUMBER(--MID(_xlpm.p,_xlfn.SEQUENCE(LEN(_xlpm.p)),1)))-1) ) ), _xlpm.p ), _xlpm.base,_xlfn.XLOOKUP(_xlpm.code,'Product Code'!A:A,'Product Code'!C:C,""), IF(RIGHT(_xlpm.p,3)="-PO",_xlpm.base&" - Pull-Out",_xlpm.base) )} -> Refrigerator Return Panel | H92: N/A | I92: {=_xlfn.LET( _xlpm.p,E92, _xlpm.code,IFERROR( IF(AND(LEFT(_xlpm.p,2)="DB",ISNUMBER(SEARCH("-2",_xlpm.p))),"DB-2", IF(LEFT(_xlpm.p,3)="OC-","OC", LEFT(_xlpm.p,_xlfn.XMATCH(TRUE,ISNUMBER(--MID(_xlpm.p,_xlfn.SEQUENCE(LEN(_xlpm.p)),1)))-1) ) ), _xlpm.p ), _xlpm.productType,_xlfn.XLOOKUP(_xlpm.code,'Product Code'!A:A,'Product Code'!D:D,""), IF(OR(RIGHT(_xlpm.p,5)="-Door",RIGHT(_xlpm.p,6)="-DOORS"),_xlpm.productType&" - Door",_xlpm.productType) )} -> x | J92: x | K92: =7/8 -> 0.875 | L92: 96 | M92: 27 | N92: N/A | O92: N/A
A93: F9-TK8 | B93: 47 | C93: =B93*0.3 -> 14.1 | D93: =C93*1.36 -> 19.176 | E93: =_xlfn.TEXTAFTER(A93,"-") -> TK8 | F93: {=_xlfn.LET( _xlpm.p,E93, _xlpm.code,IFERROR( IF(AND(LEFT(_xlpm.p,2)="DB",ISNUMBER(SEARCH("-2",_xlpm.p))),"DB-2", IF(LEFT(_xlpm.p,3)="OC-","OC", LEFT(_xlpm.p,_xlfn.XMATCH(TRUE,ISNUMBER(--MID(_xlpm.p,_xlfn.SEQUENCE(LEN(_xlpm.p)),1)))-1) ) ), _xlpm.p ), _xlfn.XLOOKUP(_xlpm.code,'Product Code'!A:A,'Product Code'!B:B,"") )} -> Toe Kick | G93: {=_xlfn.LET( _xlpm.p,E93, _xlpm.code,IFERROR( IF(AND(LEFT(_xlpm.p,2)="DB",ISNUMBER(SEARCH("-2",_xlpm.p))),"DB-2", IF(LEFT(_xlpm.p,3)="OC-","OC", LEFT(_xlpm.p,_xlfn.XMATCH(TRUE,ISNUMBER(--MID(_xlpm.p,_xlfn.SEQUENCE(LEN(_xlpm.p)),1)))-1) ) ), _xlpm.p ), _xlpm.base,_xlfn.XLOOKUP(_xlpm.code,'Product Code'!A:A,'Product Code'!C:C,""), IF(RIGHT(_xlpm.p,3)="-PO",_xlpm.base&" - Pull-Out",_xlpm.base) )} -> 0 | I93: {=_xlfn.LET( _xlpm.p,E93, _xlpm.code,IFERROR( IF(AND(LEFT(_xlpm.p,2)="DB",ISNUMBER(SEARCH("-2",_xlpm.p))),"DB-2", IF(LEFT(_xlpm.p,3)="OC-","OC", LEFT(_xlpm.p,_xlfn.XMATCH(TRUE,ISNUMBER(--MID(_xlpm.p,_xlfn.SEQUENCE(LEN(_xlpm.p)),1)))-1) ) ), _xlpm.p ), _xlpm.productType,_xlfn.XLOOKUP(_xlpm.code,'Product Code'!A:A,'Product Code'!D:D,""), IF(OR(RIGHT(_xlpm.p,5)="-Door",RIGHT(_xlpm.p,6)="-DOORS"),_xlpm.productType&" - Door",_xlpm.productType) )} -> x | J93: x | K93: 4.5 | L93: 96 | M93: =1/4 -> 0.25 | N93: =IF(ISNUMBER(SEARCH("Cabinet",F93))=FALSE,"N/A",IF(K93>=24,2,1)) -> N/A | O93: =IF(ISNUMBER(SEARCH("Cabinet",F93))=FALSE,"N/A", IF(ISNUMBER(SEARCH("DB",E93)), IF(ISNUMBER(SEARCH("-2",E93)),2,3), IF(ISNUMBER(SEARCH("-PO",E93)),1, IF(LEFT(E93,1)="B",1,0) ) ) ) -> N/A
A94: F9-OC33X103.5 | B94: 3388 | C94: =B94*0.3 -> 1016.4 | E94: =_xlfn.TEXTAFTER(A94,"-") -> OC33X103.5 | F94: {=_xlfn.LET( _xlpm.p,E94, _xlpm.code,IFERROR( IF(AND(LEFT(_xlpm.p,2)="DB",ISNUMBER(SEARCH("-2",_xlpm.p))),"DB-2", IF(LEFT(_xlpm.p,3)="OC-","OC", LEFT(_xlpm.p,_xlfn.XMATCH(TRUE,ISNUMBER(--MID(_xlpm.p,_xlfn.SEQUENCE(LEN(_xlpm.p)),1)))-1) ) ), _xlpm.p ), _xlfn.XLOOKUP(_xlpm.code,'Product Code'!A:A,'Product Code'!B:B,"") )} -> Utility Cabinet | G94: {=_xlfn.LET( _xlpm.p,E94, _xlpm.code,IFERROR( IF(AND(LEFT(_xlpm.p,2)="DB",ISNUMBER(SEARCH("-2",_xlpm.p))),"DB-2", IF(LEFT(_xlpm.p,3)="OC-","OC", LEFT(_xlpm.p,_xlfn.XMATCH(TRUE,ISNUMBER(--MID(_xlpm.p,_xlfn.SEQUENCE(LEN(_xlpm.p)),1)))-1) ) ), _xlpm.p ), _xlpm.base,_xlfn.XLOOKUP(_xlpm.code,'Product Code'!A:A,'Product Code'!C:C,""), IF(RIGHT(_xlpm.p,3)="-PO",_xlpm.base&" - Pull-Out",_xlpm.base) )} -> Oven | H94: Cabinet | I94: {=_xlfn.LET( _xlpm.p,E94, _xlpm.code,IFERROR( IF(AND(LEFT(_xlpm.p,2)="DB",ISNUMBER(SEARCH("-2",_xlpm.p))),"DB-2", IF(LEFT(_xlpm.p,3)="OC-","OC", LEFT(_xlpm.p,_xlfn.XMATCH(TRUE,ISNUMBER(--MID(_xlpm.p,_xlfn.SEQUENCE(LEN(_xlpm.p)),1)))-1) ) ), _xlpm.p ), _xlpm.productType,_xlfn.XLOOKUP(_xlpm.code,'Product Code'!A:A,'Product Code'!D:D,""), IF(OR(RIGHT(_xlpm.p,5)="-Door",RIGHT(_xlpm.p,6)="-DOORS"),_xlpm.productType&" - Door",_xlpm.productType) )} -> x | K94: 33 | L94: 103.5 | M94: 27 | N94: =IF(ISNUMBER(SEARCH("Cabinet",F94))=FALSE,"N/A",IF(K94>=24,2,1)) -> 2 | O94: =IF(ISNUMBER(SEARCH("Cabinet",F94))=FALSE,"N/A", IF(ISNUMBER(SEARCH("DB",E94)), IF(ISNUMBER(SEARCH("-2",E94)),2,3), IF(ISNUMBER(SEARCH("-PO",E94)),1, IF(LEFT(E94,1)="B",1,0) ) ) ) -> 0
A95: F9-OC-DB30 DRAWER | B95: 447 | C95: =B95*0.3 -> 134.1 | E95: =_xlfn.TEXTAFTER(A95,"-") -> OC-DB30 DRAWER | F95: {=_xlfn.LET( _xlpm.p,E95, _xlpm.code,IFERROR( IF(AND(LEFT(_xlpm.p,2)="DB",ISNUMBER(SEARCH("-2",_xlpm.p))),"DB-2", IF(LEFT(_xlpm.p,3)="OC-","OC", LEFT(_xlpm.p,_xlfn.XMATCH(TRUE,ISNUMBER(--MID(_xlpm.p,_xlfn.SEQUENCE(LEN(_xlpm.p)),1)))-1) ) ), _xlpm.p ), _xlfn.XLOOKUP(_xlpm.code,'Product Code'!A:A,'Product Code'!B:B,"") )} -> Utility Cabinet | G95: {=_xlfn.LET( _xlpm.p,E95, _xlpm.code,IFERROR( IF(AND(LEFT(_xlpm.p,2)="DB",ISNUMBER(SEARCH("-2",_xlpm.p))),"DB-2", IF(LEFT(_xlpm.p,3)="OC-","OC", LEFT(_xlpm.p,_xlfn.XMATCH(TRUE,ISNUMBER(--MID(_xlpm.p,_xlfn.SEQUENCE(LEN(_xlpm.p)),1)))-1) ) ), _xlpm.p ), _xlpm.base,_xlfn.XLOOKUP(_xlpm.code,'Product Code'!A:A,'Product Code'!C:C,""), IF(RIGHT(_xlpm.p,3)="-PO",_xlpm.base&" - Pull-Out",_xlpm.base) )} -> Oven | H95: Drawer | I95: {=_xlfn.LET( _xlpm.p,E95, _xlpm.code,IFERROR( IF(AND(LEFT(_xlpm.p,2)="DB",ISNUMBER(SEARCH("-2",_xlpm.p))),"DB-2", IF(LEFT(_xlpm.p,3)="OC-","OC", LEFT(_xlpm.p,_xlfn.XMATCH(TRUE,ISNUMBER(--MID(_xlpm.p,_xlfn.SEQUENCE(LEN(_xlpm.p)),1)))-1) ) ), _xlpm.p ), _xlpm.productType,_xlfn.XLOOKUP(_xlpm.code,'Product Code'!A:A,'Product Code'!D:D,""), IF(OR(RIGHT(_xlpm.p,5)="-Door",RIGHT(_xlpm.p,6)="-DOORS"),_xlpm.productType&" - Door",_xlpm.productType) )} -> x | K95: 30 | N95: =IF(ISNUMBER(SEARCH("Cabinet",F95))=FALSE,"N/A",IF(K95>=24,2,1)) -> 2 | O95: =IF(ISNUMBER(SEARCH("Cabinet",F95))=FALSE,"N/A", IF(ISNUMBER(SEARCH("DB",E95)), IF(ISNUMBER(SEARCH("-2",E95)),2,3), IF(ISNUMBER(SEARCH("-PO",E95)),1, IF(LEFT(E95,1)="B",1,0) ) ) ) -> 3
A96: F9-WP129327 | B96: 1705 | C96: =B96*0.3 -> 511.5 | E96: =_xlfn.TEXTAFTER(A96,"-") -> WP129327 | F96: {=_xlfn.LET( _xlpm.p,E96, _xlpm.code,IFERROR( IF(AND(LEFT(_xlpm.p,2)="DB",ISNUMBER(SEARCH("-2",_xlpm.p))),"DB-2", IF(LEFT(_xlpm.p,3)="OC-","OC", LEFT(_xlpm.p,_xlfn.XMATCH(TRUE,ISNUMBER(--MID(_xlpm.p,_xlfn.SEQUENCE(LEN(_xlpm.p)),1)))-1) ) ), _xlpm.p ), _xlfn.XLOOKUP(_xlpm.code,'Product Code'!A:A,'Product Code'!B:B,"") )} -> Utility Cabinet | G96: {=_xlfn.LET( _xlpm.p,E96, _xlpm.code,IFERROR( IF(AND(LEFT(_xlpm.p,2)="DB",ISNUMBER(SEARCH("-2",_xlpm.p))),"DB-2", IF(LEFT(_xlpm.p,3)="OC-","OC", LEFT(_xlpm.p,_xlfn.XMATCH(TRUE,ISNUMBER(--MID(_xlpm.p,_xlfn.SEQUENCE(LEN(_xlpm.p)),1)))-1) ) ), _xlpm.p ), _xlpm.base,_xlfn.XLOOKUP(_xlpm.code,'Product Code'!A:A,'Product Code'!C:C,""), IF(RIGHT(_xlpm.p,3)="-PO",_xlpm.base&" - Pull-Out",_xlpm.base) )} -> Pantry | I96: {=_xlfn.LET( _xlpm.p,E96, _xlpm.code,IFERROR( IF(AND(LEFT(_xlpm.p,2)="DB",ISNUMBER(SEARCH("-2",_xlpm.p))),"DB-2", IF(LEFT(_xlpm.p,3)="OC-","OC", LEFT(_xlpm.p,_xlfn.XMATCH(TRUE,ISNUMBER(--MID(_xlpm.p,_xlfn.SEQUENCE(LEN(_xlpm.p)),1)))-1) ) ), _xlpm.p ), _xlpm.productType,_xlfn.XLOOKUP(_xlpm.code,'Product Code'!A:A,'Product Code'!D:D,""), IF(OR(RIGHT(_xlpm.p,5)="-Door",RIGHT(_xlpm.p,6)="-DOORS"),_xlpm.productType&" - Door",_xlpm.productType) )} -> x | J96: x | K96: 12 | L96: 93 | M96: 27 | N96: N/A | O96: N/A
A97: F9-WP159327 | B97: 1841 | C97: =B97*0.3 -> 552.3 | E97: =_xlfn.TEXTAFTER(A97,"-") -> WP159327 | F97: {=_xlfn.LET( _xlpm.p,E97, _xlpm.code,IFERROR( IF(AND(LEFT(_xlpm.p,2)="DB",ISNUMBER(SEARCH("-2",_xlpm.p))),"DB-2", IF(LEFT(_xlpm.p,3)="OC-","OC", LEFT(_xlpm.p,_xlfn.XMATCH(TRUE,ISNUMBER(--MID(_xlpm.p,_xlfn.SEQUENCE(LEN(_xlpm.p)),1)))-1) ) ), _xlpm.p ), _xlfn.XLOOKUP(_xlpm.code,'Product Code'!A:A,'Product Code'!B:B,"") )} -> Utility Cabinet | G97: {=_xlfn.LET( _xlpm.p,E97, _xlpm.code,IFERROR( IF(AND(LEFT(_xlpm.p,2)="DB",ISNUMBER(SEARCH("-2",_xlpm.p))),"DB-2", IF(LEFT(_xlpm.p,3)="OC-","OC", LEFT(_xlpm.p,_xlfn.XMATCH(TRUE,ISNUMBER(--MID(_xlpm.p,_xlfn.SEQUENCE(LEN(_xlpm.p)),1)))-1) ) ), _xlpm.p ), _xlpm.base,_xlfn.XLOOKUP(_xlpm.code,'Product Code'!A:A,'Product Code'!C:C,""), IF(RIGHT(_xlpm.p,3)="-PO",_xlpm.base&" - Pull-Out",_xlpm.base) )} -> Pantry | I97: {=_xlfn.LET( _xlpm.p,E97, _xlpm.code,IFERROR( IF(AND(LEFT(_xlpm.p,2)="DB",ISNUMBER(SEARCH("-2",_xlpm.p))),"DB-2", IF(LEFT(_xlpm.p,3)="OC-","OC", LEFT(_xlpm.p,_xlfn.XMATCH(TRUE,ISNUMBER(--MID(_xlpm.p,_xlfn.SEQUENCE(LEN(_xlpm.p)),1)))-1) ) ), _xlpm.p ), _xlpm.productType,_xlfn.XLOOKUP(_xlpm.code,'Product Code'!A:A,'Product Code'!D:D,""), IF(OR(RIGHT(_xlpm.p,5)="-Door",RIGHT(_xlpm.p,6)="-DOORS"),_xlpm.productType&" - Door",_xlpm.productType) )} -> x | J97: x | K97: 15 | L97: 93 | M97: 27 | N97: =IF(ISNUMBER(SEARCH("Cabinet",F97))=FALSE,"N/A",IF(K97>=24,2,1)) -> 1 | O97: =IF(ISNUMBER(SEARCH("Cabinet",F97))=FALSE,"N/A", IF(ISNUMBER(SEARCH("DB",E97)), IF(ISNUMBER(SEARCH("-2",E97)),2,3), IF(ISNUMBER(SEARCH("-PO",E97)),1, IF(LEFT(E97,1)="B",1,0) ) ) ) -> 0
A98: F9-WP188427 | B98: 1356 | C98: =B98*0.3 -> 406.8 | E98: =_xlfn.TEXTAFTER(A98,"-") -> WP188427 | F98: {=_xlfn.LET( _xlpm.p,E98, _xlpm.code,IFERROR( IF(AND(LEFT(_xlpm.p,2)="DB",ISNUMBER(SEARCH("-2",_xlpm.p))),"DB-2", IF(LEFT(_xlpm.p,3)="OC-","OC", LEFT(_xlpm.p,_xlfn.XMATCH(TRUE,ISNUMBER(--MID(_xlpm.p,_xlfn.SEQUENCE(LEN(_xlpm.p)),1)))-1) ) ), _xlpm.p ), _xlfn.XLOOKUP(_xlpm.code,'Product Code'!A:A,'Product Code'!B:B,"") )} -> Utility Cabinet | G98: {=_xlfn.LET( _xlpm.p,E98, _xlpm.code,IFERROR( IF(AND(LEFT(_xlpm.p,2)="DB",ISNUMBER(SEARCH("-2",_xlpm.p))),"DB-2", IF(LEFT(_xlpm.p,3)="OC-","OC", LEFT(_xlpm.p,_xlfn.XMATCH(TRUE,ISNUMBER(--MID(_xlpm.p,_xlfn.SEQUENCE(LEN(_xlpm.p)),1)))-1) ) ), _xlpm.p ), _xlpm.base,_xlfn.XLOOKUP(_xlpm.code,'Product Code'!A:A,'Product Code'!C:C,""), IF(RIGHT(_xlpm.p,3)="-PO",_xlpm.base&" - Pull-Out",_xlpm.base) )} -> Pantry | I98: {=_xlfn.LET( _xlpm.p,E98, _xlpm.code,IFERROR( IF(AND(LEFT(_xlpm.p,2)="DB",ISNUMBER(SEARCH("-2",_xlpm.p))),"DB-2", IF(LEFT(_xlpm.p,3)="OC-","OC", LEFT(_xlpm.p,_xlfn.XMATCH(TRUE,ISNUMBER(--MID(_xlpm.p,_xlfn.SEQUENCE(LEN(_xlpm.p)),1)))-1) ) ), _xlpm.p ), _xlpm.productType,_xlfn.XLOOKUP(_xlpm.code,'Product Code'!A:A,'Product Code'!D:D,""), IF(OR(RIGHT(_xlpm.p,5)="-Door",RIGHT(_xlpm.p,6)="-DOORS"),_xlpm.productType&" - Door",_xlpm.productType) )} -> x | J98: x | K98: 18 | L98: 84 | M98: 27 | N98: =IF(ISNUMBER(SEARCH("Cabinet",F98))=FALSE,"N/A",IF(K98>=24,2,1)) -> 1 | O98: =IF(ISNUMBER(SEARCH("Cabinet",F98))=FALSE,"N/A", IF(ISNUMBER(SEARCH("DB",E98)), IF(ISNUMBER(SEARCH("-2",E98)),2,3), IF(ISNUMBER(SEARCH("-PO",E98)),1, IF(LEFT(E98,1)="B",1,0) ) ) ) -> 0
A99: F9-WP189027 | B99: 1506 | C99: =B99*0.3 -> 451.8 | E99: =_xlfn.TEXTAFTER(A99,"-") -> WP189027 | F99: {=_xlfn.LET( _xlpm.p,E99, _xlpm.code,IFERROR( IF(AND(LEFT(_xlpm.p,2)="DB",ISNUMBER(SEARCH("-2",_xlpm.p))),"DB-2", IF(LEFT(_xlpm.p,3)="OC-","OC", LEFT(_xlpm.p,_xlfn.XMATCH(TRUE,ISNUMBER(--MID(_xlpm.p,_xlfn.SEQUENCE(LEN(_xlpm.p)),1)))-1) ) ), _xlpm.p ), _xlfn.XLOOKUP(_xlpm.code,'Product Code'!A:A,'Product Code'!B:B,"") )} -> Utility Cabinet | G99: {=_xlfn.LET( _xlpm.p,E99, _xlpm.code,IFERROR( IF(AND(LEFT(_xlpm.p,2)="DB",ISNUMBER(SEARCH("-2",_xlpm.p))),"DB-2", IF(LEFT(_xlpm.p,3)="OC-","OC", LEFT(_xlpm.p,_xlfn.XMATCH(TRUE,ISNUMBER(--MID(_xlpm.p,_xlfn.SEQUENCE(LEN(_xlpm.p)),1)))-1) ) ), _xlpm.p ), _xlpm.base,_xlfn.XLOOKUP(_xlpm.code,'Product Code'!A:A,'Product Code'!C:C,""), IF(RIGHT(_xlpm.p,3)="-PO",_xlpm.base&" - Pull-Out",_xlpm.base) )} -> Pantry | I99: {=_xlfn.LET( _xlpm.p,E99, _xlpm.code,IFERROR( IF(AND(LEFT(_xlpm.p,2)="DB",ISNUMBER(SEARCH("-2",_xlpm.p))),"DB-2", IF(LEFT(_xlpm.p,3)="OC-","OC", LEFT(_xlpm.p,_xlfn.XMATCH(TRUE,ISNUMBER(--MID(_xlpm.p,_xlfn.SEQUENCE(LEN(_xlpm.p)),1)))-1) ) ), _xlpm.p ), _xlpm.productType,_xlfn.XLOOKUP(_xlpm.code,'Product Code'!A:A,'Product Code'!D:D,""), IF(OR(RIGHT(_xlpm.p,5)="-Door",RIGHT(_xlpm.p,6)="-DOORS"),_xlpm.productType&" - Door",_xlpm.productType) )} -> x | J99: x | K99: 18 | L99: 90 | M99: 27 | N99: =IF(ISNUMBER(SEARCH("Cabinet",F99))=FALSE,"N/A",IF(K99>=24,2,1)) -> 1 | O99: =IF(ISNUMBER(SEARCH("Cabinet",F99))=FALSE,"N/A", IF(ISNUMBER(SEARCH("DB",E99)), IF(ISNUMBER(SEARCH("-2",E99)),2,3), IF(ISNUMBER(SEARCH("-PO",E99)),1, IF(LEFT(E99,1)="B",1,0) ) ) ) -> 0
A100: F9-WP189327 | B100: 1970 | C100: =B100*0.3 -> 591 | E100: =_xlfn.TEXTAFTER(A100,"-") -> WP189327 | F100: {=_xlfn.LET( _xlpm.p,E100, _xlpm.code,IFERROR( IF(AND(LEFT(_xlpm.p,2)="DB",ISNUMBER(SEARCH("-2",_xlpm.p))),"DB-2", IF(LEFT(_xlpm.p,3)="OC-","OC", LEFT(_xlpm.p,_xlfn.XMATCH(TRUE,ISNUMBER(--MID(_xlpm.p,_xlfn.SEQUENCE(LEN(_xlpm.p)),1)))-1) ) ), _xlpm.p ), _xlfn.XLOOKUP(_xlpm.code,'Product Code'!A:A,'Product Code'!B:B,"") )} -> Utility Cabinet | G100: {=_xlfn.LET( _xlpm.p,E100, _xlpm.code,IFERROR( IF(AND(LEFT(_xlpm.p,2)="DB",ISNUMBER(SEARCH("-2",_xlpm.p))),"DB-2", IF(LEFT(_xlpm.p,3)="OC-","OC", LEFT(_xlpm.p,_xlfn.XMATCH(TRUE,ISNUMBER(--MID(_xlpm.p,_xlfn.SEQUENCE(LEN(_xlpm.p)),1)))-1) ) ), _xlpm.p ), _xlpm.base,_xlfn.XLOOKUP(_xlpm.code,'Product Code'!A:A,'Product Code'!C:C,""), IF(RIGHT(_xlpm.p,3)="-PO",_xlpm.base&" - Pull-Out",_xlpm.base) )} -> Pantry | I100: {=_xlfn.LET( _xlpm.p,E100, _xlpm.code,IFERROR( IF(AND(LEFT(_xlpm.p,2)="DB",ISNUMBER(SEARCH("-2",_xlpm.p))),"DB-2", IF(LEFT(_xlpm.p,3)="OC-","OC", LEFT(_xlpm.p,_xlfn.XMATCH(TRUE,ISNUMBER(--MID(_xlpm.p,_xlfn.SEQUENCE(LEN(_xlpm.p)),1)))-1) ) ), _xlpm.p ), _xlpm.productType,_xlfn.XLOOKUP(_xlpm.code,'Product Code'!A:A,'Product Code'!D:D,""), IF(OR(RIGHT(_xlpm.p,5)="-Door",RIGHT(_xlpm.p,6)="-DOORS"),_xlpm.productType&" - Door",_xlpm.productType) )} -> x | J100: x | K100: 18 | L100: 93 | M100: 27 | N100: N/A | O100: N/A
...

Sheet Product Code
A1: Code | B1: Product Type | C1: Product Sub-type | D1: Suis-je certain | E1: Question
A2: B | B2: Base Cabinet | C2: Standard | D2: x
A3: BBC | B3: Base Cabinet | C3: Blind Corner | D3: x
A4: BDD | B4: Dummy Door | C4: Base End | D4: x
A5: BEC | B5: Base End Corner | D5: -
A6: BES | B6: Base End Shelf | D6: -
A7: BM | B7: Moldings | C7: Base molding | D7: x
A8: BMC | B8: Base Microwave Cabinet | D8: -
A9: CBD | B9: Base Cabinet | C9: Corner (45deg) | D9: x
A10: CM | B10: Fillers | C10: Filler , mais quel type? | D10: -
A11: CSB | B11: Corner Sink Base | D11: -
A12: D | B12: Drawer Front replacement part? | D12: -
A13: DB | B13: Base Cabinet | C13: Drawer (3 drawers) | D13: x
A14: DB-2 | B14: Base Cabinet | C14: Drawer (2 drawers) | D14: x
A15: DBP | B15: Drawer Base Panel ? | D15: -
A16: DWR | B16: Panel | C16: Dishwasher Return Panel | D16: x
A17: F | B17: Door Front replacement part | D17: -
A18: FB | B18: Bathroom - Base Cabinet | D18: - | E18: utilisé dans la soumission powder room
A19: FSB | B19: Base Cabinet | C19: Farmhouse Sink | D19: x
A20: Garbage Bin | B20: Accessories | C20: Plastic Garbage Bin | E20: 7 gallon ?
A21: IBP | B21: Island Back Panel | D21: -
A22: ISP | B22: Island Skin Panel probablement | D22: -
A23: LS | B23: Base Cabinet | C23: Corner (90deg) | D23: x | E23: Does it contains a lady susan ?
A24: OC | B24: Utility Cabinet | C24: Oven | D24: x
A25: OCM | B25: Moldings | C25: Outside Corner Molding | D25: x
A26: PO | B26: Pull-Out accessory | D26: -
A27: ROD | B27: cote dessous tiroir | D27: -
A28: RRP | B28: Panel | C28: Refrigerator Return Panel | D28: x
A29: SB | B29: Base Cabinet | C29: Sink | D29: x | E29: Does it contains Tilt-Out Drawer With Tray?
A30: SM | B30: Moldings | C30: Scribe molding | D30: x
A31: SP | B31: Base Cabinet | C31: Spice Rack - Pull-Out | D31: x | E31: Does it contains 3 shelves ?
A32: TK | B32: Toe Kick | D32: x
A33: VDB | B33: Bathroom - Base Cabinet | C33: Drawer | D33: -
A34: VS | B34: Bathroom - Base Cabinet | C34: Sink | D34: -
A35: W | B35: Wall Cabinet | C35: Standard | D35: x
A36: WBC | B36: Wall Blind Corner | D36: -
A37: WBCT | B37: Wall Blind Corner Tall | D37: -
A38: WBL | B38: Wall Blind Left | D38: -
A39: WDC | B39: Wall Cabinet | C39: Corner (45deg) | D39: x
A40: WDD | B40: Wall Dummy Door | D40: -
A41: WEP | B41: Wall End Panel | D41: -
A42: WF | B42: Fillers | C42: Base/Wall/Tall Filler | D42: x
A43: WM | B43: Wall Cabinet | C43: Standard (w/ Glass Door) | D43: x
A44: WP | B44: Utility Cabinet | C44: Pantry | D44: x
A45: WPDD | B45: Wall/Pantry Dummy Door | D45: -
A46: 美式铰链 | B46: American Style Hinge | D46: -
